Workbook

Sheet 使用说明
A1: 卖家精灵选产品 → 客户期望驱动的 ASIN 动态评分表
A3: 一、核心原则
A4: 1. 必须先完成「00_客户期望配置」并确认，评分才生效。
A5: 2. 数据源严格限制为卖家精灵「选产品」真实返回字段，禁止虚构任何指标。
A6: 3. 所有权重、阈值、否决线均由客户期望动态驱动，修改后自动重算。
A8: 二、使用步骤
A9: 步骤1：到「00_客户期望配置」填写所有黄色单元格（风险偏好、价格带、毛利率、评分数上限、增长率下限、上架偏好、是否接受自营、四大权重），最后确认「是」。
A10: 步骤2：检查 B25 显示【已完成】。
A11: 步骤3：把卖家精灵选产品导出的 Excel 按「02_ASIN原始数据」表头顺序粘贴（从第3行开始）。注意 unitsGr、profit 保持数字，availableDate 尽量为日期。
A12: 步骤4：查看「04_最终评分」——红色「否决」行为一票否决；S/A/B/C 为推荐等级。
A13: 步骤5：「05_推荐清单」自动过滤出通过且总分≥6 的产品（需 Excel 365/2021+ 支持 FILTER）。
A14: 步骤6：如需调整标准，只需修改「00」的期望值，全表自动刷新。
... A26: • 黄色单元格为输入区（蓝色字体），绿色字体为跨表引用公式，黑色为计算。

Sheet 00_客户期望配置
A1: 客户期望配置（强制门禁）— 必须全部填写并确认后，评分才生效
A2: 数据源限制：仅使用卖家精灵「选产品」真实返回字段，禁止虚构任何指标
A4: 一、客户画像与硬性约束
A5: 风险偏好 | B5: 稳健 | C5: 保守=更严格否决与权重；激进=更看重增长
A6: 期望最低价格（USD） | B6: 20 | C6: 对应 price 字段，低于此价格不得高分
A7: 期望最高价格（USD） | B7: 50 | C7: 对应 price 字段，高于此价格不得高分
A8: 最低预估毛利率要求（%） | B8: 30 | C8: 对应 profit 字段，低于此值直接一票否决
A9: 最高可接受评分数 | B9: 1500 | C9: 对应 ratings 字段，超过此值直接一票否决（准入门槛）
A10: 最低可接受销量增长率（%） | B10: 10 | C10: 对应 unitsGr 字段，低于此值直接一票否决（生命周期）
A11: 上架时间偏好 | B11: 近12个月 | C11: 基于 availableDate 判断是否处于客户接受的窗口
A12: 是否接受亚马逊自营 | B12: 不接受 | C12: fulfillment=AMZ 时是否触发否决
A14: 二、权重分配（总和必须 = 100）
A15: 低竞争权重（%） | B15: 30 | C15: 评分数低 + 卖家数少 + 池内销量排名靠前
A16: 上升生命周期权重（%） | B16: 30 | C16: unitsGr 高 + 上架时间在窗口内
A17: 利润健康权重（%） | B17: 25 | C17: 价格落在期望带 + profit 达标
A18: 准入门槛低权重（%） | B18: 15 | C18: 评分数可控 + 新品窗口 + New Release
A20: 权重总和检查 | B20: =B15+B16+B17+B18 | C20: 必须等于 100，否则评分无效
A22: 三、完成确认
A23: 我已确认以上期望值，并理解评分将严格按此执行 | B23: 是
A25: 完成度检查（门禁） | B25: =IF(AND(B5<>"",B6<>"",B7<>"",B8<>"",B9<>"",B10<>"",B11<>"",B12<>"",B15<>"",B16<>"",B17<>"",B18<>"",B23="是",B20=100),"【已完成】可以进入评分","【未完成】请全部填写并确认，权重总和必须=100")
A27: 使用说明
A28: 1. 黄色单元格为客户必填输入区（蓝色字体）。2. 全部填写并确认后，B25 显示【已完成】。3. 再到 02 粘贴卖家精灵数据，04/05 自动出结果。4. 修改期望后全表自动重算。

Sheet 01_动态参数
A1: 动态参数（全部自动引用 00_客户期望配置，禁止手动修改）
A3: 权重（小数）
A4: 低竞争权重 | B4: ='00_客户期望配置'!B15/100
A5: 上升生命周期权重 | B5: ='00_客户期望配置'!B16/100
A6: 利润健康权重 | B6: ='00_客户期望配置'!B17/100
A7: 准入门槛低权重 | B7: ='00_客户期望配置'!B18/100
A9: 阈值与否决线
A10: 价格下限 | B10: ='00_客户期望配置'!B6
A11: 价格上限 | B11: ='00_客户期望配置'!B7
A12: 毛利率否决线（%） | B12: ='00_客户期望配置'!B8
A13: 评分数否决线 | B13: ='00_客户期望配置'!B9
A14: 增长率否决线（%） | B14: ='00_客户期望配置'!B10
A15: 上架时间偏好（天） | B15: =IF('00_客户期望配置'!B11="近6个月",180,IF('00_客户期望配置'!B11="近12个月",365,9999))
A16: 是否否决自营（1=是） | B16: =IF('00_客户期望配置'!B12="不接受",1,0)
A18: 说明：本表所有值均自动从「00_客户期望配置」拉取，客户修改期望后此处实时更新，驱动后续打分与否决。

Sheet 02_ASIN原始数据
A1: ASIN原始数据（请将卖家精灵「选产品」导出结果按下列字段顺序粘贴，从第2行开始）
A2: asin | B2: title | C2: brand | D2: price | E2: units | F2: unitsGr | G2: revenue | H2: bsr | I2: rating | J2: ratings | K2: ratingsCv | L2: availableDate | M2: fulfillment | N2: profit | O2: fba | P2: sellers | Q2: badge_newRelease | R2: nodeLabelPath
A3: B0SAMPLE001 | B3: Wireless Earbuds Pro Noise Cancelling | C3: TechSound | D3: 39.99 | E3: 1250 | F3: 28.5 | G3: 49987.5 | H3: 1520 | I3: 4.3 | J3: 680 | K3: 45 | L3: 45976 | M3: FBA | N3: 42.5 | O3: 5.8 | P3: 2 | Q3: Y | R3: Electronics:Headphones
A4: B0SAMPLE002 | B4: USB-C Fast Charging Cable 3-Pack | C4: CableKing | D4: 12.99 | E4: 8900 | F4: 5.2 | G4: 115611 | H4: 320 | I4: 4.6 | J4: 15200 | K4: 320 | L4: 44995 | M4: FBA | N4: 55 | O4: 3.2 | P4: 8 | Q4: N | R4: Electronics:Cables
A5: B0SAMPLE003 | B5: Portable Blender for Smoothies | C5: BlendGo | D5: 29.99 | E5: 2100 | F5: 45 | G5: 62979 | H5: 890 | I5: 4.1 | J5: 320 | K5: 28 | L5: 46073 | M5: FBA | N5: 38 | O5: 6.5 | P5: 1 | Q5: Y | R5: Home:Kitchen
A6: B0SAMPLE004 | B6: Ergonomic Office Chair Lumbar Support | C6: SitWell | D6: 189 | E6: 450 | F6: -8.5 | G6: 85050 | H6: 5600 | I6: 4.4 | J6: 2800 | K6: 15 | L6: 45444 | M6: AMZ | N6: 28 | O6: 28 | P6: 1 | Q6: N | R6: Furniture:Office Chairs
A7: B0SAMPLE005 | B7: LED Desk Lamp with Wireless Charger | C7: LightPlus | D7: 45.5 | E7: 980 | F7: 18 | G7: 44590 | H7: 2100 | I7: 4.5 | J7: 950 | K7: 60 | L7: 45874 | M7: FBA | N7: 48 | O7: 7.1 | P7: 3 | Q7: N | R7: Home:Lighting
A54: 注意：availableDate 请尽量转为日期格式；unitsGr 与 profit 请保持为数字（百分比数值，如 15 代表 15%）；badge_newRelease 填 Y/N 或 Yes/No。

Sheet 03_衍生指标
A1: 衍生指标（自动计算，基于 02 与 01）
A2: asin | B2: 上架天数 | C2: 是否在上架窗口 | D2: 价格带匹配 | E2: 毛利率达标 | F2: 评分数超限 | G2: 增长率达标 | H2: 是否自营 | I2: 池内销量排名 | J2: 低竞争原始分 | K2: 生命周期原始分 | L2: 利润健康原始分 | M2: 准入门槛原始分 | N2: 数据行号
A3: ='02_ASIN原始数据'!A3 | B3: =IF('02_ASIN原始数据'!L3="","",IF(ISNUMBER('02_ASIN原始数据'!L3),TODAY()-'02_ASIN原始数据'!L3,"")) | C3: =IF(OR(A3="",B3=""),"",IF(B3<='01_动态参数'!B15,1,0)) | D3: =IF(A3="","",IF(AND('02_ASIN原始数据'!D3>='01_动态参数'!B10,'02_ASIN原始数据'!D3<='01_动态参数'!B11),1,0)) | E3: =IF(A3="","",IF('02_ASIN原始数据'!N3>='01_动态参数'!B12,1,0)) | F3: =IF(A3="","",IF('02_ASIN原始数据'!J3>'01_动态参数'!B13,1,0)) | G3: =IF(A3="","",IF('02_ASIN原始数据'!F3>='01_动态参数'!B14,1,0)) | H3: =IF(A3="","",IF('02_ASIN原始数据'!M3="AMZ",1,0)) | I3: =IF(A3="","",IF('02_ASIN原始数据'!E3="", "",RANK('02_ASIN原始数据'!E3,'02_ASIN原始数据'!$E$3:$E$52,0))) | J3: =IF(A3="","",MIN(10,IF('02_ASIN原始数据'!J3<=300,10,IF('02_ASIN原始数据'!J3<=800,8,IF('02_ASIN原始数据'!J3<=1500,5,IF('02_ASIN原始数据'!J3<=3000,2,0))))+IF('02_ASIN原始数据'!P3<=3,2,0)+IF(I3<=10,1,0))) | K3: =IF(A3="","",MIN(10,IF('02_ASIN原始数据'!F3>=50,10,IF('02_ASIN原始数据'!F3>=30,9,IF('02_ASIN原始数据'!F3>=15,7,IF('02_ASIN原始数据'!F3>=5,5,2))))+IF(C3=1,2,0))) | L3: =IF(A3="","",IF(E3=0,0,IF(D3=1,8,3)+IF('02_ASIN原始数据'!N3>='01_动态参数'!B12+10,2,IF('02_ASIN原始数据'!N3>='01_动态参数'!B12,1,0)))) | M3: =IF(A3="","",MIN(10,IF('02_ASIN原始数据'!J3<=500,10,IF('02_ASIN原始数据'!J3<=1000,7,IF('02_ASIN原始数据'!J3<=2000,4,1)))+IF(C3=1,2,0)+IF(OR('02_ASIN原始数据'!Q3="Y",'02_ASIN原始数据'!Q3="Yes",'02_ASIN原始数据'!Q3="YES"),1,0))) | N3: 3
A4: ='02_ASIN原始数据'!A4 | B4: =IF('02_ASIN原始数据'!L4="","",IF(ISNUMBER('02_ASIN原始数据'!L4),TODAY()-'02_ASIN原始数据'!L4,"")) | C4: =IF(OR(A4="",B4=""),"",IF(B4<='01_动态参数'!B15,1,0)) | D4: =IF(A4="","",IF(AND('02_ASIN原始数据'!D4>='01_动态参数'!B10,'02_ASIN原始数据'!D4<='01_动态参数'!B11),1,0)) | E4: =IF(A4="","",IF('02_ASIN原始数据'!N4>='01_动态参数'!B12,1,0)) | F4: =IF(A4="","",IF('02_ASIN原始数据'!J4>'01_动态参数'!B13,1,0)) | G4: =IF(A4="","",IF('02_ASIN原始数据'!F4>='01_动态参数'!B14,1,0)) | H4: =IF(A4="","",IF('02_ASIN原始数据'!M4="AMZ",1,0)) | I4: =IF(A4="","",IF('02_ASIN原始数据'!E4="", "",RANK('02_ASIN原始数据'!E4,'02_ASIN原始数据'!$E$3:$E$52,0))) | J4: =IF(A4="","",MIN(10,IF('02_ASIN原始数据'!J4<=300,10,IF('02_ASIN原始数据'!J4<=800,8,IF('02_ASIN原始数据'!J4<=1500,5,IF('02_ASIN原始数据'!J4<=3000,2,0))))+IF('02_ASIN原始数据'!P4<=3,2,0)+IF(I4<=10,1,0))) | K4: =IF(A4="","",MIN(10,IF('02_ASIN原始数据'!F4>=50,10,IF('02_ASIN原始数据'!F4>=30,9,IF('02_ASIN原始数据'!F4>=15,7,IF('02_ASIN原始数据'!F4>=5,5,2))))+IF(C4=1,2,0))) | L4: =IF(A4="","",IF(E4=0,0,IF(D4=1,8,3)+IF('02_ASIN原始数据'!N4>='01_动态参数'!B12+10,2,IF('02_ASIN原始数据'!N4>='01_动态参数'!B12,1,0)))) | M4: =IF(A4="","",MIN(10,IF('02_ASIN原始数据'!J4<=500,10,IF('02_ASIN原始数据'!J4<=1000,7,IF('02_ASIN原始数据'!J4<=2000,4,1)))+IF(C4=1,2,0)+IF(OR('02_ASIN原始数据'!Q4="Y",'02_ASIN原始数据'!Q4="Yes",'02_ASIN原始数据'!Q4="YES"),1,0))) | N4: 4
A5: ='02_ASIN原始数据'!A5 | B5: =IF('02_ASIN原始数据'!L5="","",IF(ISNUMBER('02_ASIN原始数据'!L5),TODAY()-'02_ASIN原始数据'!L5,"")) | C5: =IF(OR(A5="",B5=""),"",IF(B5<='01_动态参数'!B15,1,0)) | D5: =IF(A5="","",IF(AND('02_ASIN原始数据'!D5>='01_动态参数'!B10,'02_ASIN原始数据'!D5<='01_动态参数'!B11),1,0)) | E5: =IF(A5="","",IF('02_ASIN原始数据'!N5>='01_动态参数'!B12,1,0)) | F5: =IF(A5="","",IF('02_ASIN原始数据'!J5>'01_动态参数'!B13,1,0)) | G5: =IF(A5="","",IF('02_ASIN原始数据'!F5>='01_动态参数'!B14,1,0)) | H5: =IF(A5="","",IF('02_ASIN原始数据'!M5="AMZ",1,0)) | I5: =IF(A5="","",IF('02_ASIN原始数据'!E5="", "",RANK('02_ASIN原始数据'!E5,'02_ASIN原始数据'!$E$3:$E$52,0))) | J5: =IF(A5="","",MIN(10,IF('02_ASIN原始数据'!J5<=300,10,IF('02_ASIN原始数据'!J5<=800,8,IF('02_ASIN原始数据'!J5<=1500,5,IF('02_ASIN原始数据'!J5<=3000,2,0))))+IF('02_ASIN原始数据'!P5<=3,2,0)+IF(I5<=10,1,0))) | K5: =IF(A5="","",MIN(10,IF('02_ASIN原始数据'!F5>=50,10,IF('02_ASIN原始数据'!F5>=30,9,IF('02_ASIN原始数据'!F5>=15,7,IF('02_ASIN原始数据'!F5>=5,5,2))))+IF(C5=1,2,0))) | L5: =IF(A5="","",IF(E5=0,0,IF(D5=1,8,3)+IF('02_ASIN原始数据'!N5>='01_动态参数'!B12+10,2,IF('02_ASIN原始数据'!N5>='01_动态参数'!B12,1,0)))) | M5: =IF(A5="","",MIN(10,IF('02_ASIN原始数据'!J5<=500,10,IF('02_ASIN原始数据'!J5<=1000,7,IF('02_ASIN原始数据'!J5<=2000,4,1)))+IF(C5=1,2,0)+IF(OR('02_ASIN原始数据'!Q5="Y",'02_ASIN原始数据'!Q5="Yes",'02_ASIN原始数据'!Q5="YES"),1,0))) | N5: 5
A6: ='02_ASIN原始数据'!A6 | B6: =IF('02_ASIN原始数据'!L6="","",IF(ISNUMBER('02_ASIN原始数据'!L6),TODAY()-'02_ASIN原始数据'!L6,"")) | C6: =IF(OR(A6="",B6=""),"",IF(B6<='01_动态参数'!B15,1,0)) | D6: =IF(A6="","",IF(AND('02_ASIN原始数据'!D6>='01_动态参数'!B10,'02_ASIN原始数据'!D6<='01_动态参数'!B11),1,0)) | E6: =IF(A6="","",IF('02_ASIN原始数据'!N6>='01_动态参数'!B12,1,0)) | F6: =IF(A6="","",IF('02_ASIN原始数据'!J6>'01_动态参数'!B13,1,0)) | G6: =IF(A6="","",IF('02_ASIN原始数据'!F6>='01_动态参数'!B14,1,0)) | H6: =IF(A6="","",IF('02_ASIN原始数据'!M6="AMZ",1,0)) | I6: =IF(A6="","",IF('02_ASIN原始数据'!E6="", "",RANK('02_ASIN原始数据'!E6,'02_ASIN原始数据'!$E$3:$E$52,0))) | J6: =IF(A6="","",MIN(10,IF('02_ASIN原始数据'!J6<=300,10,IF('02_ASIN原始数据'!J6<=800,8,IF('02_ASIN原始数据'!J6<=1500,5,IF('02_ASIN原始数据'!J6<=3000,2,0))))+IF('02_ASIN原始数据'!P6<=3,2,0)+IF(I6<=10,1,0))) | K6: =IF(A6="","",MIN(10,IF('02_ASIN原始数据'!F6>=50,10,IF('02_ASIN原始数据'!F6>=30,9,IF('02_ASIN原始数据'!F6>=15,7,IF('02_ASIN原始数据'!F6>=5,5,2))))+IF(C6=1,2,0))) | L6: =IF(A6="","",IF(E6=0,0,IF(D6=1,8,3)+IF('02_ASIN原始数据'!N6>='01_动态参数'!B12+10,2,IF('02_ASIN原始数据'!N6>='01_动态参数'!B12,1,0)))) | M6: =IF(A6="","",MIN(10,IF('02_ASIN原始数据'!J6<=500,10,IF('02_ASIN原始数据'!J6<=1000,7,IF('02_ASIN原始数据'!J6<=2000,4,1)))+IF(C6=1,2,0)+IF(OR('02_ASIN原始数据'!Q6="Y",'02_ASIN原始数据'!Q6="Yes",'02_ASIN原始数据'!Q6="YES"),1,0))) | N6: 6
A7: ='02_ASIN原始数据'!A7 | B7: =IF('02_ASIN原始数据'!L7="","",IF(ISNUMBER('02_ASIN原始数据'!L7),TODAY()-'02_ASIN原始数据'!L7,"")) | C7: =IF(OR(A7="",B7=""),"",IF(B7<='01_动态参数'!B15,1,0)) | D7: =IF(A7="","",IF(AND('02_ASIN原始数据'!D7>='01_动态参数'!B10,'02_ASIN原始数据'!D7<='01_动态参数'!B11),1,0)) | E7: =IF(A7="","",IF('02_ASIN原始数据'!N7>='01_动态参数'!B12,1,0)) | F7: =IF(A7="","",IF('02_ASIN原始数据'!J7>'01_动态参数'!B13,1,0)) | G7: =IF(A7="","",IF('02_ASIN原始数据'!F7>='01_动态参数'!B14,1,0)) | H7: =IF(A7="","",IF('02_ASIN原始数据'!M7="AMZ",1,0)) | I7: =IF(A7="","",IF('02_ASIN原始数据'!E7="", "",RANK('02_ASIN原始数据'!E7,'02_ASIN原始数据'!$E$3:$E$52,0))) | J7: =IF(A7="","",MIN(10,IF('02_ASIN原始数据'!J7<=300,10,IF('02_ASIN原始数据'!J7<=800,8,IF('02_ASIN原始数据'!J7<=1500,5,IF('02_ASIN原始数据'!J7<=3000,2,0))))+IF('02_ASIN原始数据'!P7<=3,2,0)+IF(I7<=10,1,0))) | K7: =IF(A7="","",MIN(10,IF('02_ASIN原始数据'!F7>=50,10,IF('02_ASIN原始数据'!F7>=30,9,IF('02_ASIN原始数据'!F7>=15,7,IF('02_ASIN原始数据'!F7>=5,5,2))))+IF(C7=1,2,0))) | L7: =IF(A7="","",IF(E7=0,0,IF(D7=1,8,3)+IF('02_ASIN原始数据'!N7>='01_动态参数'!B12+10,2,IF('02_ASIN原始数据'!N7>='01_动态参数'!B12,1,0)))) | M7: =IF(A7="","",MIN(10,IF('02_ASIN原始数据'!J7<=500,10,IF('02_ASIN原始数据'!J7<=1000,7,IF('02_ASIN原始数据'!J7<=2000,4,1)))+IF(C7=1,2,0)+IF(OR('02_ASIN原始数据'!Q7="Y",'02_ASIN原始数据'!Q7="Yes",'02_ASIN原始数据'!Q7="YES"),1,0))) | N7: 7
A8: ='02_ASIN原始数据'!A8 | B8: =IF('02_ASIN原始数据'!L8="","",IF(ISNUMBER('02_ASIN原始数据'!L8),TODAY()-'02_ASIN原始数据'!L8,"")) | C8: =IF(OR(A8="",B8=""),"",IF(B8<='01_动态参数'!B15,1,0)) | D8: =IF(A8="","",IF(AND('02_ASIN原始数据'!D8>='01_动态参数'!B10,'02_ASIN原始数据'!D8<='01_动态参数'!B11),1,0)) | E8: =IF(A8="","",IF('02_ASIN原始数据'!N8>='01_动态参数'!B12,1,0)) | F8: =IF(A8="","",IF('02_ASIN原始数据'!J8>'01_动态参数'!B13,1,0)) | G8: =IF(A8="","",IF('02_ASIN原始数据'!F8>='01_动态参数'!B14,1,0)) | H8: =IF(A8="","",IF('02_ASIN原始数据'!M8="AMZ",1,0)) | I8: =IF(A8="","",IF('02_ASIN原始数据'!E8="", "",RANK('02_ASIN原始数据'!E8,'02_ASIN原始数据'!$E$3:$E$52,0))) | J8: =IF(A8="","",MIN(10,IF('02_ASIN原始数据'!J8<=300,10,IF('02_ASIN原始数据'!J8<=800,8,IF('02_ASIN原始数据'!J8<=1500,5,IF('02_ASIN原始数据'!J8<=3000,2,0))))+IF('02_ASIN原始数据'!P8<=3,2,0)+IF(I8<=10,1,0))) | K8: =IF(A8="","",MIN(10,IF('02_ASIN原始数据'!F8>=50,10,IF('02_ASIN原始数据'!F8>=30,9,IF('02_ASIN原始数据'!F8>=15,7,IF('02_ASIN原始数据'!F8>=5,5,2))))+IF(C8=1,2,0))) | L8: =IF(A8="","",IF(E8=0,0,IF(D8=1,8,3)+IF('02_ASIN原始数据'!N8>='01_动态参数'!B12+10,2,IF('02_ASIN原始数据'!N8>='01_动态参数'!B12,1,0)))) | M8: =IF(A8="","",MIN(10,IF('02_ASIN原始数据'!J8<=500,10,IF('02_ASIN原始数据'!J8<=1000,7,IF('02_ASIN原始数据'!J8<=2000,4,1)))+IF(C8=1,2,0)+IF(OR('02_ASIN原始数据'!Q8="Y",'02_ASIN原始数据'!Q8="Yes",'02_ASIN原始数据'!Q8="YES"),1,0))) | N8: 8
A9: ='02_ASIN原始数据'!A9 | B9: =IF('02_ASIN原始数据'!L9="","",IF(ISNUMBER('02_ASIN原始数据'!L9),TODAY()-'02_ASIN原始数据'!L9,"")) | C9: =IF(OR(A9="",B9=""),"",IF(B9<='01_动态参数'!B15,1,0)) | D9: =IF(A9="","",IF(AND('02_ASIN原始数据'!D9>='01_动态参数'!B10,'02_ASIN原始数据'!D9<='01_动态参数'!B11),1,0)) | E9: =IF(A9="","",IF('02_ASIN原始数据'!N9>='01_动态参数'!B12,1,0)) | F9: =IF(A9="","",IF('02_ASIN原始数据'!J9>'01_动态参数'!B13,1,0)) | G9: =IF(A9="","",IF('02_ASIN原始数据'!F9>='01_动态参数'!B14,1,0)) | H9: =IF(A9="","",IF('02_ASIN原始数据'!M9="AMZ",1,0)) | I9: =IF(A9="","",IF('02_ASIN原始数据'!E9="", "",RANK('02_ASIN原始数据'!E9,'02_ASIN原始数据'!$E$3:$E$52,0))) | J9: =IF(A9="","",MIN(10,IF('02_ASIN原始数据'!J9<=300,10,IF('02_ASIN原始数据'!J9<=800,8,IF('02_ASIN原始数据'!J9<=1500,5,IF('02_ASIN原始数据'!J9<=3000,2,0))))+IF('02_ASIN原始数据'!P9<=3,2,0)+IF(I9<=10,1,0))) | K9: =IF(A9="","",MIN(10,IF('02_ASIN原始数据'!F9>=50,10,IF('02_ASIN原始数据'!F9>=30,9,IF('02_ASIN原始数据'!F9>=15,7,IF('02_ASIN原始数据'!F9>=5,5,2))))+IF(C9=1,2,0))) | L9: =IF(A9="","",IF(E9=0,0,IF(D9=1,8,3)+IF('02_ASIN原始数据'!N9>='01_动态参数'!B12+10,2,IF('02_ASIN原始数据'!N9>='01_动态参数'!B12,1,0)))) | M9: =IF(A9="","",MIN(10,IF('02_ASIN原始数据'!J9<=500,10,IF('02_ASIN原始数据'!J9<=1000,7,IF('02_ASIN原始数据'!J9<=2000,4,1)))+IF(C9=1,2,0)+IF(OR('02_ASIN原始数据'!Q9="Y",'02_ASIN原始数据'!Q9="Yes",'02_ASIN原始数据'!Q9="YES"),1,0))) | N9: 9
A10: ='02_ASIN原始数据'!A10 | B10: =IF('02_ASIN原始数据'!L10="","",IF(ISNUMBER('02_ASIN原始数据'!L10),TODAY()-'02_ASIN原始数据'!L10,"")) | C10: =IF(OR(A10="",B10=""),"",IF(B10<='01_动态参数'!B15,1,0)) | D10: =IF(A10="","",IF(AND('02_ASIN原始数据'!D10>='01_动态参数'!B10,'02_ASIN原始数据'!D10<='01_动态参数'!B11),1,0)) | E10: =IF(A10="","",IF('02_ASIN原始数据'!N10>='01_动态参数'!B12,1,0)) | F10: =IF(A10="","",IF('02_ASIN原始数据'!J10>'01_动态参数'!B13,1,0)) | G10: =IF(A10="","",IF('02_ASIN原始数据'!F10>='01_动态参数'!B14,1,0)) | H10: =IF(A10="","",IF('02_ASIN原始数据'!M10="AMZ",1,0)) | I10: =IF(A10="","",IF('02_ASIN原始数据'!E10="", "",RANK('02_ASIN原始数据'!E10,'02_ASIN原始数据'!$E$3:$E$52,0))) | J10: =IF(A10="","",MIN(10,IF('02_ASIN原始数据'!J10<=300,10,IF('02_ASIN原始数据'!J10<=800,8,IF('02_ASIN原始数据'!J10<=1500,5,IF('02_ASIN原始数据'!J10<=3000,2,0))))+IF('02_ASIN原始数据'!P10<=3,2,0)+IF(I10<=10,1,0))) | K10: =IF(A10="","",MIN(10,IF('02_ASIN原始数据'!F10>=50,10,IF('02_ASIN原始数据'!F10>=30,9,IF('02_ASIN原始数据'!F10>=15,7,IF('02_ASIN原始数据'!F10>=5,5,2))))+IF(C10=1,2,0))) | L10: =IF(A10="","",IF(E10=0,0,IF(D10=1,8,3)+IF('02_ASIN原始数据'!N10>='01_动态参数'!B12+10,2,IF('02_ASIN原始数据'!N10>='01_动态参数'!B12,1,0)))) | M10: =IF(A10="","",MIN(10,IF('02_ASIN原始数据'!J10<=500,10,IF('02_ASIN原始数据'!J10<=1000,7,IF('02_ASIN原始数据'!J10<=2000,4,1)))+IF(C10=1,2,0)+IF(OR('02_ASIN原始数据'!Q10="Y",'02_ASIN原始数据'!Q10="Yes",'02_ASIN原始数据'!Q10="YES"),1,0))) | N10: 10
A11: ='02_ASIN原始数据'!A11 | B11: =IF('02_ASIN原始数据'!L11="","",IF(ISNUMBER('02_ASIN原始数据'!L11),TODAY()-'02_ASIN原始数据'!L11,"")) | C11: =IF(OR(A11="",B11=""),"",IF(B11<='01_动态参数'!B15,1,0)) | D11: =IF(A11="","",IF(AND('02_ASIN原始数据'!D11>='01_动态参数'!B10,'02_ASIN原始数据'!D11<='01_动态参数'!B11),1,0)) | E11: =IF(A11="","",IF('02_ASIN原始数据'!N11>='01_动态参数'!B12,1,0)) | F11: =IF(A11="","",IF('02_ASIN原始数据'!J11>'01_动态参数'!B13,1,0)) | G11: =IF(A11="","",IF('02_ASIN原始数据'!F11>='01_动态参数'!B14,1,0)) | H11: =IF(A11="","",IF('02_ASIN原始数据'!M11="AMZ",1,0)) | I11: =IF(A11="","",IF('02_ASIN原始数据'!E11="", "",RANK('02_ASIN原始数据'!E11,'02_ASIN原始数据'!$E$3:$E$52,0))) | J11: =IF(A11="","",MIN(10,IF('02_ASIN原始数据'!J11<=300,10,IF('02_ASIN原始数据'!J11<=800,8,IF('02_ASIN原始数据'!J11<=1500,5,IF('02_ASIN原始数据'!J11<=3000,2,0))))+IF('02_ASIN原始数据'!P11<=3,2,0)+IF(I11<=10,1,0))) | K11: =IF(A11="","",MIN(10,IF('02_ASIN原始数据'!F11>=50,10,IF('02_ASIN原始数据'!F11>=30,9,IF('02_ASIN原始数据'!F11>=15,7,IF('02_ASIN原始数据'!F11>=5,5,2))))+IF(C11=1,2,0))) | L11: =IF(A11="","",IF(E11=0,0,IF(D11=1,8,3)+IF('02_ASIN原始数据'!N11>='01_动态参数'!B12+10,2,IF('02_ASIN原始数据'!N11>='01_动态参数'!B12,1,0)))) | M11: =IF(A11="","",MIN(10,IF('02_ASIN原始数据'!J11<=500,10,IF('02_ASIN原始数据'!J11<=1000,7,IF('02_ASIN原始数据'!J11<=2000,4,1)))+IF(C11=1,2,0)+IF(OR('02_ASIN原始数据'!Q11="Y",'02_ASIN原始数据'!Q11="Yes",'02_ASIN原始数据'!Q11="YES"),1,0))) | N11: 11
A12: ='02_ASIN原始数据'!A12 | B12: =IF('02_ASIN原始数据'!L12="","",IF(ISNUMBER('02_ASIN原始数据'!L12),TODAY()-'02_ASIN原始数据'!L12,"")) | C12: =IF(OR(A12="",B12=""),"",IF(B12<='01_动态参数'!B15,1,0)) | D12: =IF(A12="","",IF(AND('02_ASIN原始数据'!D12>='01_动态参数'!B10,'02_ASIN原始数据'!D12<='01_动态参数'!B11),1,0)) | E12: =IF(A12="","",IF('02_ASIN原始数据'!N12>='01_动态参数'!B12,1,0)) | F12: =IF(A12="","",IF('02_ASIN原始数据'!J12>'01_动态参数'!B13,1,0)) | G12: =IF(A12="","",IF('02_ASIN原始数据'!F12>='01_动态参数'!B14,1,0)) | H12: =IF(A12="","",IF('02_ASIN原始数据'!M12="AMZ",1,0)) | I12: =IF(A12="","",IF('02_ASIN原始数据'!E12="", "",RANK('02_ASIN原始数据'!E12,'02_ASIN原始数据'!$E$3:$E$52,0))) | J12: =IF(A12="","",MIN(10,IF('02_ASIN原始数据'!J12<=300,10,IF('02_ASIN原始数据'!J12<=800,8,IF('02_ASIN原始数据'!J12<=1500,5,IF('02_ASIN原始数据'!J12<=3000,2,0))))+IF('02_ASIN原始数据'!P12<=3,2,0)+IF(I12<=10,1,0))) | K12: =IF(A12="","",MIN(10,IF('02_ASIN原始数据'!F12>=50,10,IF('02_ASIN原始数据'!F12>=30,9,IF('02_ASIN原始数据'!F12>=15,7,IF('02_ASIN原始数据'!F12>=5,5,2))))+IF(C12=1,2,0))) | L12: =IF(A12="","",IF(E12=0,0,IF(D12=1,8,3)+IF('02_ASIN原始数据'!N12>='01_动态参数'!B12+10,2,IF('02_ASIN原始数据'!N12>='01_动态参数'!B12,1,0)))) | M12: =IF(A12="","",MIN(10,IF('02_ASIN原始数据'!J12<=500,10,IF('02_ASIN原始数据'!J12<=1000,7,IF('02_ASIN原始数据'!J12<=2000,4,1)))+IF(C12=1,2,0)+IF(OR('02_ASIN原始数据'!Q12="Y",'02_ASIN原始数据'!Q12="Yes",'02_ASIN原始数据'!Q12="YES"),1,0))) | N12: 12
A13: ='02_ASIN原始数据'!A13 | B13: =IF('02_ASIN原始数据'!L13="","",IF(ISNUMBER('02_ASIN原始数据'!L13),TODAY()-'02_ASIN原始数据'!L13,"")) | C13: =IF(OR(A13="",B13=""),"",IF(B13<='01_动态参数'!B15,1,0)) | D13: =IF(A13="","",IF(AND('02_ASIN原始数据'!D13>='01_动态参数'!B10,'02_ASIN原始数据'!D13<='01_动态参数'!B11),1,0)) | E13: =IF(A13="","",IF('02_ASIN原始数据'!N13>='01_动态参数'!B12,1,0)) | F13: =IF(A13="","",IF('02_ASIN原始数据'!J13>'01_动态参数'!B13,1,0)) | G13: =IF(A13="","",IF('02_ASIN原始数据'!F13>='01_动态参数'!B14,1,0)) | H13: =IF(A13="","",IF('02_ASIN原始数据'!M13="AMZ",1,0)) | I13: =IF(A13="","",IF('02_ASIN原始数据'!E13="", "",RANK('02_ASIN原始数据'!E13,'02_ASIN原始数据'!$E$3:$E$52,0))) | J13: =IF(A13="","",MIN(10,IF('02_ASIN原始数据'!J13<=300,10,IF('02_ASIN原始数据'!J13<=800,8,IF('02_ASIN原始数据'!J13<=1500,5,IF('02_ASIN原始数据'!J13<=3000,2,0))))+IF('02_ASIN原始数据'!P13<=3,2,0)+IF(I13<=10,1,0))) | K13: =IF(A13="","",MIN(10,IF('02_ASIN原始数据'!F13>=50,10,IF('02_ASIN原始数据'!F13>=30,9,IF('02_ASIN原始数据'!F13>=15,7,IF('02_ASIN原始数据'!F13>=5,5,2))))+IF(C13=1,2,0))) | L13: =IF(A13="","",IF(E13=0,0,IF(D13=1,8,3)+IF('02_ASIN原始数据'!N13>='01_动态参数'!B12+10,2,IF('02_ASIN原始数据'!N13>='01_动态参数'!B12,1,0)))) | M13: =IF(A13="","",MIN(10,IF('02_ASIN原始数据'!J13<=500,10,IF('02_ASIN原始数据'!J13<=1000,7,IF('02_ASIN原始数据'!J13<=2000,4,1)))+IF(C13=1,2,0)+IF(OR('02_ASIN原始数据'!Q13="Y",'02_ASIN原始数据'!Q13="Yes",'02_ASIN原始数据'!Q13="YES"),1,0))) | N13: 13
A14: ='02_ASIN原始数据'!A14 | B14: =IF('02_ASIN原始数据'!L14="","",IF(ISNUMBER('02_ASIN原始数据'!L14),TODAY()-'02_ASIN原始数据'!L14,"")) | C14: =IF(OR(A14="",B14=""),"",IF(B14<='01_动态参数'!B15,1,0)) | D14: =IF(A14="","",IF(AND('02_ASIN原始数据'!D14>='01_动态参数'!B10,'02_ASIN原始数据'!D14<='01_动态参数'!B11),1,0)) | E14: =IF(A14="","",IF('02_ASIN原始数据'!N14>='01_动态参数'!B12,1,0)) | F14: =IF(A14="","",IF('02_ASIN原始数据'!J14>'01_动态参数'!B13,1,0)) | G14: =IF(A14="","",IF('02_ASIN原始数据'!F14>='01_动态参数'!B14,1,0)) | H14: =IF(A14="","",IF('02_ASIN原始数据'!M14="AMZ",1,0)) | I14: =IF(A14="","",IF('02_ASIN原始数据'!E14="", "",RANK('02_ASIN原始数据'!E14,'02_ASIN原始数据'!$E$3:$E$52,0))) | J14: =IF(A14="","",MIN(10,IF('02_ASIN原始数据'!J14<=300,10,IF('02_ASIN原始数据'!J14<=800,8,IF('02_ASIN原始数据'!J14<=1500,5,IF('02_ASIN原始数据'!J14<=3000,2,0))))+IF('02_ASIN原始数据'!P14<=3,2,0)+IF(I14<=10,1,0))) | K14: =IF(A14="","",MIN(10,IF('02_ASIN原始数据'!F14>=50,10,IF('02_ASIN原始数据'!F14>=30,9,IF('02_ASIN原始数据'!F14>=15,7,IF('02_ASIN原始数据'!F14>=5,5,2))))+IF(C14=1,2,0))) | L14: =IF(A14="","",IF(E14=0,0,IF(D14=1,8,3)+IF('02_ASIN原始数据'!N14>='01_动态参数'!B12+10,2,IF('02_ASIN原始数据'!N14>='01_动态参数'!B12,1,0)))) | M14: =IF(A14="","",MIN(10,IF('02_ASIN原始数据'!J14<=500,10,IF('02_ASIN原始数据'!J14<=1000,7,IF('02_ASIN原始数据'!J14<=2000,4,1)))+IF(C14=1,2,0)+IF(OR('02_ASIN原始数据'!Q14="Y",'02_ASIN原始数据'!Q14="Yes",'02_ASIN原始数据'!Q14="YES"),1,0))) | N14: 14
A15: ='02_ASIN原始数据'!A15 | B15: =IF('02_ASIN原始数据'!L15="","",IF(ISNUMBER('02_ASIN原始数据'!L15),TODAY()-'02_ASIN原始数据'!L15,"")) | C15: =IF(OR(A15="",B15=""),"",IF(B15<='01_动态参数'!B15,1,0)) | D15: =IF(A15="","",IF(AND('02_ASIN原始数据'!D15>='01_动态参数'!B10,'02_ASIN原始数据'!D15<='01_动态参数'!B11),1,0)) | E15: =IF(A15="","",IF('02_ASIN原始数据'!N15>='01_动态参数'!B12,1,0)) | F15: =IF(A15="","",IF('02_ASIN原始数据'!J15>'01_动态参数'!B13,1,0)) | G15: =IF(A15="","",IF('02_ASIN原始数据'!F15>='01_动态参数'!B14,1,0)) | H15: =IF(A15="","",IF('02_ASIN原始数据'!M15="AMZ",1,0)) | I15: =IF(A15="","",IF('02_ASIN原始数据'!E15="", "",RANK('02_ASIN原始数据'!E15,'02_ASIN原始数据'!$E$3:$E$52,0))) | J15: =IF(A15="","",MIN(10,IF('02_ASIN原始数据'!J15<=300,10,IF('02_ASIN原始数据'!J15<=800,8,IF('02_ASIN原始数据'!J15<=1500,5,IF('02_ASIN原始数据'!J15<=3000,2,0))))+IF('02_ASIN原始数据'!P15<=3,2,0)+IF(I15<=10,1,0))) | K15: =IF(A15="","",MIN(10,IF('02_ASIN原始数据'!F15>=50,10,IF('02_ASIN原始数据'!F15>=30,9,IF('02_ASIN原始数据'!F15>=15,7,IF('02_ASIN原始数据'!F15>=5,5,2))))+IF(C15=1,2,0))) | L15: =IF(A15="","",IF(E15=0,0,IF(D15=1,8,3)+IF('02_ASIN原始数据'!N15>='01_动态参数'!B12+10,2,IF('02_ASIN原始数据'!N15>='01_动态参数'!B12,1,0)))) | M15: =IF(A15="","",MIN(10,IF('02_ASIN原始数据'!J15<=500,10,IF('02_ASIN原始数据'!J15<=1000,7,IF('02_ASIN原始数据'!J15<=2000,4,1)))+IF(C15=1,2,0)+IF(OR('02_ASIN原始数据'!Q15="Y",'02_ASIN原始数据'!Q15="Yes",'02_ASIN原始数据'!Q15="YES"),1,0))) | N15: 15
A16: ='02_ASIN原始数据'!A16 | B16: =IF('02_ASIN原始数据'!L16="","",IF(ISNUMBER('02_ASIN原始数据'!L16),TODAY()-'02_ASIN原始数据'!L16,"")) | C16: =IF(OR(A16="",B16=""),"",IF(B16<='01_动态参数'!B15,1,0)) | D16: =IF(A16="","",IF(AND('02_ASIN原始数据'!D16>='01_动态参数'!B10,'02_ASIN原始数据'!D16<='01_动态参数'!B11),1,0)) | E16: =IF(A16="","",IF('02_ASIN原始数据'!N16>='01_动态参数'!B12,1,0)) | F16: =IF(A16="","",IF('02_ASIN原始数据'!J16>'01_动态参数'!B13,1,0)) | G16: =IF(A16="","",IF('02_ASIN原始数据'!F16>='01_动态参数'!B14,1,0)) | H16: =IF(A16="","",IF('02_ASIN原始数据'!M16="AMZ",1,0)) | I16: =IF(A16="","",IF('02_ASIN原始数据'!E16="", "",RANK('02_ASIN原始数据'!E16,'02_ASIN原始数据'!$E$3:$E$52,0))) | J16: =IF(A16="","",MIN(10,IF('02_ASIN原始数据'!J16<=300,10,IF('02_ASIN原始数据'!J16<=800,8,IF('02_ASIN原始数据'!J16<=1500,5,IF('02_ASIN原始数据'!J16<=3000,2,0))))+IF('02_ASIN原始数据'!P16<=3,2,0)+IF(I16<=10,1,0))) | K16: =IF(A16="","",MIN(10,IF('02_ASIN原始数据'!F16>=50,10,IF('02_ASIN原始数据'!F16>=30,9,IF('02_ASIN原始数据'!F16>=15,7,IF('02_ASIN原始数据'!F16>=5,5,2))))+IF(C16=1,2,0))) | L16: =IF(A16="","",IF(E16=0,0,IF(D16=1,8,3)+IF('02_ASIN原始数据'!N16>='01_动态参数'!B12+10,2,IF('02_ASIN原始数据'!N16>='01_动态参数'!B12,1,0)))) | M16: =IF(A16="","",MIN(10,IF('02_ASIN原始数据'!J16<=500,10,IF('02_ASIN原始数据'!J16<=1000,7,IF('02_ASIN原始数据'!J16<=2000,4,1)))+IF(C16=1,2,0)+IF(OR('02_ASIN原始数据'!Q16="Y",'02_ASIN原始数据'!Q16="Yes",'02_ASIN原始数据'!Q16="YES"),1,0))) | N16: 16
A17: ='02_ASIN原始数据'!A17 | B17: =IF('02_ASIN原始数据'!L17="","",IF(ISNUMBER('02_ASIN原始数据'!L17),TODAY()-'02_ASIN原始数据'!L17,"")) | C17: =IF(OR(A17="",B17=""),"",IF(B17<='01_动态参数'!B15,1,0)) | D17: =IF(A17="","",IF(AND('02_ASIN原始数据'!D17>='01_动态参数'!B10,'02_ASIN原始数据'!D17<='01_动态参数'!B11),1,0)) | E17: =IF(A17="","",IF('02_ASIN原始数据'!N17>='01_动态参数'!B12,1,0)) | F17: =IF(A17="","",IF('02_ASIN原始数据'!J17>'01_动态参数'!B13,1,0)) | G17: =IF(A17="","",IF('02_ASIN原始数据'!F17>='01_动态参数'!B14,1,0)) | H17: =IF(A17="","",IF('02_ASIN原始数据'!M17="AMZ",1,0)) | I17: =IF(A17="","",IF('02_ASIN原始数据'!E17="", "",RANK('02_ASIN原始数据'!E17,'02_ASIN原始数据'!$E$3:$E$52,0))) | J17: =IF(A17="","",MIN(10,IF('02_ASIN原始数据'!J17<=300,10,IF('02_ASIN原始数据'!J17<=800,8,IF('02_ASIN原始数据'!J17<=1500,5,IF('02_ASIN原始数据'!J17<=3000,2,0))))+IF('02_ASIN原始数据'!P17<=3,2,0)+IF(I17<=10,1,0))) | K17: =IF(A17="","",MIN(10,IF('02_ASIN原始数据'!F17>=50,10,IF('02_ASIN原始数据'!F17>=30,9,IF('02_ASIN原始数据'!F17>=15,7,IF('02_ASIN原始数据'!F17>=5,5,2))))+IF(C17=1,2,0))) | L17: =IF(A17="","",IF(E17=0,0,IF(D17=1,8,3)+IF('02_ASIN原始数据'!N17>='01_动态参数'!B12+10,2,IF('02_ASIN原始数据'!N17>='01_动态参数'!B12,1,0)))) | M17: =IF(A17="","",MIN(10,IF('02_ASIN原始数据'!J17<=500,10,IF('02_ASIN原始数据'!J17<=1000,7,IF('02_ASIN原始数据'!J17<=2000,4,1)))+IF(C17=1,2,0)+IF(OR('02_ASIN原始数据'!Q17="Y",'02_ASIN原始数据'!Q17="Yes",'02_ASIN原始数据'!Q17="YES"),1,0))) | N17: 17
A18: ='02_ASIN原始数据'!A18 | B18: =IF('02_ASIN原始数据'!L18="","",IF(ISNUMBER('02_ASIN原始数据'!L18),TODAY()-'02_ASIN原始数据'!L18,"")) | C18: =IF(OR(A18="",B18=""),"",IF(B18<='01_动态参数'!B15,1,0)) | D18: =IF(A18="","",IF(AND('02_ASIN原始数据'!D18>='01_动态参数'!B10,'02_ASIN原始数据'!D18<='01_动态参数'!B11),1,0)) | E18: =IF(A18="","",IF('02_ASIN原始数据'!N18>='01_动态参数'!B12,1,0)) | F18: =IF(A18="","",IF('02_ASIN原始数据'!J18>'01_动态参数'!B13,1,0)) | G18: =IF(A18="","",IF('02_ASIN原始数据'!F18>='01_动态参数'!B14,1,0)) | H18: =IF(A18="","",IF('02_ASIN原始数据'!M18="AMZ",1,0)) | I18: =IF(A18="","",IF('02_ASIN原始数据'!E18="", "",RANK('02_ASIN原始数据'!E18,'02_ASIN原始数据'!$E$3:$E$52,0))) | J18: =IF(A18="","",MIN(10,IF('02_ASIN原始数据'!J18<=300,10,IF('02_ASIN原始数据'!J18<=800,8,IF('02_ASIN原始数据'!J18<=1500,5,IF('02_ASIN原始数据'!J18<=3000,2,0))))+IF('02_ASIN原始数据'!P18<=3,2,0)+IF(I18<=10,1,0))) | K18: =IF(A18="","",MIN(10,IF('02_ASIN原始数据'!F18>=50,10,IF('02_ASIN原始数据'!F18>=30,9,IF('02_ASIN原始数据'!F18>=15,7,IF('02_ASIN原始数据'!F18>=5,5,2))))+IF(C18=1,2,0))) | L18: =IF(A18="","",IF(E18=0,0,IF(D18=1,8,3)+IF('02_ASIN原始数据'!N18>='01_动态参数'!B12+10,2,IF('02_ASIN原始数据'!N18>='01_动态参数'!B12,1,0)))) | M18: =IF(A18="","",MIN(10,IF('02_ASIN原始数据'!J18<=500,10,IF('02_ASIN原始数据'!J18<=1000,7,IF('02_ASIN原始数据'!J18<=2000,4,1)))+IF(C18=1,2,0)+IF(OR('02_ASIN原始数据'!Q18="Y",'02_ASIN原始数据'!Q18="Yes",'02_ASIN原始数据'!Q18="YES"),1,0))) | N18: 18
A19: ='02_ASIN原始数据'!A19 | B19: =IF('02_ASIN原始数据'!L19="","",IF(ISNUMBER('02_ASIN原始数据'!L19),TODAY()-'02_ASIN原始数据'!L19,"")) | C19: =IF(OR(A19="",B19=""),"",IF(B19<='01_动态参数'!B15,1,0)) | D19: =IF(A19="","",IF(AND('02_ASIN原始数据'!D19>='01_动态参数'!B10,'02_ASIN原始数据'!D19<='01_动态参数'!B11),1,0)) | E19: =IF(A19="","",IF('02_ASIN原始数据'!N19>='01_动态参数'!B12,1,0)) | F19: =IF(A19="","",IF('02_ASIN原始数据'!J19>'01_动态参数'!B13,1,0)) | G19: =IF(A19="","",IF('02_ASIN原始数据'!F19>='01_动态参数'!B14,1,0)) | H19: =IF(A19="","",IF('02_ASIN原始数据'!M19="AMZ",1,0)) | I19: =IF(A19="","",IF('02_ASIN原始数据'!E19="", "",RANK('02_ASIN原始数据'!E19,'02_ASIN原始数据'!$E$3:$E$52,0))) | J19: =IF(A19="","",MIN(10,IF('02_ASIN原始数据'!J19<=300,10,IF('02_ASIN原始数据'!J19<=800,8,IF('02_ASIN原始数据'!J19<=1500,5,IF('02_ASIN原始数据'!J19<=3000,2,0))))+IF('02_ASIN原始数据'!P19<=3,2,0)+IF(I19<=10,1,0))) | K19: =IF(A19="","",MIN(10,IF('02_ASIN原始数据'!F19>=50,10,IF('02_ASIN原始数据'!F19>=30,9,IF('02_ASIN原始数据'!F19>=15,7,IF('02_ASIN原始数据'!F19>=5,5,2))))+IF(C19=1,2,0))) | L19: =IF(A19="","",IF(E19=0,0,IF(D19=1,8,3)+IF('02_ASIN原始数据'!N19>='01_动态参数'!B12+10,2,IF('02_ASIN原始数据'!N19>='01_动态参数'!B12,1,0)))) | M19: =IF(A19="","",MIN(10,IF('02_ASIN原始数据'!J19<=500,10,IF('02_ASIN原始数据'!J19<=1000,7,IF('02_ASIN原始数据'!J19<=2000,4,1)))+IF(C19=1,2,0)+IF(OR('02_ASIN原始数据'!Q19="Y",'02_ASIN原始数据'!Q19="Yes",'02_ASIN原始数据'!Q19="YES"),1,0))) | N19: 19
A20: ='02_ASIN原始数据'!A20 | B20: =IF('02_ASIN原始数据'!L20="","",IF(ISNUMBER('02_ASIN原始数据'!L20),TODAY()-'02_ASIN原始数据'!L20,"")) | C20: =IF(OR(A20="",B20=""),"",IF(B20<='01_动态参数'!B15,1,0)) | D20: =IF(A20="","",IF(AND('02_ASIN原始数据'!D20>='01_动态参数'!B10,'02_ASIN原始数据'!D20<='01_动态参数'!B11),1,0)) | E20: =IF(A20="","",IF('02_ASIN原始数据'!N20>='01_动态参数'!B12,1,0)) | F20: =IF(A20="","",IF('02_ASIN原始数据'!J20>'01_动态参数'!B13,1,0)) | G20: =IF(A20="","",IF('02_ASIN原始数据'!F20>='01_动态参数'!B14,1,0)) | H20: =IF(A20="","",IF('02_ASIN原始数据'!M20="AMZ",1,0)) | I20: =IF(A20="","",IF('02_ASIN原始数据'!E20="", "",RANK('02_ASIN原始数据'!E20,'02_ASIN原始数据'!$E$3:$E$52,0))) | J20: =IF(A20="","",MIN(10,IF('02_ASIN原始数据'!J20<=300,10,IF('02_ASIN原始数据'!J20<=800,8,IF('02_ASIN原始数据'!J20<=1500,5,IF('02_ASIN原始数据'!J20<=3000,2,0))))+IF('02_ASIN原始数据'!P20<=3,2,0)+IF(I20<=10,1,0))) | K20: =IF(A20="","",MIN(10,IF('02_ASIN原始数据'!F20>=50,10,IF('02_ASIN原始数据'!F20>=30,9,IF('02_ASIN原始数据'!F20>=15,7,IF('02_ASIN原始数据'!F20>=5,5,2))))+IF(C20=1,2,0))) | L20: =IF(A20="","",IF(E20=0,0,IF(D20=1,8,3)+IF('02_ASIN原始数据'!N20>='01_动态参数'!B12+10,2,IF('02_ASIN原始数据'!N20>='01_动态参数'!B12,1,0)))) | M20: =IF(A20="","",MIN(10,IF('02_ASIN原始数据'!J20<=500,10,IF('02_ASIN原始数据'!J20<=1000,7,IF('02_ASIN原始数据'!J20<=2000,4,1)))+IF(C20=1,2,0)+IF(OR('02_ASIN原始数据'!Q20="Y",'02_ASIN原始数据'!Q20="Yes",'02_ASIN原始数据'!Q20="YES"),1,0))) | N20: 20
A21: ='02_ASIN原始数据'!A21 | B21: =IF('02_ASIN原始数据'!L21="","",IF(ISNUMBER('02_ASIN原始数据'!L21),TODAY()-'02_ASIN原始数据'!L21,"")) | C21: =IF(OR(A21="",B21=""),"",IF(B21<='01_动态参数'!B15,1,0)) | D21: =IF(A21="","",IF(AND('02_ASIN原始数据'!D21>='01_动态参数'!B10,'02_ASIN原始数据'!D21<='01_动态参数'!B11),1,0)) | E21: =IF(A21="","",IF('02_ASIN原始数据'!N21>='01_动态参数'!B12,1,0)) | F21: =IF(A21="","",IF('02_ASIN原始数据'!J21>'01_动态参数'!B13,1,0)) | G21: =IF(A21="","",IF('02_ASIN原始数据'!F21>='01_动态参数'!B14,1,0)) | H21: =IF(A21="","",IF('02_ASIN原始数据'!M21="AMZ",1,0)) | I21: =IF(A21="","",IF('02_ASIN原始数据'!E21="", "",RANK('02_ASIN原始数据'!E21,'02_ASIN原始数据'!$E$3:$E$52,0))) | J21: =IF(A21="","",MIN(10,IF('02_ASIN原始数据'!J21<=300,10,IF('02_ASIN原始数据'!J21<=800,8,IF('02_ASIN原始数据'!J21<=1500,5,IF('02_ASIN原始数据'!J21<=3000,2,0))))+IF('02_ASIN原始数据'!P21<=3,2,0)+IF(I21<=10,1,0))) | K21: =IF(A21="","",MIN(10,IF('02_ASIN原始数据'!F21>=50,10,IF('02_ASIN原始数据'!F21>=30,9,IF('02_ASIN原始数据'!F21>=15,7,IF('02_ASIN原始数据'!F21>=5,5,2))))+IF(C21=1,2,0))) | L21: =IF(A21="","",IF(E21=0,0,IF(D21=1,8,3)+IF('02_ASIN原始数据'!N21>='01_动态参数'!B12+10,2,IF('02_ASIN原始数据'!N21>='01_动态参数'!B12,1,0)))) | M21: =IF(A21="","",MIN(10,IF('02_ASIN原始数据'!J21<=500,10,IF('02_ASIN原始数据'!J21<=1000,7,IF('02_ASIN原始数据'!J21<=2000,4,1)))+IF(C21=1,2,0)+IF(OR('02_ASIN原始数据'!Q21="Y",'02_ASIN原始数据'!Q21="Yes",'02_ASIN原始数据'!Q21="YES"),1,0))) | N21: 21
A22: ='02_ASIN原始数据'!A22 | B22: =IF('02_ASIN原始数据'!L22="","",IF(ISNUMBER('02_ASIN原始数据'!L22),TODAY()-'02_ASIN原始数据'!L22,"")) | C22: =IF(OR(A22="",B22=""),"",IF(B22<='01_动态参数'!B15,1,0)) | D22: =IF(A22="","",IF(AND('02_ASIN原始数据'!D22>='01_动态参数'!B10,'02_ASIN原始数据'!D22<='01_动态参数'!B11),1,0)) | E22: =IF(A22="","",IF('02_ASIN原始数据'!N22>='01_动态参数'!B12,1,0)) | F22: =IF(A22="","",IF('02_ASIN原始数据'!J22>'01_动态参数'!B13,1,0)) | G22: =IF(A22="","",IF('02_ASIN原始数据'!F22>='01_动态参数'!B14,1,0)) | H22: =IF(A22="","",IF('02_ASIN原始数据'!M22="AMZ",1,0)) | I22: =IF(A22="","",IF('02_ASIN原始数据'!E22="", "",RANK('02_ASIN原始数据'!E22,'02_ASIN原始数据'!$E$3:$E$52,0))) | J22: =IF(A22="","",MIN(10,IF('02_ASIN原始数据'!J22<=300,10,IF('02_ASIN原始数据'!J22<=800,8,IF('02_ASIN原始数据'!J22<=1500,5,IF('02_ASIN原始数据'!J22<=3000,2,0))))+IF('02_ASIN原始数据'!P22<=3,2,0)+IF(I22<=10,1,0))) | K22: =IF(A22="","",MIN(10,IF('02_ASIN原始数据'!F22>=50,10,IF('02_ASIN原始数据'!F22>=30,9,IF('02_ASIN原始数据'!F22>=15,7,IF('02_ASIN原始数据'!F22>=5,5,2))))+IF(C22=1,2,0))) | L22: =IF(A22="","",IF(E22=0,0,IF(D22=1,8,3)+IF('02_ASIN原始数据'!N22>='01_动态参数'!B12+10,2,IF('02_ASIN原始数据'!N22>='01_动态参数'!B12,1,0)))) | M22: =IF(A22="","",MIN(10,IF('02_ASIN原始数据'!J22<=500,10,IF('02_ASIN原始数据'!J22<=1000,7,IF('02_ASIN原始数据'!J22<=2000,4,1)))+IF(C22=1,2,0)+IF(OR('02_ASIN原始数据'!Q22="Y",'02_ASIN原始数据'!Q22="Yes",'02_ASIN原始数据'!Q22="YES"),1,0))) | N22: 22
A23: ='02_ASIN原始数据'!A23 | B23: =IF('02_ASIN原始数据'!L23="","",IF(ISNUMBER('02_ASIN原始数据'!L23),TODAY()-'02_ASIN原始数据'!L23,"")) | C23: =IF(OR(A23="",B23=""),"",IF(B23<='01_动态参数'!B15,1,0)) | D23: =IF(A23="","",IF(AND('02_ASIN原始数据'!D23>='01_动态参数'!B10,'02_ASIN原始数据'!D23<='01_动态参数'!B11),1,0)) | E23: =IF(A23="","",IF('02_ASIN原始数据'!N23>='01_动态参数'!B12,1,0)) | F23: =IF(A23="","",IF('02_ASIN原始数据'!J23>'01_动态参数'!B13,1,0)) | G23: =IF(A23="","",IF('02_ASIN原始数据'!F23>='01_动态参数'!B14,1,0)) | H23: =IF(A23="","",IF('02_ASIN原始数据'!M23="AMZ",1,0)) | I23: =IF(A23="","",IF('02_ASIN原始数据'!E23="", "",RANK('02_ASIN原始数据'!E23,'02_ASIN原始数据'!$E$3:$E$52,0))) | J23: =IF(A23="","",MIN(10,IF('02_ASIN原始数据'!J23<=300,10,IF('02_ASIN原始数据'!J23<=800,8,IF('02_ASIN原始数据'!J23<=1500,5,IF('02_ASIN原始数据'!J23<=3000,2,0))))+IF('02_ASIN原始数据'!P23<=3,2,0)+IF(I23<=10,1,0))) | K23: =IF(A23="","",MIN(10,IF('02_ASIN原始数据'!F23>=50,10,IF('02_ASIN原始数据'!F23>=30,9,IF('02_ASIN原始数据'!F23>=15,7,IF('02_ASIN原始数据'!F23>=5,5,2))))+IF(C23=1,2,0))) | L23: =IF(A23="","",IF(E23=0,0,IF(D23=1,8,3)+IF('02_ASIN原始数据'!N23>='01_动态参数'!B12+10,2,IF('02_ASIN原始数据'!N23>='01_动态参数'!B12,1,0)))) | M23: =IF(A23="","",MIN(10,IF('02_ASIN原始数据'!J23<=500,10,IF('02_ASIN原始数据'!J23<=1000,7,IF('02_ASIN原始数据'!J23<=2000,4,1)))+IF(C23=1,2,0)+IF(OR('02_ASIN原始数据'!Q23="Y",'02_ASIN原始数据'!Q23="Yes",'02_ASIN原始数据'!Q23="YES"),1,0))) | N23: 23
A24: ='02_ASIN原始数据'!A24 | B24: =IF('02_ASIN原始数据'!L24="","",IF(ISNUMBER('02_ASIN原始数据'!L24),TODAY()-'02_ASIN原始数据'!L24,"")) | C24: =IF(OR(A24="",B24=""),"",IF(B24<='01_动态参数'!B15,1,0)) | D24: =IF(A24="","",IF(AND('02_ASIN原始数据'!D24>='01_动态参数'!B10,'02_ASIN原始数据'!D24<='01_动态参数'!B11),1,0)) | E24: =IF(A24="","",IF('02_ASIN原始数据'!N24>='01_动态参数'!B12,1,0)) | F24: =IF(A24="","",IF('02_ASIN原始数据'!J24>'01_动态参数'!B13,1,0)) | G24: =IF(A24="","",IF('02_ASIN原始数据'!F24>='01_动态参数'!B14,1,0)) | H24: =IF(A24="","",IF('02_ASIN原始数据'!M24="AMZ",1,0)) | I24: =IF(A24="","",IF('02_ASIN原始数据'!E24="", "",RANK('02_ASIN原始数据'!E24,'02_ASIN原始数据'!$E$3:$E$52,0))) | J24: =IF(A24="","",MIN(10,IF('02_ASIN原始数据'!J24<=300,10,IF('02_ASIN原始数据'!J24<=800,8,IF('02_ASIN原始数据'!J24<=1500,5,IF('02_ASIN原始数据'!J24<=3000,2,0))))+IF('02_ASIN原始数据'!P24<=3,2,0)+IF(I24<=10,1,0))) | K24: =IF(A24="","",MIN(10,IF('02_ASIN原始数据'!F24>=50,10,IF('02_ASIN原始数据'!F24>=30,9,IF('02_ASIN原始数据'!F24>=15,7,IF('02_ASIN原始数据'!F24>=5,5,2))))+IF(C24=1,2,0))) | L24: =IF(A24="","",IF(E24=0,0,IF(D24=1,8,3)+IF('02_ASIN原始数据'!N24>='01_动态参数'!B12+10,2,IF('02_ASIN原始数据'!N24>='01_动态参数'!B12,1,0)))) | M24: =IF(A24="","",MIN(10,IF('02_ASIN原始数据'!J24<=500,10,IF('02_ASIN原始数据'!J24<=1000,7,IF('02_ASIN原始数据'!J24<=2000,4,1)))+IF(C24=1,2,0)+IF(OR('02_ASIN原始数据'!Q24="Y",'02_ASIN原始数据'!Q24="Yes",'02_ASIN原始数据'!Q24="YES"),1,0))) | N24: 24
A25: ='02_ASIN原始数据'!A25 | B25: =IF('02_ASIN原始数据'!L25="","",IF(ISNUMBER('02_ASIN原始数据'!L25),TODAY()-'02_ASIN原始数据'!L25,"")) | C25: =IF(OR(A25="",B25=""),"",IF(B25<='01_动态参数'!B15,1,0)) | D25: =IF(A25="","",IF(AND('02_ASIN原始数据'!D25>='01_动态参数'!B10,'02_ASIN原始数据'!D25<='01_动态参数'!B11),1,0)) | E25: =IF(A25="","",IF('02_ASIN原始数据'!N25>='01_动态参数'!B12,1,0)) | F25: =IF(A25="","",IF('02_ASIN原始数据'!J25>'01_动态参数'!B13,1,0)) | G25: =IF(A25="","",IF('02_ASIN原始数据'!F25>='01_动态参数'!B14,1,0)) | H25: =IF(A25="","",IF('02_ASIN原始数据'!M25="AMZ",1,0)) | I25: =IF(A25="","",IF('02_ASIN原始数据'!E25="", "",RANK('02_ASIN原始数据'!E25,'02_ASIN原始数据'!$E$3:$E$52,0))) | J25: =IF(A25="","",MIN(10,IF('02_ASIN原始数据'!J25<=300,10,IF('02_ASIN原始数据'!J25<=800,8,IF('02_ASIN原始数据'!J25<=1500,5,IF('02_ASIN原始数据'!J25<=3000,2,0))))+IF('02_ASIN原始数据'!P25<=3,2,0)+IF(I25<=10,1,0))) | K25: =IF(A25="","",MIN(10,IF('02_ASIN原始数据'!F25>=50,10,IF('02_ASIN原始数据'!F25>=30,9,IF('02_ASIN原始数据'!F25>=15,7,IF('02_ASIN原始数据'!F25>=5,5,2))))+IF(C25=1,2,0))) | L25: =IF(A25="","",IF(E25=0,0,IF(D25=1,8,3)+IF('02_ASIN原始数据'!N25>='01_动态参数'!B12+10,2,IF('02_ASIN原始数据'!N25>='01_动态参数'!B12,1,0)))) | M25: =IF(A25="","",MIN(10,IF('02_ASIN原始数据'!J25<=500,10,IF('02_ASIN原始数据'!J25<=1000,7,IF('02_ASIN原始数据'!J25<=2000,4,1)))+IF(C25=1,2,0)+IF(OR('02_ASIN原始数据'!Q25="Y",'02_ASIN原始数据'!Q25="Yes",'02_ASIN原始数据'!Q25="YES"),1,0))) | N25: 25
A26: ='02_ASIN原始数据'!A26 | B26: =IF('02_ASIN原始数据'!L26="","",IF(ISNUMBER('02_ASIN原始数据'!L26),TODAY()-'02_ASIN原始数据'!L26,"")) | C26: =IF(OR(A26="",B26=""),"",IF(B26<='01_动态参数'!B15,1,0)) | D26: =IF(A26="","",IF(AND('02_ASIN原始数据'!D26>='01_动态参数'!B10,'02_ASIN原始数据'!D26<='01_动态参数'!B11),1,0)) | E26: =IF(A26="","",IF('02_ASIN原始数据'!N26>='01_动态参数'!B12,1,0)) | F26: =IF(A26="","",IF('02_ASIN原始数据'!J26>'01_动态参数'!B13,1,0)) | G26: =IF(A26="","",IF('02_ASIN原始数据'!F26>='01_动态参数'!B14,1,0)) | H26: =IF(A26="","",IF('02_ASIN原始数据'!M26="AMZ",1,0)) | I26: =IF(A26="","",IF('02_ASIN原始数据'!E26="", "",RANK('02_ASIN原始数据'!E26,'02_ASIN原始数据'!$E$3:$E$52,0))) | J26: =IF(A26="","",MIN(10,IF('02_ASIN原始数据'!J26<=300,10,IF('02_ASIN原始数据'!J26<=800,8,IF('02_ASIN原始数据'!J26<=1500,5,IF('02_ASIN原始数据'!J26<=3000,2,0))))+IF('02_ASIN原始数据'!P26<=3,2,0)+IF(I26<=10,1,0))) | K26: =IF(A26="","",MIN(10,IF('02_ASIN原始数据'!F26>=50,10,IF('02_ASIN原始数据'!F26>=30,9,IF('02_ASIN原始数据'!F26>=15,7,IF('02_ASIN原始数据'!F26>=5,5,2))))+IF(C26=1,2,0))) | L26: =IF(A26="","",IF(E26=0,0,IF(D26=1,8,3)+IF('02_ASIN原始数据'!N26>='01_动态参数'!B12+10,2,IF('02_ASIN原始数据'!N26>='01_动态参数'!B12,1,0)))) | M26: =IF(A26="","",MIN(10,IF('02_ASIN原始数据'!J26<=500,10,IF('02_ASIN原始数据'!J26<=1000,7,IF('02_ASIN原始数据'!J26<=2000,4,1)))+IF(C26=1,2,0)+IF(OR('02_ASIN原始数据'!Q26="Y",'02_ASIN原始数据'!Q26="Yes",'02_ASIN原始数据'!Q26="YES"),1,0))) | N26: 26
A27: ='02_ASIN原始数据'!A27 | B27: =IF('02_ASIN原始数据'!L27="","",IF(ISNUMBER('02_ASIN原始数据'!L27),TODAY()-'02_ASIN原始数据'!L27,"")) | C27: =IF(OR(A27="",B27=""),"",IF(B27<='01_动态参数'!B15,1,0)) | D27: =IF(A27="","",IF(AND('02_ASIN原始数据'!D27>='01_动态参数'!B10,'02_ASIN原始数据'!D27<='01_动态参数'!B11),1,0)) | E27: =IF(A27="","",IF('02_ASIN原始数据'!N27>='01_动态参数'!B12,1,0)) | F27: =IF(A27="","",IF('02_ASIN原始数据'!J27>'01_动态参数'!B13,1,0)) | G27: =IF(A27="","",IF('02_ASIN原始数据'!F27>='01_动态参数'!B14,1,0)) | H27: =IF(A27="","",IF('02_ASIN原始数据'!M27="AMZ",1,0)) | I27: =IF(A27="","",IF('02_ASIN原始数据'!E27="", "",RANK('02_ASIN原始数据'!E27,'02_ASIN原始数据'!$E$3:$E$52,0))) | J27: =IF(A27="","",MIN(10,IF('02_ASIN原始数据'!J27<=300,10,IF('02_ASIN原始数据'!J27<=800,8,IF('02_ASIN原始数据'!J27<=1500,5,IF('02_ASIN原始数据'!J27<=3000,2,0))))+IF('02_ASIN原始数据'!P27<=3,2,0)+IF(I27<=10,1,0))) | K27: =IF(A27="","",MIN(10,IF('02_ASIN原始数据'!F27>=50,10,IF('02_ASIN原始数据'!F27>=30,9,IF('02_ASIN原始数据'!F27>=15,7,IF('02_ASIN原始数据'!F27>=5,5,2))))+IF(C27=1,2,0))) | L27: =IF(A27="","",IF(E27=0,0,IF(D27=1,8,3)+IF('02_ASIN原始数据'!N27>='01_动态参数'!B12+10,2,IF('02_ASIN原始数据'!N27>='01_动态参数'!B12,1,0)))) | M27: =IF(A27="","",MIN(10,IF('02_ASIN原始数据'!J27<=500,10,IF('02_ASIN原始数据'!J27<=1000,7,IF('02_ASIN原始数据'!J27<=2000,4,1)))+IF(C27=1,2,0)+IF(OR('02_ASIN原始数据'!Q27="Y",'02_ASIN原始数据'!Q27="Yes",'02_ASIN原始数据'!Q27="YES"),1,0))) | N27: 27
A28: ='02_ASIN原始数据'!A28 | B28: =IF('02_ASIN原始数据'!L28="","",IF(ISNUMBER('02_ASIN原始数据'!L28),TODAY()-'02_ASIN原始数据'!L28,"")) | C28: =IF(OR(A28="",B28=""),"",IF(B28<='01_动态参数'!B15,1,0)) | D28: =IF(A28="","",IF(AND('02_ASIN原始数据'!D28>='01_动态参数'!B10,'02_ASIN原始数据'!D28<='01_动态参数'!B11),1,0)) | E28: =IF(A28="","",IF('02_ASIN原始数据'!N28>='01_动态参数'!B12,1,0)) | F28: =IF(A28="","",IF('02_ASIN原始数据'!J28>'01_动态参数'!B13,1,0)) | G28: =IF(A28="","",IF('02_ASIN原始数据'!F28>='01_动态参数'!B14,1,0)) | H28: =IF(A28="","",IF('02_ASIN原始数据'!M28="AMZ",1,0)) | I28: =IF(A28="","",IF('02_ASIN原始数据'!E28="", "",RANK('02_ASIN原始数据'!E28,'02_ASIN原始数据'!$E$3:$E$52,0))) | J28: =IF(A28="","",MIN(10,IF('02_ASIN原始数据'!J28<=300,10,IF('02_ASIN原始数据'!J28<=800,8,IF('02_ASIN原始数据'!J28<=1500,5,IF('02_ASIN原始数据'!J28<=3000,2,0))))+IF('02_ASIN原始数据'!P28<=3,2,0)+IF(I28<=10,1,0))) | K28: =IF(A28="","",MIN(10,IF('02_ASIN原始数据'!F28>=50,10,IF('02_ASIN原始数据'!F28>=30,9,IF('02_ASIN原始数据'!F28>=15,7,IF('02_ASIN原始数据'!F28>=5,5,2))))+IF(C28=1,2,0))) | L28: =IF(A28="","",IF(E28=0,0,IF(D28=1,8,3)+IF('02_ASIN原始数据'!N28>='01_动态参数'!B12+10,2,IF('02_ASIN原始数据'!N28>='01_动态参数'!B12,1,0)))) | M28: =IF(A28="","",MIN(10,IF('02_ASIN原始数据'!J28<=500,10,IF('02_ASIN原始数据'!J28<=1000,7,IF('02_ASIN原始数据'!J28<=2000,4,1)))+IF(C28=1,2,0)+IF(OR('02_ASIN原始数据'!Q28="Y",'02_ASIN原始数据'!Q28="Yes",'02_ASIN原始数据'!Q28="YES"),1,0))) | N28: 28
A29: ='02_ASIN原始数据'!A29 | B29: =IF('02_ASIN原始数据'!L29="","",IF(ISNUMBER('02_ASIN原始数据'!L29),TODAY()-'02_ASIN原始数据'!L29,"")) | C29: =IF(OR(A29="",B29=""),"",IF(B29<='01_动态参数'!B15,1,0)) | D29: =IF(A29="","",IF(AND('02_ASIN原始数据'!D29>='01_动态参数'!B10,'02_ASIN原始数据'!D29<='01_动态参数'!B11),1,0)) | E29: =IF(A29="","",IF('02_ASIN原始数据'!N29>='01_动态参数'!B12,1,0)) | F29: =IF(A29="","",IF('02_ASIN原始数据'!J29>'01_动态参数'!B13,1,0)) | G29: =IF(A29="","",IF('02_ASIN原始数据'!F29>='01_动态参数'!B14,1,0)) | H29: =IF(A29="","",IF('02_ASIN原始数据'!M29="AMZ",1,0)) | I29: =IF(A29="","",IF('02_ASIN原始数据'!E29="", "",RANK('02_ASIN原始数据'!E29,'02_ASIN原始数据'!$E$3:$E$52,0))) | J29: =IF(A29="","",MIN(10,IF('02_ASIN原始数据'!J29<=300,10,IF('02_ASIN原始数据'!J29<=800,8,IF('02_ASIN原始数据'!J29<=1500,5,IF('02_ASIN原始数据'!J29<=3000,2,0))))+IF('02_ASIN原始数据'!P29<=3,2,0)+IF(I29<=10,1,0))) | K29: =IF(A29="","",MIN(10,IF('02_ASIN原始数据'!F29>=50,10,IF('02_ASIN原始数据'!F29>=30,9,IF('02_ASIN原始数据'!F29>=15,7,IF('02_ASIN原始数据'!F29>=5,5,2))))+IF(C29=1,2,0))) | L29: =IF(A29="","",IF(E29=0,0,IF(D29=1,8,3)+IF('02_ASIN原始数据'!N29>='01_动态参数'!B12+10,2,IF('02_ASIN原始数据'!N29>='01_动态参数'!B12,1,0)))) | M29: =IF(A29="","",MIN(10,IF('02_ASIN原始数据'!J29<=500,10,IF('02_ASIN原始数据'!J29<=1000,7,IF('02_ASIN原始数据'!J29<=2000,4,1)))+IF(C29=1,2,0)+IF(OR('02_ASIN原始数据'!Q29="Y",'02_ASIN原始数据'!Q29="Yes",'02_ASIN原始数据'!Q29="YES"),1,0))) | N29: 29
A30: ='02_ASIN原始数据'!A30 | B30: =IF('02_ASIN原始数据'!L30="","",IF(ISNUMBER('02_ASIN原始数据'!L30),TODAY()-'02_ASIN原始数据'!L30,"")) | C30: =IF(OR(A30="",B30=""),"",IF(B30<='01_动态参数'!B15,1,0)) | D30: =IF(A30="","",IF(AND('02_ASIN原始数据'!D30>='01_动态参数'!B10,'02_ASIN原始数据'!D30<='01_动态参数'!B11),1,0)) | E30: =IF(A30="","",IF('02_ASIN原始数据'!N30>='01_动态参数'!B12,1,0)) | F30: =IF(A30="","",IF('02_ASIN原始数据'!J30>'01_动态参数'!B13,1,0)) | G30: =IF(A30="","",IF('02_ASIN原始数据'!F30>='01_动态参数'!B14,1,0)) | H30: =IF(A30="","",IF('02_ASIN原始数据'!M30="AMZ",1,0)) | I30: =IF(A30="","",IF('02_ASIN原始数据'!E30="", "",RANK('02_ASIN原始数据'!E30,'02_ASIN原始数据'!$E$3:$E$52,0))) | J30: =IF(A30="","",MIN(10,IF('02_ASIN原始数据'!J30<=300,10,IF('02_ASIN原始数据'!J30<=800,8,IF('02_ASIN原始数据'!J30<=1500,5,IF('02_ASIN原始数据'!J30<=3000,2,0))))+IF('02_ASIN原始数据'!P30<=3,2,0)+IF(I30<=10,1,0))) | K30: =IF(A30="","",MIN(10,IF('02_ASIN原始数据'!F30>=50,10,IF('02_ASIN原始数据'!F30>=30,9,IF('02_ASIN原始数据'!F30>=15,7,IF('02_ASIN原始数据'!F30>=5,5,2))))+IF(C30=1,2,0))) | L30: =IF(A30="","",IF(E30=0,0,IF(D30=1,8,3)+IF('02_ASIN原始数据'!N30>='01_动态参数'!B12+10,2,IF('02_ASIN原始数据'!N30>='01_动态参数'!B12,1,0)))) | M30: =IF(A30="","",MIN(10,IF('02_ASIN原始数据'!J30<=500,10,IF('02_ASIN原始数据'!J30<=1000,7,IF('02_ASIN原始数据'!J30<=2000,4,1)))+IF(C30=1,2,0)+IF(OR('02_ASIN原始数据'!Q30="Y",'02_ASIN原始数据'!Q30="Yes",'02_ASIN原始数据'!Q30="YES"),1,0))) | N30: 30
A31: ='02_ASIN原始数据'!A31 | B31: =IF('02_ASIN原始数据'!L31="","",IF(ISNUMBER('02_ASIN原始数据'!L31),TODAY()-'02_ASIN原始数据'!L31,"")) | C31: =IF(OR(A31="",B31=""),"",IF(B31<='01_动态参数'!B15,1,0)) | D31: =IF(A31="","",IF(AND('02_ASIN原始数据'!D31>='01_动态参数'!B10,'02_ASIN原始数据'!D31<='01_动态参数'!B11),1,0)) | E31: =IF(A31="","",IF('02_ASIN原始数据'!N31>='01_动态参数'!B12,1,0)) | F31: =IF(A31="","",IF('02_ASIN原始数据'!J31>'01_动态参数'!B13,1,0)) | G31: =IF(A31="","",IF('02_ASIN原始数据'!F31>='01_动态参数'!B14,1,0)) | H31: =IF(A31="","",IF('02_ASIN原始数据'!M31="AMZ",1,0)) | I31: =IF(A31="","",IF('02_ASIN原始数据'!E31="", "",RANK('02_ASIN原始数据'!E31,'02_ASIN原始数据'!$E$3:$E$52,0))) | J31: =IF(A31="","",MIN(10,IF('02_ASIN原始数据'!J31<=300,10,IF('02_ASIN原始数据'!J31<=800,8,IF('02_ASIN原始数据'!J31<=1500,5,IF('02_ASIN原始数据'!J31<=3000,2,0))))+IF('02_ASIN原始数据'!P31<=3,2,0)+IF(I31<=10,1,0))) | K31: =IF(A31="","",MIN(10,IF('02_ASIN原始数据'!F31>=50,10,IF('02_ASIN原始数据'!F31>=30,9,IF('02_ASIN原始数据'!F31>=15,7,IF('02_ASIN原始数据'!F31>=5,5,2))))+IF(C31=1,2,0))) | L31: =IF(A31="","",IF(E31=0,0,IF(D31=1,8,3)+IF('02_ASIN原始数据'!N31>='01_动态参数'!B12+10,2,IF('02_ASIN原始数据'!N31>='01_动态参数'!B12,1,0)))) | M31: =IF(A31="","",MIN(10,IF('02_ASIN原始数据'!J31<=500,10,IF('02_ASIN原始数据'!J31<=1000,7,IF('02_ASIN原始数据'!J31<=2000,4,1)))+IF(C31=1,2,0)+IF(OR('02_ASIN原始数据'!Q31="Y",'02_ASIN原始数据'!Q31="Yes",'02_ASIN原始数据'!Q31="YES"),1,0))) | N31: 31
A32: ='02_ASIN原始数据'!A32 | B32: =IF('02_ASIN原始数据'!L32="","",IF(ISNUMBER('02_ASIN原始数据'!L32),TODAY()-'02_ASIN原始数据'!L32,"")) | C32: =IF(OR(A32="",B32=""),"",IF(B32<='01_动态参数'!B15,1,0)) | D32: =IF(A32="","",IF(AND('02_ASIN原始数据'!D32>='01_动态参数'!B10,'02_ASIN原始数据'!D32<='01_动态参数'!B11),1,0)) | E32: =IF(A32="","",IF('02_ASIN原始数据'!N32>='01_动态参数'!B12,1,0)) | F32: =IF(A32="","",IF('02_ASIN原始数据'!J32>'01_动态参数'!B13,1,0)) | G32: =IF(A32="","",IF('02_ASIN原始数据'!F32>='01_动态参数'!B14,1,0)) | H32: =IF(A32="","",IF('02_ASIN原始数据'!M32="AMZ",1,0)) | I32: =IF(A32="","",IF('02_ASIN原始数据'!E32="", "",RANK('02_ASIN原始数据'!E32,'02_ASIN原始数据'!$E$3:$E$52,0))) | J32: =IF(A32="","",MIN(10,IF('02_ASIN原始数据'!J32<=300,10,IF('02_ASIN原始数据'!J32<=800,8,IF('02_ASIN原始数据'!J32<=1500,5,IF('02_ASIN原始数据'!J32<=3000,2,0))))+IF('02_ASIN原始数据'!P32<=3,2,0)+IF(I32<=10,1,0))) | K32: =IF(A32="","",MIN(10,IF('02_ASIN原始数据'!F32>=50,10,IF('02_ASIN原始数据'!F32>=30,9,IF('02_ASIN原始数据'!F32>=15,7,IF('02_ASIN原始数据'!F32>=5,5,2))))+IF(C32=1,2,0))) | L32: =IF(A32="","",IF(E32=0,0,IF(D32=1,8,3)+IF('02_ASIN原始数据'!N32>='01_动态参数'!B12+10,2,IF('02_ASIN原始数据'!N32>='01_动态参数'!B12,1,0)))) | M32: =IF(A32="","",MIN(10,IF('02_ASIN原始数据'!J32<=500,10,IF('02_ASIN原始数据'!J32<=1000,7,IF('02_ASIN原始数据'!J32<=2000,4,1)))+IF(C32=1,2,0)+IF(OR('02_ASIN原始数据'!Q32="Y",'02_ASIN原始数据'!Q32="Yes",'02_ASIN原始数据'!Q32="YES"),1,0))) | N32: 32
A33: ='02_ASIN原始数据'!A33 | B33: =IF('02_ASIN原始数据'!L33="","",IF(ISNUMBER('02_ASIN原始数据'!L33),TODAY()-'02_ASIN原始数据'!L33,"")) | C33: =IF(OR(A33="",B33=""),"",IF(B33<='01_动态参数'!B15,1,0)) | D33: =IF(A33="","",IF(AND('02_ASIN原始数据'!D33>='01_动态参数'!B10,'02_ASIN原始数据'!D33<='01_动态参数'!B11),1,0)) | E33: =IF(A33="","",IF('02_ASIN原始数据'!N33>='01_动态参数'!B12,1,0)) | F33: =IF(A33="","",IF('02_ASIN原始数据'!J33>'01_动态参数'!B13,1,0)) | G33: =IF(A33="","",IF('02_ASIN原始数据'!F33>='01_动态参数'!B14,1,0)) | H33: =IF(A33="","",IF('02_ASIN原始数据'!M33="AMZ",1,0)) | I33: =IF(A33="","",IF('02_ASIN原始数据'!E33="", "",RANK('02_ASIN原始数据'!E33,'02_ASIN原始数据'!$E$3:$E$52,0))) | J33: =IF(A33="","",MIN(10,IF('02_ASIN原始数据'!J33<=300,10,IF('02_ASIN原始数据'!J33<=800,8,IF('02_ASIN原始数据'!J33<=1500,5,IF('02_ASIN原始数据'!J33<=3000,2,0))))+IF('02_ASIN原始数据'!P33<=3,2,0)+IF(I33<=10,1,0))) | K33: =IF(A33="","",MIN(10,IF('02_ASIN原始数据'!F33>=50,10,IF('02_ASIN原始数据'!F33>=30,9,IF('02_ASIN原始数据'!F33>=15,7,IF('02_ASIN原始数据'!F33>=5,5,2))))+IF(C33=1,2,0))) | L33: =IF(A33="","",IF(E33=0,0,IF(D33=1,8,3)+IF('02_ASIN原始数据'!N33>='01_动态参数'!B12+10,2,IF('02_ASIN原始数据'!N33>='01_动态参数'!B12,1,0)))) | M33: =IF(A33="","",MIN(10,IF('02_ASIN原始数据'!J33<=500,10,IF('02_ASIN原始数据'!J33<=1000,7,IF('02_ASIN原始数据'!J33<=2000,4,1)))+IF(C33=1,2,0)+IF(OR('02_ASIN原始数据'!Q33="Y",'02_ASIN原始数据'!Q33="Yes",'02_ASIN原始数据'!Q33="YES"),1,0))) | N33: 33
A34: ='02_ASIN原始数据'!A34 | B34: =IF('02_ASIN原始数据'!L34="","",IF(ISNUMBER('02_ASIN原始数据'!L34),TODAY()-'02_ASIN原始数据'!L34,"")) | C34: =IF(OR(A34="",B34=""),"",IF(B34<='01_动态参数'!B15,1,0)) | D34: =IF(A34="","",IF(AND('02_ASIN原始数据'!D34>='01_动态参数'!B10,'02_ASIN原始数据'!D34<='01_动态参数'!B11),1,0)) | E34: =IF(A34="","",IF('02_ASIN原始数据'!N34>='01_动态参数'!B12,1,0)) | F34: =IF(A34="","",IF('02_ASIN原始数据'!J34>'01_动态参数'!B13,1,0)) | G34: =IF(A34="","",IF('02_ASIN原始数据'!F34>='01_动态参数'!B14,1,0)) | H34: =IF(A34="","",IF('02_ASIN原始数据'!M34="AMZ",1,0)) | I34: =IF(A34="","",IF('02_ASIN原始数据'!E34="", "",RANK('02_ASIN原始数据'!E34,'02_ASIN原始数据'!$E$3:$E$52,0))) | J34: =IF(A34="","",MIN(10,IF('02_ASIN原始数据'!J34<=300,10,IF('02_ASIN原始数据'!J34<=800,8,IF('02_ASIN原始数据'!J34<=1500,5,IF('02_ASIN原始数据'!J34<=3000,2,0))))+IF('02_ASIN原始数据'!P34<=3,2,0)+IF(I34<=10,1,0))) | K34: =IF(A34="","",MIN(10,IF('02_ASIN原始数据'!F34>=50,10,IF('02_ASIN原始数据'!F34>=30,9,IF('02_ASIN原始数据'!F34>=15,7,IF('02_ASIN原始数据'!F34>=5,5,2))))+IF(C34=1,2,0))) | L34: =IF(A34="","",IF(E34=0,0,IF(D34=1,8,3)+IF('02_ASIN原始数据'!N34>='01_动态参数'!B12+10,2,IF('02_ASIN原始数据'!N34>='01_动态参数'!B12,1,0)))) | M34: =IF(A34="","",MIN(10,IF('02_ASIN原始数据'!J34<=500,10,IF('02_ASIN原始数据'!J34<=1000,7,IF('02_ASIN原始数据'!J34<=2000,4,1)))+IF(C34=1,2,0)+IF(OR('02_ASIN原始数据'!Q34="Y",'02_ASIN原始数据'!Q34="Yes",'02_ASIN原始数据'!Q34="YES"),1,0))) | N34: 34
A35: ='02_ASIN原始数据'!A35 | B35: =IF('02_ASIN原始数据'!L35="","",IF(ISNUMBER('02_ASIN原始数据'!L35),TODAY()-'02_ASIN原始数据'!L35,"")) | C35: =IF(OR(A35="",B35=""),"",IF(B35<='01_动态参数'!B15,1,0)) | D35: =IF(A35="","",IF(AND('02_ASIN原始数据'!D35>='01_动态参数'!B10,'02_ASIN原始数据'!D35<='01_动态参数'!B11),1,0)) | E35: =IF(A35="","",IF('02_ASIN原始数据'!N35>='01_动态参数'!B12,1,0)) | F35: =IF(A35="","",IF('02_ASIN原始数据'!J35>'01_动态参数'!B13,1,0)) | G35: =IF(A35="","",IF('02_ASIN原始数据'!F35>='01_动态参数'!B14,1,0)) | H35: =IF(A35="","",IF('02_ASIN原始数据'!M35="AMZ",1,0)) | I35: =IF(A35="","",IF('02_ASIN原始数据'!E35="", "",RANK('02_ASIN原始数据'!E35,'02_ASIN原始数据'!$E$3:$E$52,0))) | J35: =IF(A35="","",MIN(10,IF('02_ASIN原始数据'!J35<=300,10,IF('02_ASIN原始数据'!J35<=800,8,IF('02_ASIN原始数据'!J35<=1500,5,IF('02_ASIN原始数据'!J35<=3000,2,0))))+IF('02_ASIN原始数据'!P35<=3,2,0)+IF(I35<=10,1,0))) | K35: =IF(A35="","",MIN(10,IF('02_ASIN原始数据'!F35>=50,10,IF('02_ASIN原始数据'!F35>=30,9,IF('02_ASIN原始数据'!F35>=15,7,IF('02_ASIN原始数据'!F35>=5,5,2))))+IF(C35=1,2,0))) | L35: =IF(A35="","",IF(E35=0,0,IF(D35=1,8,3)+IF('02_ASIN原始数据'!N35>='01_动态参数'!B12+10,2,IF('02_ASIN原始数据'!N35>='01_动态参数'!B12,1,0)))) | M35: =IF(A35="","",MIN(10,IF('02_ASIN原始数据'!J35<=500,10,IF('02_ASIN原始数据'!J35<=1000,7,IF('02_ASIN原始数据'!J35<=2000,4,1)))+IF(C35=1,2,0)+IF(OR('02_ASIN原始数据'!Q35="Y",'02_ASIN原始数据'!Q35="Yes",'02_ASIN原始数据'!Q35="YES"),1,0))) | N35: 35
A36: ='02_ASIN原始数据'!A36 | B36: =IF('02_ASIN原始数据'!L36="","",IF(ISNUMBER('02_ASIN原始数据'!L36),TODAY()-'02_ASIN原始数据'!L36,"")) | C36: =IF(OR(A36="",B36=""),"",IF(B36<='01_动态参数'!B15,1,0)) | D36: =IF(A36="","",IF(AND('02_ASIN原始数据'!D36>='01_动态参数'!B10,'02_ASIN原始数据'!D36<='01_动态参数'!B11),1,0)) | E36: =IF(A36="","",IF('02_ASIN原始数据'!N36>='01_动态参数'!B12,1,0)) | F36: =IF(A36="","",IF('02_ASIN原始数据'!J36>'01_动态参数'!B13,1,0)) | G36: =IF(A36="","",IF('02_ASIN原始数据'!F36>='01_动态参数'!B14,1,0)) | H36: =IF(A36="","",IF('02_ASIN原始数据'!M36="AMZ",1,0)) | I36: =IF(A36="","",IF('02_ASIN原始数据'!E36="", "",RANK('02_ASIN原始数据'!E36,'02_ASIN原始数据'!$E$3:$E$52,0))) | J36: =IF(A36="","",MIN(10,IF('02_ASIN原始数据'!J36<=300,10,IF('02_ASIN原始数据'!J36<=800,8,IF('02_ASIN原始数据'!J36<=1500,5,IF('02_ASIN原始数据'!J36<=3000,2,0))))+IF('02_ASIN原始数据'!P36<=3,2,0)+IF(I36<=10,1,0))) | K36: =IF(A36="","",MIN(10,IF('02_ASIN原始数据'!F36>=50,10,IF('02_ASIN原始数据'!F36>=30,9,IF('02_ASIN原始数据'!F36>=15,7,IF('02_ASIN原始数据'!F36>=5,5,2))))+IF(C36=1,2,0))) | L36: =IF(A36="","",IF(E36=0,0,IF(D36=1,8,3)+IF('02_ASIN原始数据'!N36>='01_动态参数'!B12+10,2,IF('02_ASIN原始数据'!N36>='01_动态参数'!B12,1,0)))) | M36: =IF(A36="","",MIN(10,IF('02_ASIN原始数据'!J36<=500,10,IF('02_ASIN原始数据'!J36<=1000,7,IF('02_ASIN原始数据'!J36<=2000,4,1)))+IF(C36=1,2,0)+IF(OR('02_ASIN原始数据'!Q36="Y",'02_ASIN原始数据'!Q36="Yes",'02_ASIN原始数据'!Q36="YES"),1,0))) | N36: 36
A37: ='02_ASIN原始数据'!A37 | B37: =IF('02_ASIN原始数据'!L37="","",IF(ISNUMBER('02_ASIN原始数据'!L37),TODAY()-'02_ASIN原始数据'!L37,"")) | C37: =IF(OR(A37="",B37=""),"",IF(B37<='01_动态参数'!B15,1,0)) | D37: =IF(A37="","",IF(AND('02_ASIN原始数据'!D37>='01_动态参数'!B10,'02_ASIN原始数据'!D37<='01_动态参数'!B11),1,0)) | E37: =IF(A37="","",IF('02_ASIN原始数据'!N37>='01_动态参数'!B12,1,0)) | F37: =IF(A37="","",IF('02_ASIN原始数据'!J37>'01_动态参数'!B13,1,0)) | G37: =IF(A37="","",IF('02_ASIN原始数据'!F37>='01_动态参数'!B14,1,0)) | H37: =IF(A37="","",IF('02_ASIN原始数据'!M37="AMZ",1,0)) | I37: =IF(A37="","",IF('02_ASIN原始数据'!E37="", "",RANK('02_ASIN原始数据'!E37,'02_ASIN原始数据'!$E$3:$E$52,0))) | J37: =IF(A37="","",MIN(10,IF('02_ASIN原始数据'!J37<=300,10,IF('02_ASIN原始数据'!J37<=800,8,IF('02_ASIN原始数据'!J37<=1500,5,IF('02_ASIN原始数据'!J37<=3000,2,0))))+IF('02_ASIN原始数据'!P37<=3,2,0)+IF(I37<=10,1,0))) | K37: =IF(A37="","",MIN(10,IF('02_ASIN原始数据'!F37>=50,10,IF('02_ASIN原始数据'!F37>=30,9,IF('02_ASIN原始数据'!F37>=15,7,IF('02_ASIN原始数据'!F37>=5,5,2))))+IF(C37=1,2,0))) | L37: =IF(A37="","",IF(E37=0,0,IF(D37=1,8,3)+IF('02_ASIN原始数据'!N37>='01_动态参数'!B12+10,2,IF('02_ASIN原始数据'!N37>='01_动态参数'!B12,1,0)))) | M37: =IF(A37="","",MIN(10,IF('02_ASIN原始数据'!J37<=500,10,IF('02_ASIN原始数据'!J37<=1000,7,IF('02_ASIN原始数据'!J37<=2000,4,1)))+IF(C37=1,2,0)+IF(OR('02_ASIN原始数据'!Q37="Y",'02_ASIN原始数据'!Q37="Yes",'02_ASIN原始数据'!Q37="YES"),1,0))) | N37: 37
A38: ='02_ASIN原始数据'!A38 | B38: =IF('02_ASIN原始数据'!L38="","",IF(ISNUMBER('02_ASIN原始数据'!L38),TODAY()-'02_ASIN原始数据'!L38,"")) | C38: =IF(OR(A38="",B38=""),"",IF(B38<='01_动态参数'!B15,1,0)) | D38: =IF(A38="","",IF(AND('02_ASIN原始数据'!D38>='01_动态参数'!B10,'02_ASIN原始数据'!D38<='01_动态参数'!B11),1,0)) | E38: =IF(A38="","",IF('02_ASIN原始数据'!N38>='01_动态参数'!B12,1,0)) | F38: =IF(A38="","",IF('02_ASIN原始数据'!J38>'01_动态参数'!B13,1,0)) | G38: =IF(A38="","",IF('02_ASIN原始数据'!F38>='01_动态参数'!B14,1,0)) | H38: =IF(A38="","",IF('02_ASIN原始数据'!M38="AMZ",1,0)) | I38: =IF(A38="","",IF('02_ASIN原始数据'!E38="", "",RANK('02_ASIN原始数据'!E38,'02_ASIN原始数据'!$E$3:$E$52,0))) | J38: =IF(A38="","",MIN(10,IF('02_ASIN原始数据'!J38<=300,10,IF('02_ASIN原始数据'!J38<=800,8,IF('02_ASIN原始数据'!J38<=1500,5,IF('02_ASIN原始数据'!J38<=3000,2,0))))+IF('02_ASIN原始数据'!P38<=3,2,0)+IF(I38<=10,1,0))) | K38: =IF(A38="","",MIN(10,IF('02_ASIN原始数据'!F38>=50,10,IF('02_ASIN原始数据'!F38>=30,9,IF('02_ASIN原始数据'!F38>=15,7,IF('02_ASIN原始数据'!F38>=5,5,2))))+IF(C38=1,2,0))) | L38: =IF(A38="","",IF(E38=0,0,IF(D38=1,8,3)+IF('02_ASIN原始数据'!N38>='01_动态参数'!B12+10,2,IF('02_ASIN原始数据'!N38>='01_动态参数'!B12,1,0)))) | M38: =IF(A38="","",MIN(10,IF('02_ASIN原始数据'!J38<=500,10,IF('02_ASIN原始数据'!J38<=1000,7,IF('02_ASIN原始数据'!J38<=2000,4,1)))+IF(C38=1,2,0)+IF(OR('02_ASIN原始数据'!Q38="Y",'02_ASIN原始数据'!Q38="Yes",'02_ASIN原始数据'!Q38="YES"),1,0))) | N38: 38
A39: ='02_ASIN原始数据'!A39 | B39: =IF('02_ASIN原始数据'!L39="","",IF(ISNUMBER('02_ASIN原始数据'!L39),TODAY()-'02_ASIN原始数据'!L39,"")) | C39: =IF(OR(A39="",B39=""),"",IF(B39<='01_动态参数'!B15,1,0)) | D39: =IF(A39="","",IF(AND('02_ASIN原始数据'!D39>='01_动态参数'!B10,'02_ASIN原始数据'!D39<='01_动态参数'!B11),1,0)) | E39: =IF(A39="","",IF('02_ASIN原始数据'!N39>='01_动态参数'!B12,1,0)) | F39: =IF(A39="","",IF('02_ASIN原始数据'!J39>'01_动态参数'!B13,1,0)) | G39: =IF(A39="","",IF('02_ASIN原始数据'!F39>='01_动态参数'!B14,1,0)) | H39: =IF(A39="","",IF('02_ASIN原始数据'!M39="AMZ",1,0)) | I39: =IF(A39="","",IF('02_ASIN原始数据'!E39="", "",RANK('02_ASIN原始数据'!E39,'02_ASIN原始数据'!$E$3:$E$52,0))) | J39: =IF(A39="","",MIN(10,IF('02_ASIN原始数据'!J39<=300,10,IF('02_ASIN原始数据'!J39<=800,8,IF('02_ASIN原始数据'!J39<=1500,5,IF('02_ASIN原始数据'!J39<=3000,2,0))))+IF('02_ASIN原始数据'!P39<=3,2,0)+IF(I39<=10,1,0))) | K39: =IF(A39="","",MIN(10,IF('02_ASIN原始数据'!F39>=50,10,IF('02_ASIN原始数据'!F39>=30,9,IF('02_ASIN原始数据'!F39>=15,7,IF('02_ASIN原始数据'!F39>=5,5,2))))+IF(C39=1,2,0))) | L39: =IF(A39="","",IF(E39=0,0,IF(D39=1,8,3)+IF('02_ASIN原始数据'!N39>='01_动态参数'!B12+10,2,IF('02_ASIN原始数据'!N39>='01_动态参数'!B12,1,0)))) | M39: =IF(A39="","",MIN(10,IF('02_ASIN原始数据'!J39<=500,10,IF('02_ASIN原始数据'!J39<=1000,7,IF('02_ASIN原始数据'!J39<=2000,4,1)))+IF(C39=1,2,0)+IF(OR('02_ASIN原始数据'!Q39="Y",'02_ASIN原始数据'!Q39="Yes",'02_ASIN原始数据'!Q39="YES"),1,0))) | N39: 39
A40: ='02_ASIN原始数据'!A40 | B40: =IF('02_ASIN原始数据'!L40="","",IF(ISNUMBER('02_ASIN原始数据'!L40),TODAY()-'02_ASIN原始数据'!L40,"")) | C40: =IF(OR(A40="",B40=""),"",IF(B40<='01_动态参数'!B15,1,0)) | D40: =IF(A40="","",IF(AND('02_ASIN原始数据'!D40>='01_动态参数'!B10,'02_ASIN原始数据'!D40<='01_动态参数'!B11),1,0)) | E40: =IF(A40="","",IF('02_ASIN原始数据'!N40>='01_动态参数'!B12,1,0)) | F40: =IF(A40="","",IF('02_ASIN原始数据'!J40>'01_动态参数'!B13,1,0)) | G40: =IF(A40="","",IF('02_ASIN原始数据'!F40>='01_动态参数'!B14,1,0)) | H40: =IF(A40="","",IF('02_ASIN原始数据'!M40="AMZ",1,0)) | I40: =IF(A40="","",IF('02_ASIN原始数据'!E40="", "",RANK('02_ASIN原始数据'!E40,'02_ASIN原始数据'!$E$3:$E$52,0))) | J40: =IF(A40="","",MIN(10,IF('02_ASIN原始数据'!J40<=300,10,IF('02_ASIN原始数据'!J40<=800,8,IF('02_ASIN原始数据'!J40<=1500,5,IF('02_ASIN原始数据'!J40<=3000,2,0))))+IF('02_ASIN原始数据'!P40<=3,2,0)+IF(I40<=10,1,0))) | K40: =IF(A40="","",MIN(10,IF('02_ASIN原始数据'!F40>=50,10,IF('02_ASIN原始数据'!F40>=30,9,IF('02_ASIN原始数据'!F40>=15,7,IF('02_ASIN原始数据'!F40>=5,5,2))))+IF(C40=1,2,0))) | L40: =IF(A40="","",IF(E40=0,0,IF(D40=1,8,3)+IF('02_ASIN原始数据'!N40>='01_动态参数'!B12+10,2,IF('02_ASIN原始数据'!N40>='01_动态参数'!B12,1,0)))) | M40: =IF(A40="","",MIN(10,IF('02_ASIN原始数据'!J40<=500,10,IF('02_ASIN原始数据'!J40<=1000,7,IF('02_ASIN原始数据'!J40<=2000,4,1)))+IF(C40=1,2,0)+IF(OR('02_ASIN原始数据'!Q40="Y",'02_ASIN原始数据'!Q40="Yes",'02_ASIN原始数据'!Q40="YES"),1,0))) | N40: 40
A41: ='02_ASIN原始数据'!A41 | B41: =IF('02_ASIN原始数据'!L41="","",IF(ISNUMBER('02_ASIN原始数据'!L41),TODAY()-'02_ASIN原始数据'!L41,"")) | C41: =IF(OR(A41="",B41=""),"",IF(B41<='01_动态参数'!B15,1,0)) | D41: =IF(A41="","",IF(AND('02_ASIN原始数据'!D41>='01_动态参数'!B10,'02_ASIN原始数据'!D41<='01_动态参数'!B11),1,0)) | E41: =IF(A41="","",IF('02_ASIN原始数据'!N41>='01_动态参数'!B12,1,0)) | F41: =IF(A41="","",IF('02_ASIN原始数据'!J41>'01_动态参数'!B13,1,0)) | G41: =IF(A41="","",IF('02_ASIN原始数据'!F41>='01_动态参数'!B14,1,0)) | H41: =IF(A41="","",IF('02_ASIN原始数据'!M41="AMZ",1,0)) | I41: =IF(A41="","",IF('02_ASIN原始数据'!E41="", "",RANK('02_ASIN原始数据'!E41,'02_ASIN原始数据'!$E$3:$E$52,0))) | J41: =IF(A41="","",MIN(10,IF('02_ASIN原始数据'!J41<=300,10,IF('02_ASIN原始数据'!J41<=800,8,IF('02_ASIN原始数据'!J41<=1500,5,IF('02_ASIN原始数据'!J41<=3000,2,0))))+IF('02_ASIN原始数据'!P41<=3,2,0)+IF(I41<=10,1,0))) | K41: =IF(A41="","",MIN(10,IF('02_ASIN原始数据'!F41>=50,10,IF('02_ASIN原始数据'!F41>=30,9,IF('02_ASIN原始数据'!F41>=15,7,IF('02_ASIN原始数据'!F41>=5,5,2))))+IF(C41=1,2,0))) | L41: =IF(A41="","",IF(E41=0,0,IF(D41=1,8,3)+IF('02_ASIN原始数据'!N41>='01_动态参数'!B12+10,2,IF('02_ASIN原始数据'!N41>='01_动态参数'!B12,1,0)))) | M41: =IF(A41="","",MIN(10,IF('02_ASIN原始数据'!J41<=500,10,IF('02_ASIN原始数据'!J41<=1000,7,IF('02_ASIN原始数据'!J41<=2000,4,1)))+IF(C41=1,2,0)+IF(OR('02_ASIN原始数据'!Q41="Y",'02_ASIN原始数据'!Q41="Yes",'02_ASIN原始数据'!Q41="YES"),1,0))) | N41: 41
A42: ='02_ASIN原始数据'!A42 | B42: =IF('02_ASIN原始数据'!L42="","",IF(ISNUMBER('02_ASIN原始数据'!L42),TODAY()-'02_ASIN原始数据'!L42,"")) | C42: =IF(OR(A42="",B42=""),"",IF(B42<='01_动态参数'!B15,1,0)) | D42: =IF(A42="","",IF(AND('02_ASIN原始数据'!D42>='01_动态参数'!B10,'02_ASIN原始数据'!D42<='01_动态参数'!B11),1,0)) | E42: =IF(A42="","",IF('02_ASIN原始数据'!N42>='01_动态参数'!B12,1,0)) | F42: =IF(A42="","",IF('02_ASIN原始数据'!J42>'01_动态参数'!B13,1,0)) | G42: =IF(A42="","",IF('02_ASIN原始数据'!F42>='01_动态参数'!B14,1,0)) | H42: =IF(A42="","",IF('02_ASIN原始数据'!M42="AMZ",1,0)) | I42: =IF(A42="","",IF('02_ASIN原始数据'!E42="", "",RANK('02_ASIN原始数据'!E42,'02_ASIN原始数据'!$E$3:$E$52,0))) | J42: =IF(A42="","",MIN(10,IF('02_ASIN原始数据'!J42<=300,10,IF('02_ASIN原始数据'!J42<=800,8,IF('02_ASIN原始数据'!J42<=1500,5,IF('02_ASIN原始数据'!J42<=3000,2,0))))+IF('02_ASIN原始数据'!P42<=3,2,0)+IF(I42<=10,1,0))) | K42: =IF(A42="","",MIN(10,IF('02_ASIN原始数据'!F42>=50,10,IF('02_ASIN原始数据'!F42>=30,9,IF('02_ASIN原始数据'!F42>=15,7,IF('02_ASIN原始数据'!F42>=5,5,2))))+IF(C42=1,2,0))) | L42: =IF(A42="","",IF(E42=0,0,IF(D42=1,8,3)+IF('02_ASIN原始数据'!N42>='01_动态参数'!B12+10,2,IF('02_ASIN原始数据'!N42>='01_动态参数'!B12,1,0)))) | M42: =IF(A42="","",MIN(10,IF('02_ASIN原始数据'!J42<=500,10,IF('02_ASIN原始数据'!J42<=1000,7,IF('02_ASIN原始数据'!J42<=2000,4,1)))+IF(C42=1,2,0)+IF(OR('02_ASIN原始数据'!Q42="Y",'02_ASIN原始数据'!Q42="Yes",'02_ASIN原始数据'!Q42="YES"),1,0))) | N42: 42
A43: ='02_ASIN原始数据'!A43 | B43: =IF('02_ASIN原始数据'!L43="","",IF(ISNUMBER('02_ASIN原始数据'!L43),TODAY()-'02_ASIN原始数据'!L43,"")) | C43: =IF(OR(A43="",B43=""),"",IF(B43<='01_动态参数'!B15,1,0)) | D43: =IF(A43="","",IF(AND('02_ASIN原始数据'!D43>='01_动态参数'!B10,'02_ASIN原始数据'!D43<='01_动态参数'!B11),1,0)) | E43: =IF(A43="","",IF('02_ASIN原始数据'!N43>='01_动态参数'!B12,1,0)) | F43: =IF(A43="","",IF('02_ASIN原始数据'!J43>'01_动态参数'!B13,1,0)) | G43: =IF(A43="","",IF('02_ASIN原始数据'!F43>='01_动态参数'!B14,1,0)) | H43: =IF(A43="","",IF('02_ASIN原始数据'!M43="AMZ",1,0)) | I43: =IF(A43="","",IF('02_ASIN原始数据'!E43="", "",RANK('02_ASIN原始数据'!E43,'02_ASIN原始数据'!$E$3:$E$52,0))) | J43: =IF(A43="","",MIN(10,IF('02_ASIN原始数据'!J43<=300,10,IF('02_ASIN原始数据'!J43<=800,8,IF('02_ASIN原始数据'!J43<=1500,5,IF('02_ASIN原始数据'!J43<=3000,2,0))))+IF('02_ASIN原始数据'!P43<=3,2,0)+IF(I43<=10,1,0))) | K43: =IF(A43="","",MIN(10,IF('02_ASIN原始数据'!F43>=50,10,IF('02_ASIN原始数据'!F43>=30,9,IF('02_ASIN原始数据'!F43>=15,7,IF('02_ASIN原始数据'!F43>=5,5,2))))+IF(C43=1,2,0))) | L43: =IF(A43="","",IF(E43=0,0,IF(D43=1,8,3)+IF('02_ASIN原始数据'!N43>='01_动态参数'!B12+10,2,IF('02_ASIN原始数据'!N43>='01_动态参数'!B12,1,0)))) | M43: =IF(A43="","",MIN(10,IF('02_ASIN原始数据'!J43<=500,10,IF('02_ASIN原始数据'!J43<=1000,7,IF('02_ASIN原始数据'!J43<=2000,4,1)))+IF(C43=1,2,0)+IF(OR('02_ASIN原始数据'!Q43="Y",'02_ASIN原始数据'!Q43="Yes",'02_ASIN原始数据'!Q43="YES"),1,0))) | N43: 43
A44: ='02_ASIN原始数据'!A44 | B44: =IF('02_ASIN原始数据'!L44="","",IF(ISNUMBER('02_ASIN原始数据'!L44),TODAY()-'02_ASIN原始数据'!L44,"")) | C44: =IF(OR(A44="",B44=""),"",IF(B44<='01_动态参数'!B15,1,0)) | D44: =IF(A44="","",IF(AND('02_ASIN原始数据'!D44>='01_动态参数'!B10,'02_ASIN原始数据'!D44<='01_动态参数'!B11),1,0)) | E44: =IF(A44="","",IF('02_ASIN原始数据'!N44>='01_动态参数'!B12,1,0)) | F44: =IF(A44="","",IF('02_ASIN原始数据'!J44>'01_动态参数'!B13,1,0)) | G44: =IF(A44="","",IF('02_ASIN原始数据'!F44>='01_动态参数'!B14,1,0)) | H44: =IF(A44="","",IF('02_ASIN原始数据'!M44="AMZ",1,0)) | I44: =IF(A44="","",IF('02_ASIN原始数据'!E44="", "",RANK('02_ASIN原始数据'!E44,'02_ASIN原始数据'!$E$3:$E$52,0))) | J44: =IF(A44="","",MIN(10,IF('02_ASIN原始数据'!J44<=300,10,IF('02_ASIN原始数据'!J44<=800,8,IF('02_ASIN原始数据'!J44<=1500,5,IF('02_ASIN原始数据'!J44<=3000,2,0))))+IF('02_ASIN原始数据'!P44<=3,2,0)+IF(I44<=10,1,0))) | K44: =IF(A44="","",MIN(10,IF('02_ASIN原始数据'!F44>=50,10,IF('02_ASIN原始数据'!F44>=30,9,IF('02_ASIN原始数据'!F44>=15,7,IF('02_ASIN原始数据'!F44>=5,5,2))))+IF(C44=1,2,0))) | L44: =IF(A44="","",IF(E44=0,0,IF(D44=1,8,3)+IF('02_ASIN原始数据'!N44>='01_动态参数'!B12+10,2,IF('02_ASIN原始数据'!N44>='01_动态参数'!B12,1,0)))) | M44: =IF(A44="","",MIN(10,IF('02_ASIN原始数据'!J44<=500,10,IF('02_ASIN原始数据'!J44<=1000,7,IF('02_ASIN原始数据'!J44<=2000,4,1)))+IF(C44=1,2,0)+IF(OR('02_ASIN原始数据'!Q44="Y",'02_ASIN原始数据'!Q44="Yes",'02_ASIN原始数据'!Q44="YES"),1,0))) | N44: 44
A45: ='02_ASIN原始数据'!A45 | B45: =IF('02_ASIN原始数据'!L45="","",IF(ISNUMBER('02_ASIN原始数据'!L45),TODAY()-'02_ASIN原始数据'!L45,"")) | C45: =IF(OR(A45="",B45=""),"",IF(B45<='01_动态参数'!B15,1,0)) | D45: =IF(A45="","",IF(AND('02_ASIN原始数据'!D45>='01_动态参数'!B10,'02_ASIN原始数据'!D45<='01_动态参数'!B11),1,0)) | E45: =IF(A45="","",IF('02_ASIN原始数据'!N45>='01_动态参数'!B12,1,0)) | F45: =IF(A45="","",IF('02_ASIN原始数据'!J45>'01_动态参数'!B13,1,0)) | G45: =IF(A45="","",IF('02_ASIN原始数据'!F45>='01_动态参数'!B14,1,0)) | H45: =IF(A45="","",IF('02_ASIN原始数据'!M45="AMZ",1,0)) | I45: =IF(A45="","",IF('02_ASIN原始数据'!E45="", "",RANK('02_ASIN原始数据'!E45,'02_ASIN原始数据'!$E$3:$E$52,0))) | J45: =IF(A45="","",MIN(10,IF('02_ASIN原始数据'!J45<=300,10,IF('02_ASIN原始数据'!J45<=800,8,IF('02_ASIN原始数据'!J45<=1500,5,IF('02_ASIN原始数据'!J45<=3000,2,0))))+IF('02_ASIN原始数据'!P45<=3,2,0)+IF(I45<=10,1,0))) | K45: =IF(A45="","",MIN(10,IF('02_ASIN原始数据'!F45>=50,10,IF('02_ASIN原始数据'!F45>=30,9,IF('02_ASIN原始数据'!F45>=15,7,IF('02_ASIN原始数据'!F45>=5,5,2))))+IF(C45=1,2,0))) | L45: =IF(A45="","",IF(E45=0,0,IF(D45=1,8,3)+IF('02_ASIN原始数据'!N45>='01_动态参数'!B12+10,2,IF('02_ASIN原始数据'!N45>='01_动态参数'!B12,1,0)))) | M45: =IF(A45="","",MIN(10,IF('02_ASIN原始数据'!J45<=500,10,IF('02_ASIN原始数据'!J45<=1000,7,IF('02_ASIN原始数据'!J45<=2000,4,1)))+IF(C45=1,2,0)+IF(OR('02_ASIN原始数据'!Q45="Y",'02_ASIN原始数据'!Q45="Yes",'02_ASIN原始数据'!Q45="YES"),1,0))) | N45: 45
A46: ='02_ASIN原始数据'!A46 | B46: =IF('02_ASIN原始数据'!L46="","",IF(ISNUMBER('02_ASIN原始数据'!L46),TODAY()-'02_ASIN原始数据'!L46,"")) | C46: =IF(OR(A46="",B46=""),"",IF(B46<='01_动态参数'!B15,1,0)) | D46: =IF(A46="","",IF(AND('02_ASIN原始数据'!D46>='01_动态参数'!B10,'02_ASIN原始数据'!D46<='01_动态参数'!B11),1,0)) | E46: =IF(A46="","",IF('02_ASIN原始数据'!N46>='01_动态参数'!B12,1,0)) | F46: =IF(A46="","",IF('02_ASIN原始数据'!J46>'01_动态参数'!B13,1,0)) | G46: =IF(A46="","",IF('02_ASIN原始数据'!F46>='01_动态参数'!B14,1,0)) | H46: =IF(A46="","",IF('02_ASIN原始数据'!M46="AMZ",1,0)) | I46: =IF(A46="","",IF('02_ASIN原始数据'!E46="", "",RANK('02_ASIN原始数据'!E46,'02_ASIN原始数据'!$E$3:$E$52,0))) | J46: =IF(A46="","",MIN(10,IF('02_ASIN原始数据'!J46<=300,10,IF('02_ASIN原始数据'!J46<=800,8,IF('02_ASIN原始数据'!J46<=1500,5,IF('02_ASIN原始数据'!J46<=3000,2,0))))+IF('02_ASIN原始数据'!P46<=3,2,0)+IF(I46<=10,1,0))) | K46: =IF(A46="","",MIN(10,IF('02_ASIN原始数据'!F46>=50,10,IF('02_ASIN原始数据'!F46>=30,9,IF('02_ASIN原始数据'!F46>=15,7,IF('02_ASIN原始数据'!F46>=5,5,2))))+IF(C46=1,2,0))) | L46: =IF(A46="","",IF(E46=0,0,IF(D46=1,8,3)+IF('02_ASIN原始数据'!N46>='01_动态参数'!B12+10,2,IF('02_ASIN原始数据'!N46>='01_动态参数'!B12,1,0)))) | M46: =IF(A46="","",MIN(10,IF('02_ASIN原始数据'!J46<=500,10,IF('02_ASIN原始数据'!J46<=1000,7,IF('02_ASIN原始数据'!J46<=2000,4,1)))+IF(C46=1,2,0)+IF(OR('02_ASIN原始数据'!Q46="Y",'02_ASIN原始数据'!Q46="Yes",'02_ASIN原始数据'!Q46="YES"),1,0))) | N46: 46
A47: ='02_ASIN原始数据'!A47 | B47: =IF('02_ASIN原始数据'!L47="","",IF(ISNUMBER('02_ASIN原始数据'!L47),TODAY()-'02_ASIN原始数据'!L47,"")) | C47: =IF(OR(A47="",B47=""),"",IF(B47<='01_动态参数'!B15,1,0)) | D47: =IF(A47="","",IF(AND('02_ASIN原始数据'!D47>='01_动态参数'!B10,'02_ASIN原始数据'!D47<='01_动态参数'!B11),1,0)) | E47: =IF(A47="","",IF('02_ASIN原始数据'!N47>='01_动态参数'!B12,1,0)) | F47: =IF(A47="","",IF('02_ASIN原始数据'!J47>'01_动态参数'!B13,1,0)) | G47: =IF(A47="","",IF('02_ASIN原始数据'!F47>='01_动态参数'!B14,1,0)) | H47: =IF(A47="","",IF('02_ASIN原始数据'!M47="AMZ",1,0)) | I47: =IF(A47="","",IF('02_ASIN原始数据'!E47="", "",RANK('02_ASIN原始数据'!E47,'02_ASIN原始数据'!$E$3:$E$52,0))) | J47: =IF(A47="","",MIN(10,IF('02_ASIN原始数据'!J47<=300,10,IF('02_ASIN原始数据'!J47<=800,8,IF('02_ASIN原始数据'!J47<=1500,5,IF('02_ASIN原始数据'!J47<=3000,2,0))))+IF('02_ASIN原始数据'!P47<=3,2,0)+IF(I47<=10,1,0))) | K47: =IF(A47="","",MIN(10,IF('02_ASIN原始数据'!F47>=50,10,IF('02_ASIN原始数据'!F47>=30,9,IF('02_ASIN原始数据'!F47>=15,7,IF('02_ASIN原始数据'!F47>=5,5,2))))+IF(C47=1,2,0))) | L47: =IF(A47="","",IF(E47=0,0,IF(D47=1,8,3)+IF('02_ASIN原始数据'!N47>='01_动态参数'!B12+10,2,IF('02_ASIN原始数据'!N47>='01_动态参数'!B12,1,0)))) | M47: =IF(A47="","",MIN(10,IF('02_ASIN原始数据'!J47<=500,10,IF('02_ASIN原始数据'!J47<=1000,7,IF('02_ASIN原始数据'!J47<=2000,4,1)))+IF(C47=1,2,0)+IF(OR('02_ASIN原始数据'!Q47="Y",'02_ASIN原始数据'!Q47="Yes",'02_ASIN原始数据'!Q47="YES"),1,0))) | N47: 47
A48: ='02_ASIN原始数据'!A48 | B48: =IF('02_ASIN原始数据'!L48="","",IF(ISNUMBER('02_ASIN原始数据'!L48),TODAY()-'02_ASIN原始数据'!L48,"")) | C48: =IF(OR(A48="",B48=""),"",IF(B48<='01_动态参数'!B15,1,0)) | D48: =IF(A48="","",IF(AND('02_ASIN原始数据'!D48>='01_动态参数'!B10,'02_ASIN原始数据'!D48<='01_动态参数'!B11),1,0)) | E48: =IF(A48="","",IF('02_ASIN原始数据'!N48>='01_动态参数'!B12,1,0)) | F48: =IF(A48="","",IF('02_ASIN原始数据'!J48>'01_动态参数'!B13,1,0)) | G48: =IF(A48="","",IF('02_ASIN原始数据'!F48>='01_动态参数'!B14,1,0)) | H48: =IF(A48="","",IF('02_ASIN原始数据'!M48="AMZ",1,0)) | I48: =IF(A48="","",IF('02_ASIN原始数据'!E48="", "",RANK('02_ASIN原始数据'!E48,'02_ASIN原始数据'!$E$3:$E$52,0))) | J48: =IF(A48="","",MIN(10,IF('02_ASIN原始数据'!J48<=300,10,IF('02_ASIN原始数据'!J48<=800,8,IF('02_ASIN原始数据'!J48<=1500,5,IF('02_ASIN原始数据'!J48<=3000,2,0))))+IF('02_ASIN原始数据'!P48<=3,2,0)+IF(I48<=10,1,0))) | K48: =IF(A48="","",MIN(10,IF('02_ASIN原始数据'!F48>=50,10,IF('02_ASIN原始数据'!F48>=30,9,IF('02_ASIN原始数据'!F48>=15,7,IF('02_ASIN原始数据'!F48>=5,5,2))))+IF(C48=1,2,0))) | L48: =IF(A48="","",IF(E48=0,0,IF(D48=1,8,3)+IF('02_ASIN原始数据'!N48>='01_动态参数'!B12+10,2,IF('02_ASIN原始数据'!N48>='01_动态参数'!B12,1,0)))) | M48: =IF(A48="","",MIN(10,IF('02_ASIN原始数据'!J48<=500,10,IF('02_ASIN原始数据'!J48<=1000,7,IF('02_ASIN原始数据'!J48<=2000,4,1)))+IF(C48=1,2,0)+IF(OR('02_ASIN原始数据'!Q48="Y",'02_ASIN原始数据'!Q48="Yes",'02_ASIN原始数据'!Q48="YES"),1,0))) | N48: 48
A49: ='02_ASIN原始数据'!A49 | B49: =IF('02_ASIN原始数据'!L49="","",IF(ISNUMBER('02_ASIN原始数据'!L49),TODAY()-'02_ASIN原始数据'!L49,"")) | C49: =IF(OR(A49="",B49=""),"",IF(B49<='01_动态参数'!B15,1,0)) | D49: =IF(A49="","",IF(AND('02_ASIN原始数据'!D49>='01_动态参数'!B10,'02_ASIN原始数据'!D49<='01_动态参数'!B11),1,0)) | E49: =IF(A49="","",IF('02_ASIN原始数据'!N49>='01_动态参数'!B12,1,0)) | F49: =IF(A49="","",IF('02_ASIN原始数据'!J49>'01_动态参数'!B13,1,0)) | G49: =IF(A49="","",IF('02_ASIN原始数据'!F49>='01_动态参数'!B14,1,0)) | H49: =IF(A49="","",IF('02_ASIN原始数据'!M49="AMZ",1,0)) | I49: =IF(A49="","",IF('02_ASIN原始数据'!E49="", "",RANK('02_ASIN原始数据'!E49,'02_ASIN原始数据'!$E$3:$E$52,0))) | J49: =IF(A49="","",MIN(10,IF('02_ASIN原始数据'!J49<=300,10,IF('02_ASIN原始数据'!J49<=800,8,IF('02_ASIN原始数据'!J49<=1500,5,IF('02_ASIN原始数据'!J49<=3000,2,0))))+IF('02_ASIN原始数据'!P49<=3,2,0)+IF(I49<=10,1,0))) | K49: =IF(A49="","",MIN(10,IF('02_ASIN原始数据'!F49>=50,10,IF('02_ASIN原始数据'!F49>=30,9,IF('02_ASIN原始数据'!F49>=15,7,IF('02_ASIN原始数据'!F49>=5,5,2))))+IF(C49=1,2,0))) | L49: =IF(A49="","",IF(E49=0,0,IF(D49=1,8,3)+IF('02_ASIN原始数据'!N49>='01_动态参数'!B12+10,2,IF('02_ASIN原始数据'!N49>='01_动态参数'!B12,1,0)))) | M49: =IF(A49="","",MIN(10,IF('02_ASIN原始数据'!J49<=500,10,IF('02_ASIN原始数据'!J49<=1000,7,IF('02_ASIN原始数据'!J49<=2000,4,1)))+IF(C49=1,2,0)+IF(OR('02_ASIN原始数据'!Q49="Y",'02_ASIN原始数据'!Q49="Yes",'02_ASIN原始数据'!Q49="YES"),1,0))) | N49: 49
A50: ='02_ASIN原始数据'!A50 | B50: =IF('02_ASIN原始数据'!L50="","",IF(ISNUMBER('02_ASIN原始数据'!L50),TODAY()-'02_ASIN原始数据'!L50,"")) | C50: =IF(OR(A50="",B50=""),"",IF(B50<='01_动态参数'!B15,1,0)) | D50: =IF(A50="","",IF(AND('02_ASIN原始数据'!D50>='01_动态参数'!B10,'02_ASIN原始数据'!D50<='01_动态参数'!B11),1,0)) | E50: =IF(A50="","",IF('02_ASIN原始数据'!N50>='01_动态参数'!B12,1,0)) | F50: =IF(A50="","",IF('02_ASIN原始数据'!J50>'01_动态参数'!B13,1,0)) | G50: =IF(A50="","",IF('02_ASIN原始数据'!F50>='01_动态参数'!B14,1,0)) | H50: =IF(A50="","",IF('02_ASIN原始数据'!M50="AMZ",1,0)) | I50: =IF(A50="","",IF('02_ASIN原始数据'!E50="", "",RANK('02_ASIN原始数据'!E50,'02_ASIN原始数据'!$E$3:$E$52,0))) | J50: =IF(A50="","",MIN(10,IF('02_ASIN原始数据'!J50<=300,10,IF('02_ASIN原始数据'!J50<=800,8,IF('02_ASIN原始数据'!J50<=1500,5,IF('02_ASIN原始数据'!J50<=3000,2,0))))+IF('02_ASIN原始数据'!P50<=3,2,0)+IF(I50<=10,1,0))) | K50: =IF(A50="","",MIN(10,IF('02_ASIN原始数据'!F50>=50,10,IF('02_ASIN原始数据'!F50>=30,9,IF('02_ASIN原始数据'!F50>=15,7,IF('02_ASIN原始数据'!F50>=5,5,2))))+IF(C50=1,2,0))) | L50: =IF(A50="","",IF(E50=0,0,IF(D50=1,8,3)+IF('02_ASIN原始数据'!N50>='01_动态参数'!B12+10,2,IF('02_ASIN原始数据'!N50>='01_动态参数'!B12,1,0)))) | M50: =IF(A50="","",MIN(10,IF('02_ASIN原始数据'!J50<=500,10,IF('02_ASIN原始数据'!J50<=1000,7,IF('02_ASIN原始数据'!J50<=2000,4,1)))+IF(C50=1,2,0)+IF(OR('02_ASIN原始数据'!Q50="Y",'02_ASIN原始数据'!Q50="Yes",'02_ASIN原始数据'!Q50="YES"),1,0))) | N50: 50
A51: ='02_ASIN原始数据'!A51 | B51: =IF('02_ASIN原始数据'!L51="","",IF(ISNUMBER('02_ASIN原始数据'!L51),TODAY()-'02_ASIN原始数据'!L51,"")) | C51: =IF(OR(A51="",B51=""),"",IF(B51<='01_动态参数'!B15,1,0)) | D51: =IF(A51="","",IF(AND('02_ASIN原始数据'!D51>='01_动态参数'!B10,'02_ASIN原始数据'!D51<='01_动态参数'!B11),1,0)) | E51: =IF(A51="","",IF('02_ASIN原始数据'!N51>='01_动态参数'!B12,1,0)) | F51: =IF(A51="","",IF('02_ASIN原始数据'!J51>'01_动态参数'!B13,1,0)) | G51: =IF(A51="","",IF('02_ASIN原始数据'!F51>='01_动态参数'!B14,1,0)) | H51: =IF(A51="","",IF('02_ASIN原始数据'!M51="AMZ",1,0)) | I51: =IF(A51="","",IF('02_ASIN原始数据'!E51="", "",RANK('02_ASIN原始数据'!E51,'02_ASIN原始数据'!$E$3:$E$52,0))) | J51: =IF(A51="","",MIN(10,IF('02_ASIN原始数据'!J51<=300,10,IF('02_ASIN原始数据'!J51<=800,8,IF('02_ASIN原始数据'!J51<=1500,5,IF('02_ASIN原始数据'!J51<=3000,2,0))))+IF('02_ASIN原始数据'!P51<=3,2,0)+IF(I51<=10,1,0))) | K51: =IF(A51="","",MIN(10,IF('02_ASIN原始数据'!F51>=50,10,IF('02_ASIN原始数据'!F51>=30,9,IF('02_ASIN原始数据'!F51>=15,7,IF('02_ASIN原始数据'!F51>=5,5,2))))+IF(C51=1,2,0))) | L51: =IF(A51="","",IF(E51=0,0,IF(D51=1,8,3)+IF('02_ASIN原始数据'!N51>='01_动态参数'!B12+10,2,IF('02_ASIN原始数据'!N51>='01_动态参数'!B12,1,0)))) | M51: =IF(A51="","",MIN(10,IF('02_ASIN原始数据'!J51<=500,10,IF('02_ASIN原始数据'!J51<=1000,7,IF('02_ASIN原始数据'!J51<=2000,4,1)))+IF(C51=1,2,0)+IF(OR('02_ASIN原始数据'!Q51="Y",'02_ASIN原始数据'!Q51="Yes",'02_ASIN原始数据'!Q51="YES"),1,0))) | N51: 51
A52: ='02_ASIN原始数据'!A52 | B52: =IF('02_ASIN原始数据'!L52="","",IF(ISNUMBER('02_ASIN原始数据'!L52),TODAY()-'02_ASIN原始数据'!L52,"")) | C52: =IF(OR(A52="",B52=""),"",IF(B52<='01_动态参数'!B15,1,0)) | D52: =IF(A52="","",IF(AND('02_ASIN原始数据'!D52>='01_动态参数'!B10,'02_ASIN原始数据'!D52<='01_动态参数'!B11),1,0)) | E52: =IF(A52="","",IF('02_ASIN原始数据'!N52>='01_动态参数'!B12,1,0)) | F52: =IF(A52="","",IF('02_ASIN原始数据'!J52>'01_动态参数'!B13,1,0)) | G52: =IF(A52="","",IF('02_ASIN原始数据'!F52>='01_动态参数'!B14,1,0)) | H52: =IF(A52="","",IF('02_ASIN原始数据'!M52="AMZ",1,0)) | I52: =IF(A52="","",IF('02_ASIN原始数据'!E52="", "",RANK('02_ASIN原始数据'!E52,'02_ASIN原始数据'!$E$3:$E$52,0))) | J52: =IF(A52="","",MIN(10,IF('02_ASIN原始数据'!J52<=300,10,IF('02_ASIN原始数据'!J52<=800,8,IF('02_ASIN原始数据'!J52<=1500,5,IF('02_ASIN原始数据'!J52<=3000,2,0))))+IF('02_ASIN原始数据'!P52<=3,2,0)+IF(I52<=10,1,0))) | K52: =IF(A52="","",MIN(10,IF('02_ASIN原始数据'!F52>=50,10,IF('02_ASIN原始数据'!F52>=30,9,IF('02_ASIN原始数据'!F52>=15,7,IF('02_ASIN原始数据'!F52>=5,5,2))))+IF(C52=1,2,0))) | L52: =IF(A52="","",IF(E52=0,0,IF(D52=1,8,3)+IF('02_ASIN原始数据'!N52>='01_动态参数'!B12+10,2,IF('02_ASIN原始数据'!N52>='01_动态参数'!B12,1,0)))) | M52: =IF(A52="","",MIN(10,IF('02_ASIN原始数据'!J52<=500,10,IF('02_ASIN原始数据'!J52<=1000,7,IF('02_ASIN原始数据'!J52<=2000,4,1)))+IF(C52=1,2,0)+IF(OR('02_ASIN原始数据'!Q52="Y",'02_ASIN原始数据'!Q52="Yes",'02_ASIN原始数据'!Q52="YES"),1,0))) | N52: 52

Sheet 04_最终评分
A1: 最终评分 + 一票否决高亮（自动计算）
A2: =IF('00_客户期望配置'!B25="【已完成】可以进入评分","","【警告】请先到「00_客户期望配置」完成所有填写并确认，否则本表结果无效")
A3: asin | B3: title | C3: 低竞争得分 | D3: 生命周期得分 | E3: 利润健康得分 | F3: 准入门槛得分 | G3: 加权总分 | H3: 一票否决 | I3: 推荐等级 | J3: 自动理由 | K3: brand | L3: price
A4: ='03_衍生指标'!A3 | B4: ='02_ASIN原始数据'!B3 | C4: ='03_衍生指标'!J3 | D4: ='03_衍生指标'!K3 | E4: ='03_衍生指标'!L3 | F4: ='03_衍生指标'!M3 | G4: =IF(A4="","",C4*'01_动态参数'!B4+D4*'01_动态参数'!B5+E4*'01_动态参数'!B6+F4*'01_动态参数'!B7) | H4: =IF(A4="","",IF(OR('03_衍生指标'!F3=1,'03_衍生指标'!G3=0,'03_衍生指标'!E3=0,AND('03_衍生指标'!H3=1,'01_动态参数'!B16=1)),"否决","通过")) | I4: =IF(A4="","",IF(H4="否决","淘汰",IF(G4>=8,"S",IF(G4>=7,"A",IF(G4>=6,"B",IF(G4>=5,"C","淘汰")))))) | J4: =IF(A4="","",IF(H4="否决","触发否决："&IF('03_衍生指标'!F3=1,"评分数超限 ","")&IF('03_衍生指标'!G3=0,"增长率不达标 ","")&IF('03_衍生指标'!E3=0,"毛利率不足 ","")&IF(AND('03_衍生指标'!H3=1,'01_动态参数'!B16=1),"自营不接受",""),"推荐：竞争/增长/利润/门槛综合达标")) | K4: ='02_ASIN原始数据'!C3 | L4: ='02_ASIN原始数据'!D3
A5: ='03_衍生指标'!A4 | B5: ='02_ASIN原始数据'!B4 | C5: ='03_衍生指标'!J4 | D5: ='03_衍生指标'!K4 | E5: ='03_衍生指标'!L4 | F5: ='03_衍生指标'!M4 | G5: =IF(A5="","",C5*'01_动态参数'!B4+D5*'01_动态参数'!B5+E5*'01_动态参数'!B6+F5*'01_动态参数'!B7) | H5: =IF(A5="","",IF(OR('03_衍生指标'!F4=1,'03_衍生指标'!G4=0,'03_衍生指标'!E4=0,AND('03_衍生指标'!H4=1,'01_动态参数'!B16=1)),"否决","通过")) | I5: =IF(A5="","",IF(H5="否决","淘汰",IF(G5>=8,"S",IF(G5>=7,"A",IF(G5>=6,"B",IF(G5>=5,"C","淘汰")))))) | J5: =IF(A5="","",IF(H5="否决","触发否决："&IF('03_衍生指标'!F4=1,"评分数超限 ","")&IF('03_衍生指标'!G4=0,"增长率不达标 ","")&IF('03_衍生指标'!E4=0,"毛利率不足 ","")&IF(AND('03_衍生指标'!H4=1,'01_动态参数'!B16=1),"自营不接受",""),"推荐：竞争/增长/利润/门槛综合达标")) | K5: ='02_ASIN原始数据'!C4 | L5: ='02_ASIN原始数据'!D4
A6: ='03_衍生指标'!A5 | B6: ='02_ASIN原始数据'!B5 | C6: ='03_衍生指标'!J5 | D6: ='03_衍生指标'!K5 | E6: ='03_衍生指标'!L5 | F6: ='03_衍生指标'!M5 | G6: =IF(A6="","",C6*'01_动态参数'!B4+D6*'01_动态参数'!B5+E6*'01_动态参数'!B6+F6*'01_动态参数'!B7) | H6: =IF(A6="","",IF(OR('03_衍生指标'!F5=1,'03_衍生指标'!G5=0,'03_衍生指标'!E5=0,AND('03_衍生指标'!H5=1,'01_动态参数'!B16=1)),"否决","通过")) | I6: =IF(A6="","",IF(H6="否决","淘汰",IF(G6>=8,"S",IF(G6>=7,"A",IF(G6>=6,"B",IF(G6>=5,"C","淘汰")))))) | J6: =IF(A6="","",IF(H6="否决","触发否决："&IF('03_衍生指标'!F5=1,"评分数超限 ","")&IF('03_衍生指标'!G5=0,"增长率不达标 ","")&IF('03_衍生指标'!E5=0,"毛利率不足 ","")&IF(AND('03_衍生指标'!H5=1,'01_动态参数'!B16=1),"自营不接受",""),"推荐：竞争/增长/利润/门槛综合达标")) | K6: ='02_ASIN原始数据'!C5 | L6: ='02_ASIN原始数据'!D5
A7: ='03_衍生指标'!A6 | B7: ='02_ASIN原始数据'!B6 | C7: ='03_衍生指标'!J6 | D7: ='03_衍生指标'!K6 | E7: ='03_衍生指标'!L6 | F7: ='03_衍生指标'!M6 | G7: =IF(A7="","",C7*'01_动态参数'!B4+D7*'01_动态参数'!B5+E7*'01_动态参数'!B6+F7*'01_动态参数'!B7) | H7: =IF(A7="","",IF(OR('03_衍生指标'!F6=1,'03_衍生指标'!G6=0,'03_衍生指标'!E6=0,AND('03_衍生指标'!H6=1,'01_动态参数'!B16=1)),"否决","通过")) | I7: =IF(A7="","",IF(H7="否决","淘汰",IF(G7>=8,"S",IF(G7>=7,"A",IF(G7>=6,"B",IF(G7>=5,"C","淘汰")))))) | J7: =IF(A7="","",IF(H7="否决","触发否决："&IF('03_衍生指标'!F6=1,"评分数超限 ","")&IF('03_衍生指标'!G6=0,"增长率不达标 ","")&IF('03_衍生指标'!E6=0,"毛利率不足 ","")&IF(AND('03_衍生指标'!H6=1,'01_动态参数'!B16=1),"自营不接受",""),"推荐：竞争/增长/利润/门槛综合达标")) | K7: ='02_ASIN原始数据'!C6 | L7: ='02_ASIN原始数据'!D6
A8: ='03_衍生指标'!A7 | B8: ='02_ASIN原始数据'!B7 | C8: ='03_衍生指标'!J7 | D8: ='03_衍生指标'!K7 | E8: ='03_衍生指标'!L7 | F8: ='03_衍生指标'!M7 | G8: =IF(A8="","",C8*'01_动态参数'!B4+D8*'01_动态参数'!B5+E8*'01_动态参数'!B6+F8*'01_动态参数'!B7) | H8: =IF(A8="","",IF(OR('03_衍生指标'!F7=1,'03_衍生指标'!G7=0,'03_衍生指标'!E7=0,AND('03_衍生指标'!H7=1,'01_动态参数'!B16=1)),"否决","通过")) | I8: =IF(A8="","",IF(H8="否决","淘汰",IF(G8>=8,"S",IF(G8>=7,"A",IF(G8>=6,"B",IF(G8>=5,"C","淘汰")))))) | J8: =IF(A8="","",IF(H8="否决","触发否决："&IF('03_衍生指标'!F7=1,"评分数超限 ","")&IF('03_衍生指标'!G7=0,"增长率不达标 ","")&IF('03_衍生指标'!E7=0,"毛利率不足 ","")&IF(AND('03_衍生指标'!H7=1,'01_动态参数'!B16=1),"自营不接受",""),"推荐：竞争/增长/利润/门槛综合达标")) | K8: ='02_ASIN原始数据'!C7 | L8: ='02_ASIN原始数据'!D7
A9: ='03_衍生指标'!A8 | B9: ='02_ASIN原始数据'!B8 | C9: ='03_衍生指标'!J8 | D9: ='03_衍生指标'!K8 | E9: ='03_衍生指标'!L8 | F9: ='03_衍生指标'!M8 | G9: =IF(A9="","",C9*'01_动态参数'!B4+D9*'01_动态参数'!B5+E9*'01_动态参数'!B6+F9*'01_动态参数'!B7) | H9: =IF(A9="","",IF(OR('03_衍生指标'!F8=1,'03_衍生指标'!G8=0,'03_衍生指标'!E8=0,AND('03_衍生指标'!H8=1,'01_动态参数'!B16=1)),"否决","通过")) | I9: =IF(A9="","",IF(H9="否决","淘汰",IF(G9>=8,"S",IF(G9>=7,"A",IF(G9>=6,"B",IF(G9>=5,"C","淘汰")))))) | J9: =IF(A9="","",IF(H9="否决","触发否决："&IF('03_衍生指标'!F8=1,"评分数超限 ","")&IF('03_衍生指标'!G8=0,"增长率不达标 ","")&IF('03_衍生指标'!E8=0,"毛利率不足 ","")&IF(AND('03_衍生指标'!H8=1,'01_动态参数'!B16=1),"自营不接受",""),"推荐：竞争/增长/利润/门槛综合达标")) | K9: ='02_ASIN原始数据'!C8 | L9: ='02_ASIN原始数据'!D8
A10: ='03_衍生指标'!A9 | B10: ='02_ASIN原始数据'!B9 | C10: ='03_衍生指标'!J9 | D10: ='03_衍生指标'!K9 | E10: ='03_衍生指标'!L9 | F10: ='03_衍生指标'!M9 | G10: =IF(A10="","",C10*'01_动态参数'!B4+D10*'01_动态参数'!B5+E10*'01_动态参数'!B6+F10*'01_动态参数'!B7) | H10: =IF(A10="","",IF(OR('03_衍生指标'!F9=1,'03_衍生指标'!G9=0,'03_衍生指标'!E9=0,AND('03_衍生指标'!H9=1,'01_动态参数'!B16=1)),"否决","通过")) | I10: =IF(A10="","",IF(H10="否决","淘汰",IF(G10>=8,"S",IF(G10>=7,"A",IF(G10>=6,"B",IF(G10>=5,"C","淘汰")))))) | J10: =IF(A10="","",IF(H10="否决","触发否决："&IF('03_衍生指标'!F9=1,"评分数超限 ","")&IF('03_衍生指标'!G9=0,"增长率不达标 ","")&IF('03_衍生指标'!E9=0,"毛利率不足 ","")&IF(AND('03_衍生指标'!H9=1,'01_动态参数'!B16=1),"自营不接受",""),"推荐：竞争/增长/利润/门槛综合达标")) | K10: ='02_ASIN原始数据'!C9 | L10: ='02_ASIN原始数据'!D9
A11: ='03_衍生指标'!A10 | B11: ='02_ASIN原始数据'!B10 | C11: ='03_衍生指标'!J10 | D11: ='03_衍生指标'!K10 | E11: ='03_衍生指标'!L10 | F11: ='03_衍生指标'!M10 | G11: =IF(A11="","",C11*'01_动态参数'!B4+D11*'01_动态参数'!B5+E11*'01_动态参数'!B6+F11*'01_动态参数'!B7) | H11: =IF(A11="","",IF(OR('03_衍生指标'!F10=1,'03_衍生指标'!G10=0,'03_衍生指标'!E10=0,AND('03_衍生指标'!H10=1,'01_动态参数'!B16=1)),"否决","通过")) | I11: =IF(A11="","",IF(H11="否决","淘汰",IF(G11>=8,"S",IF(G11>=7,"A",IF(G11>=6,"B",IF(G11>=5,"C","淘汰")))))) | J11: =IF(A11="","",IF(H11="否决","触发否决："&IF('03_衍生指标'!F10=1,"评分数超限 ","")&IF('03_衍生指标'!G10=0,"增长率不达标 ","")&IF('03_衍生指标'!E10=0,"毛利率不足 ","")&IF(AND('03_衍生指标'!H10=1,'01_动态参数'!B16=1),"自营不接受",""),"推荐：竞争/增长/利润/门槛综合达标")) | K11: ='02_ASIN原始数据'!C10 | L11: ='02_ASIN原始数据'!D10
A12: ='03_衍生指标'!A11 | B12: ='02_ASIN原始数据'!B11 | C12: ='03_衍生指标'!J11 | D12: ='03_衍生指标'!K11 | E12: ='03_衍生指标'!L11 | F12: ='03_衍生指标'!M11 | G12: =IF(A12="","",C12*'01_动态参数'!B4+D12*'01_动态参数'!B5+E12*'01_动态参数'!B6+F12*'01_动态参数'!B7) | H12: =IF(A12="","",IF(OR('03_衍生指标'!F11=1,'03_衍生指标'!G11=0,'03_衍生指标'!E11=0,AND('03_衍生指标'!H11=1,'01_动态参数'!B16=1)),"否决","通过")) | I12: =IF(A12="","",IF(H12="否决","淘汰",IF(G12>=8,"S",IF(G12>=7,"A",IF(G12>=6,"B",IF(G12>=5,"C","淘汰")))))) | J12: =IF(A12="","",IF(H12="否决","触发否决："&IF('03_衍生指标'!F11=1,"评分数超限 ","")&IF('03_衍生指标'!G11=0,"增长率不达标 ","")&IF('03_衍生指标'!E11=0,"毛利率不足 ","")&IF(AND('03_衍生指标'!H11=1,'01_动态参数'!B16=1),"自营不接受",""),"推荐：竞争/增长/利润/门槛综合达标")) | K12: ='02_ASIN原始数据'!C11 | L12: ='02_ASIN原始数据'!D11
A13: ='03_衍生指标'!A12 | B13: ='02_ASIN原始数据'!B12 | C13: ='03_衍生指标'!J12 | D13: ='03_衍生指标'!K12 | E13: ='03_衍生指标'!L12 | F13: ='03_衍生指标'!M12 | G13: =IF(A13="","",C13*'01_动态参数'!B4+D13*'01_动态参数'!B5+E13*'01_动态参数'!B6+F13*'01_动态参数'!B7) | H13: =IF(A13="","",IF(OR('03_衍生指标'!F12=1,'03_衍生指标'!G12=0,'03_衍生指标'!E12=0,AND('03_衍生指标'!H12=1,'01_动态参数'!B16=1)),"否决","通过")) | I13: =IF(A13="","",IF(H13="否决","淘汰",IF(G13>=8,"S",IF(G13>=7,"A",IF(G13>=6,"B",IF(G13>=5,"C","淘汰")))))) | J13: =IF(A13="","",IF(H13="否决","触发否决："&IF('03_衍生指标'!F12=1,"评分数超限 ","")&IF('03_衍生指标'!G12=0,"增长率不达标 ","")&IF('03_衍生指标'!E12=0,"毛利率不足 ","")&IF(AND('03_衍生指标'!H12=1,'01_动态参数'!B16=1),"自营不接受",""),"推荐：竞争/增长/利润/门槛综合达标")) | K13: ='02_ASIN原始数据'!C12 | L13: ='02_ASIN原始数据'!D12
A14: ='03_衍生指标'!A13 | B14: ='02_ASIN原始数据'!B13 | C14: ='03_衍生指标'!J13 | D14: ='03_衍生指标'!K13 | E14: ='03_衍生指标'!L13 | F14: ='03_衍生指标'!M13 | G14: =IF(A14="","",C14*'01_动态参数'!B4+D14*'01_动态参数'!B5+E14*'01_动态参数'!B6+F14*'01_动态参数'!B7) | H14: =IF(A14="","",IF(OR('03_衍生指标'!F13=1,'03_衍生指标'!G13=0,'03_衍生指标'!E13=0,AND('03_衍生指标'!H13=1,'01_动态参数'!B16=1)),"否决","通过")) | I14: =IF(A14="","",IF(H14="否决","淘汰",IF(G14>=8,"S",IF(G14>=7,"A",IF(G14>=6,"B",IF(G14>=5,"C","淘汰")))))) | J14: =IF(A14="","",IF(H14="否决","触发否决："&IF('03_衍生指标'!F13=1,"评分数超限 ","")&IF('03_衍生指标'!G13=0,"增长率不达标 ","")&IF('03_衍生指标'!E13=0,"毛利率不足 ","")&IF(AND('03_衍生指标'!H13=1,'01_动态参数'!B16=1),"自营不接受",""),"推荐：竞争/增长/利润/门槛综合达标")) | K14: ='02_ASIN原始数据'!C13 | L14: ='02_ASIN原始数据'!D13
A15: ='03_衍生指标'!A14 | B15: ='02_ASIN原始数据'!B14 | C15: ='03_衍生指标'!J14 | D15: ='03_衍生指标'!K14 | E15: ='03_衍生指标'!L14 | F15: ='03_衍生指标'!M14 | G15: =IF(A15="","",C15*'01_动态参数'!B4+D15*'01_动态参数'!B5+E15*'01_动态参数'!B6+F15*'01_动态参数'!B7) | H15: =IF(A15="","",IF(OR('03_衍生指标'!F14=1,'03_衍生指标'!G14=0,'03_衍生指标'!E14=0,AND('03_衍生指标'!H14=1,'01_动态参数'!B16=1)),"否决","通过")) | I15: =IF(A15="","",IF(H15="否决","淘汰",IF(G15>=8,"S",IF(G15>=7,"A",IF(G15>=6,"B",IF(G15>=5,"C","淘汰")))))) | J15: =IF(A15="","",IF(H15="否决","触发否决："&IF('03_衍生指标'!F14=1,"评分数超限 ","")&IF('03_衍生指标'!G14=0,"增长率不达标 ","")&IF('03_衍生指标'!E14=0,"毛利率不足 ","")&IF(AND('03_衍生指标'!H14=1,'01_动态参数'!B16=1),"自营不接受",""),"推荐：竞争/增长/利润/门槛综合达标")) | K15: ='02_ASIN原始数据'!C14 | L15: ='02_ASIN原始数据'!D14
A16: ='03_衍生指标'!A15 | B16: ='02_ASIN原始数据'!B15 | C16: ='03_衍生指标'!J15 | D16: ='03_衍生指标'!K15 | E16: ='03_衍生指标'!L15 | F16: ='03_衍生指标'!M15 | G16: =IF(A16="","",C16*'01_动态参数'!B4+D16*'01_动态参数'!B5+E16*'01_动态参数'!B6+F16*'01_动态参数'!B7) | H16: =IF(A16="","",IF(OR('03_衍生指标'!F15=1,'03_衍生指标'!G15=0,'03_衍生指标'!E15=0,AND('03_衍生指标'!H15=1,'01_动态参数'!B16=1)),"否决","通过")) | I16: =IF(A16="","",IF(H16="否决","淘汰",IF(G16>=8,"S",IF(G16>=7,"A",IF(G16>=6,"B",IF(G16>=5,"C","淘汰")))))) | J16: =IF(A16="","",IF(H16="否决","触发否决："&IF('03_衍生指标'!F15=1,"评分数超限 ","")&IF('03_衍生指标'!G15=0,"增长率不达标 ","")&IF('03_衍生指标'!E15=0,"毛利率不足 ","")&IF(AND('03_衍生指标'!H15=1,'01_动态参数'!B16=1),"自营不接受",""),"推荐：竞争/增长/利润/门槛综合达标")) | K16: ='02_ASIN原始数据'!C15 | L16: ='02_ASIN原始数据'!D15
A17: ='03_衍生指标'!A16 | B17: ='02_ASIN原始数据'!B16 | C17: ='03_衍生指标'!J16 | D17: ='03_衍生指标'!K16 | E17: ='03_衍生指标'!L16 | F17: ='03_衍生指标'!M16 | G17: =IF(A17="","",C17*'01_动态参数'!B4+D17*'01_动态参数'!B5+E17*'01_动态参数'!B6+F17*'01_动态参数'!B7) | H17: =IF(A17="","",IF(OR('03_衍生指标'!F16=1,'03_衍生指标'!G16=0,'03_衍生指标'!E16=0,AND('03_衍生指标'!H16=1,'01_动态参数'!B16=1)),"否决","通过")) | I17: =IF(A17="","",IF(H17="否决","淘汰",IF(G17>=8,"S",IF(G17>=7,"A",IF(G17>=6,"B",IF(G17>=5,"C","淘汰")))))) | J17: =IF(A17="","",IF(H17="否决","触发否决："&IF('03_衍生指标'!F16=1,"评分数超限 ","")&IF('03_衍生指标'!G16=0,"增长率不达标 ","")&IF('03_衍生指标'!E16=0,"毛利率不足 ","")&IF(AND('03_衍生指标'!H16=1,'01_动态参数'!B16=1),"自营不接受",""),"推荐：竞争/增长/利润/门槛综合达标")) | K17: ='02_ASIN原始数据'!C16 | L17: ='02_ASIN原始数据'!D16
A18: ='03_衍生指标'!A17 | B18: ='02_ASIN原始数据'!B17 | C18: ='03_衍生指标'!J17 | D18: ='03_衍生指标'!K17 | E18: ='03_衍生指标'!L17 | F18: ='03_衍生指标'!M17 | G18: =IF(A18="","",C18*'01_动态参数'!B4+D18*'01_动态参数'!B5+E18*'01_动态参数'!B6+F18*'01_动态参数'!B7) | H18: =IF(A18="","",IF(OR('03_衍生指标'!F17=1,'03_衍生指标'!G17=0,'03_衍生指标'!E17=0,AND('03_衍生指标'!H17=1,'01_动态参数'!B16=1)),"否决","通过")) | I18: =IF(A18="","",IF(H18="否决","淘汰",IF(G18>=8,"S",IF(G18>=7,"A",IF(G18>=6,"B",IF(G18>=5,"C","淘汰")))))) | J18: =IF(A18="","",IF(H18="否决","触发否决："&IF('03_衍生指标'!F17=1,"评分数超限 ","")&IF('03_衍生指标'!G17=0,"增长率不达标 ","")&IF('03_衍生指标'!E17=0,"毛利率不足 ","")&IF(AND('03_衍生指标'!H17=1,'01_动态参数'!B16=1),"自营不接受",""),"推荐：竞争/增长/利润/门槛综合达标")) | K18: ='02_ASIN原始数据'!C17 | L18: ='02_ASIN原始数据'!D17
A19: ='03_衍生指标'!A18 | B19: ='02_ASIN原始数据'!B18 | C19: ='03_衍生指标'!J18 | D19: ='03_衍生指标'!K18 | E19: ='03_衍生指标'!L18 | F19: ='03_衍生指标'!M18 | G19: =IF(A19="","",C19*'01_动态参数'!B4+D19*'01_动态参数'!B5+E19*'01_动态参数'!B6+F19*'01_动态参数'!B7) | H19: =IF(A19="","",IF(OR('03_衍生指标'!F18=1,'03_衍生指标'!G18=0,'03_衍生指标'!E18=0,AND('03_衍生指标'!H18=1,'01_动态参数'!B16=1)),"否决","通过")) | I19: =IF(A19="","",IF(H19="否决","淘汰",IF(G19>=8,"S",IF(G19>=7,"A",IF(G19>=6,"B",IF(G19>=5,"C","淘汰")))))) | J19: =IF(A19="","",IF(H19="否决","触发否决："&IF('03_衍生指标'!F18=1,"评分数超限 ","")&IF('03_衍生指标'!G18=0,"增长率不达标 ","")&IF('03_衍生指标'!E18=0,"毛利率不足 ","")&IF(AND('03_衍生指标'!H18=1,'01_动态参数'!B16=1),"自营不接受",""),"推荐：竞争/增长/利润/门槛综合达标")) | K19: ='02_ASIN原始数据'!C18 | L19: ='02_ASIN原始数据'!D18
A20: ='03_衍生指标'!A19 | B20: ='02_ASIN原始数据'!B19 | C20: ='03_衍生指标'!J19 | D20: ='03_衍生指标'!K19 | E20: ='03_衍生指标'!L19 | F20: ='03_衍生指标'!M19 | G20: =IF(A20="","",C20*'01_动态参数'!B4+D20*'01_动态参数'!B5+E20*'01_动态参数'!B6+F20*'01_动态参数'!B7) | H20: =IF(A20="","",IF(OR('03_衍生指标'!F19=1,'03_衍生指标'!G19=0,'03_衍生指标'!E19=0,AND('03_衍生指标'!H19=1,'01_动态参数'!B16=1)),"否决","通过")) | I20: =IF(A20="","",IF(H20="否决","淘汰",IF(G20>=8,"S",IF(G20>=7,"A",IF(G20>=6,"B",IF(G20>=5,"C","淘汰")))))) | J20: =IF(A20="","",IF(H20="否决","触发否决："&IF('03_衍生指标'!F19=1,"评分数超限 ","")&IF('03_衍生指标'!G19=0,"增长率不达标 ","")&IF('03_衍生指标'!E19=0,"毛利率不足 ","")&IF(AND('03_衍生指标'!H19=1,'01_动态参数'!B16=1),"自营不接受",""),"推荐：竞争/增长/利润/门槛综合达标")) | K20: ='02_ASIN原始数据'!C19 | L20: ='02_ASIN原始数据'!D19
A21: ='03_衍生指标'!A20 | B21: ='02_ASIN原始数据'!B20 | C21: ='03_衍生指标'!J20 | D21: ='03_衍生指标'!K20 | E21: ='03_衍生指标'!L20 | F21: ='03_衍生指标'!M20 | G21: =IF(A21="","",C21*'01_动态参数'!B4+D21*'01_动态参数'!B5+E21*'01_动态参数'!B6+F21*'01_动态参数'!B7) | H21: =IF(A21="","",IF(OR('03_衍生指标'!F20=1,'03_衍生指标'!G20=0,'03_衍生指标'!E20=0,AND('03_衍生指标'!H20=1,'01_动态参数'!B16=1)),"否决","通过")) | I21: =IF(A21="","",IF(H21="否决","淘汰",IF(G21>=8,"S",IF(G21>=7,"A",IF(G21>=6,"B",IF(G21>=5,"C","淘汰")))))) | J21: =IF(A21="","",IF(H21="否决","触发否决："&IF('03_衍生指标'!F20=1,"评分数超限 ","")&IF('03_衍生指标'!G20=0,"增长率不达标 ","")&IF('03_衍生指标'!E20=0,"毛利率不足 ","")&IF(AND('03_衍生指标'!H20=1,'01_动态参数'!B16=1),"自营不接受",""),"推荐：竞争/增长/利润/门槛综合达标")) | K21: ='02_ASIN原始数据'!C20 | L21: ='02_ASIN原始数据'!D20
A22: ='03_衍生指标'!A21 | B22: ='02_ASIN原始数据'!B21 | C22: ='03_衍生指标'!J21 | D22: ='03_衍生指标'!K21 | E22: ='03_衍生指标'!L21 | F22: ='03_衍生指标'!M21 | G22: =IF(A22="","",C22*'01_动态参数'!B4+D22*'01_动态参数'!B5+E22*'01_动态参数'!B6+F22*'01_动态参数'!B7) | H22: =IF(A22="","",IF(OR('03_衍生指标'!F21=1,'03_衍生指标'!G21=0,'03_衍生指标'!E21=0,AND('03_衍生指标'!H21=1,'01_动态参数'!B16=1)),"否决","通过")) | I22: =IF(A22="","",IF(H22="否决","淘汰",IF(G22>=8,"S",IF(G22>=7,"A",IF(G22>=6,"B",IF(G22>=5,"C","淘汰")))))) | J22: =IF(A22="","",IF(H22="否决","触发否决："&IF('03_衍生指标'!F21=1,"评分数超限 ","")&IF('03_衍生指标'!G21=0,"增长率不达标 ","")&IF('03_衍生指标'!E21=0,"毛利率不足 ","")&IF(AND('03_衍生指标'!H21=1,'01_动态参数'!B16=1),"自营不接受",""),"推荐：竞争/增长/利润/门槛综合达标")) | K22: ='02_ASIN原始数据'!C21 | L22: ='02_ASIN原始数据'!D21
A23: ='03_衍生指标'!A22 | B23: ='02_ASIN原始数据'!B22 | C23: ='03_衍生指标'!J22 | D23: ='03_衍生指标'!K22 | E23: ='03_衍生指标'!L22 | F23: ='03_衍生指标'!M22 | G23: =IF(A23="","",C23*'01_动态参数'!B4+D23*'01_动态参数'!B5+E23*'01_动态参数'!B6+F23*'01_动态参数'!B7) | H23: =IF(A23="","",IF(OR('03_衍生指标'!F22=1,'03_衍生指标'!G22=0,'03_衍生指标'!E22=0,AND('03_衍生指标'!H22=1,'01_动态参数'!B16=1)),"否决","通过")) | I23: =IF(A23="","",IF(H23="否决","淘汰",IF(G23>=8,"S",IF(G23>=7,"A",IF(G23>=6,"B",IF(G23>=5,"C","淘汰")))))) | J23: =IF(A23="","",IF(H23="否决","触发否决："&IF('03_衍生指标'!F22=1,"评分数超限 ","")&IF('03_衍生指标'!G22=0,"增长率不达标 ","")&IF('03_衍生指标'!E22=0,"毛利率不足 ","")&IF(AND('03_衍生指标'!H22=1,'01_动态参数'!B16=1),"自营不接受",""),"推荐：竞争/增长/利润/门槛综合达标")) | K23: ='02_ASIN原始数据'!C22 | L23: ='02_ASIN原始数据'!D22
A24: ='03_衍生指标'!A23 | B24: ='02_ASIN原始数据'!B23 | C24: ='03_衍生指标'!J23 | D24: ='03_衍生指标'!K23 | E24: ='03_衍生指标'!L23 | F24: ='03_衍生指标'!M23 | G24: =IF(A24="","",C24*'01_动态参数'!B4+D24*'01_动态参数'!B5+E24*'01_动态参数'!B6+F24*'01_动态参数'!B7) | H24: =IF(A24="","",IF(OR('03_衍生指标'!F23=1,'03_衍生指标'!G23=0,'03_衍生指标'!E23=0,AND('03_衍生指标'!H23=1,'01_动态参数'!B16=1)),"否决","通过")) | I24: =IF(A24="","",IF(H24="否决","淘汰",IF(G24>=8,"S",IF(G24>=7,"A",IF(G24>=6,"B",IF(G24>=5,"C","淘汰")))))) | J24: =IF(A24="","",IF(H24="否决","触发否决："&IF('03_衍生指标'!F23=1,"评分数超限 ","")&IF('03_衍生指标'!G23=0,"增长率不达标 ","")&IF('03_衍生指标'!E23=0,"毛利率不足 ","")&IF(AND('03_衍生指标'!H23=1,'01_动态参数'!B16=1),"自营不接受",""),"推荐：竞争/增长/利润/门槛综合达标")) | K24: ='02_ASIN原始数据'!C23 | L24: ='02_ASIN原始数据'!D23
A25: ='03_衍生指标'!A24 | B25: ='02_ASIN原始数据'!B24 | C25: ='03_衍生指标'!J24 | D25: ='03_衍生指标'!K24 | E25: ='03_衍生指标'!L24 | F25: ='03_衍生指标'!M24 | G25: =IF(A25="","",C25*'01_动态参数'!B4+D25*'01_动态参数'!B5+E25*'01_动态参数'!B6+F25*'01_动态参数'!B7) | H25: =IF(A25="","",IF(OR('03_衍生指标'!F24=1,'03_衍生指标'!G24=0,'03_衍生指标'!E24=0,AND('03_衍生指标'!H24=1,'01_动态参数'!B16=1)),"否决","通过")) | I25: =IF(A25="","",IF(H25="否决","淘汰",IF(G25>=8,"S",IF(G25>=7,"A",IF(G25>=6,"B",IF(G25>=5,"C","淘汰")))))) | J25: =IF(A25="","",IF(H25="否决","触发否决："&IF('03_衍生指标'!F24=1,"评分数超限 ","")&IF('03_衍生指标'!G24=0,"增长率不达标 ","")&IF('03_衍生指标'!E24=0,"毛利率不足 ","")&IF(AND('03_衍生指标'!H24=1,'01_动态参数'!B16=1),"自营不接受",""),"推荐：竞争/增长/利润/门槛综合达标")) | K25: ='02_ASIN原始数据'!C24 | L25: ='02_ASIN原始数据'!D24
A26: ='03_衍生指标'!A25 | B26: ='02_ASIN原始数据'!B25 | C26: ='03_衍生指标'!J25 | D26: ='03_衍生指标'!K25 | E26: ='03_衍生指标'!L25 | F26: ='03_衍生指标'!M25 | G26: =IF(A26="","",C26*'01_动态参数'!B4+D26*'01_动态参数'!B5+E26*'01_动态参数'!B6+F26*'01_动态参数'!B7) | H26: =IF(A26="","",IF(OR('03_衍生指标'!F25=1,'03_衍生指标'!G25=0,'03_衍生指标'!E25=0,AND('03_衍生指标'!H25=1,'01_动态参数'!B16=1)),"否决","通过")) | I26: =IF(A26="","",IF(H26="否决","淘汰",IF(G26>=8,"S",IF(G26>=7,"A",IF(G26>=6,"B",IF(G26>=5,"C","淘汰")))))) | J26: =IF(A26="","",IF(H26="否决","触发否决："&IF('03_衍生指标'!F25=1,"评分数超限 ","")&IF('03_衍生指标'!G25=0,"增长率不达标 ","")&IF('03_衍生指标'!E25=0,"毛利率不足 ","")&IF(AND('03_衍生指标'!H25=1,'01_动态参数'!B16=1),"自营不接受",""),"推荐：竞争/增长/利润/门槛综合达标")) | K26: ='02_ASIN原始数据'!C25 | L26: ='02_ASIN原始数据'!D25
A27: ='03_衍生指标'!A26 | B27: ='02_ASIN原始数据'!B26 | C27: ='03_衍生指标'!J26 | D27: ='03_衍生指标'!K26 | E27: ='03_衍生指标'!L26 | F27: ='03_衍生指标'!M26 | G27: =IF(A27="","",C27*'01_动态参数'!B4+D27*'01_动态参数'!B5+E27*'01_动态参数'!B6+F27*'01_动态参数'!B7) | H27: =IF(A27="","",IF(OR('03_衍生指标'!F26=1,'03_衍生指标'!G26=0,'03_衍生指标'!E26=0,AND('03_衍生指标'!H26=1,'01_动态参数'!B16=1)),"否决","通过")) | I27: =IF(A27="","",IF(H27="否决","淘汰",IF(G27>=8,"S",IF(G27>=7,"A",IF(G27>=6,"B",IF(G27>=5,"C","淘汰")))))) | J27: =IF(A27="","",IF(H27="否决","触发否决："&IF('03_衍生指标'!F26=1,"评分数超限 ","")&IF('03_衍生指标'!G26=0,"增长率不达标 ","")&IF('03_衍生指标'!E26=0,"毛利率不足 ","")&IF(AND('03_衍生指标'!H26=1,'01_动态参数'!B16=1),"自营不接受",""),"推荐：竞争/增长/利润/门槛综合达标")) | K27: ='02_ASIN原始数据'!C26 | L27: ='02_ASIN原始数据'!D26
A28: ='03_衍生指标'!A27 | B28: ='02_ASIN原始数据'!B27 | C28: ='03_衍生指标'!J27 | D28: ='03_衍生指标'!K27 | E28: ='03_衍生指标'!L27 | F28: ='03_衍生指标'!M27 | G28: =IF(A28="","",C28*'01_动态参数'!B4+D28*'01_动态参数'!B5+E28*'01_动态参数'!B6+F28*'01_动态参数'!B7) | H28: =IF(A28="","",IF(OR('03_衍生指标'!F27=1,'03_衍生指标'!G27=0,'03_衍生指标'!E27=0,AND('03_衍生指标'!H27=1,'01_动态参数'!B16=1)),"否决","通过")) | I28: =IF(A28="","",IF(H28="否决","淘汰",IF(G28>=8,"S",IF(G28>=7,"A",IF(G28>=6,"B",IF(G28>=5,"C","淘汰")))))) | J28: =IF(A28="","",IF(H28="否决","触发否决："&IF('03_衍生指标'!F27=1,"评分数超限 ","")&IF('03_衍生指标'!G27=0,"增长率不达标 ","")&IF('03_衍生指标'!E27=0,"毛利率不足 ","")&IF(AND('03_衍生指标'!H27=1,'01_动态参数'!B16=1),"自营不接受",""),"推荐：竞争/增长/利润/门槛综合达标")) | K28: ='02_ASIN原始数据'!C27 | L28: ='02_ASIN原始数据'!D27
A29: ='03_衍生指标'!A28 | B29: ='02_ASIN原始数据'!B28 | C29: ='03_衍生指标'!J28 | D29: ='03_衍生指标'!K28 | E29: ='03_衍生指标'!L28 | F29: ='03_衍生指标'!M28 | G29: =IF(A29="","",C29*'01_动态参数'!B4+D29*'01_动态参数'!B5+E29*'01_动态参数'!B6+F29*'01_动态参数'!B7) | H29: =IF(A29="","",IF(OR('03_衍生指标'!F28=1,'03_衍生指标'!G28=0,'03_衍生指标'!E28=0,AND('03_衍生指标'!H28=1,'01_动态参数'!B16=1)),"否决","通过")) | I29: =IF(A29="","",IF(H29="否决","淘汰",IF(G29>=8,"S",IF(G29>=7,"A",IF(G29>=6,"B",IF(G29>=5,"C","淘汰")))))) | J29: =IF(A29="","",IF(H29="否决","触发否决："&IF('03_衍生指标'!F28=1,"评分数超限 ","")&IF('03_衍生指标'!G28=0,"增长率不达标 ","")&IF('03_衍生指标'!E28=0,"毛利率不足 ","")&IF(AND('03_衍生指标'!H28=1,'01_动态参数'!B16=1),"自营不接受",""),"推荐：竞争/增长/利润/门槛综合达标")) | K29: ='02_ASIN原始数据'!C28 | L29: ='02_ASIN原始数据'!D28
A30: ='03_衍生指标'!A29 | B30: ='02_ASIN原始数据'!B29 | C30: ='03_衍生指标'!J29 | D30: ='03_衍生指标'!K29 | E30: ='03_衍生指标'!L29 | F30: ='03_衍生指标'!M29 | G30: =IF(A30="","",C30*'01_动态参数'!B4+D30*'01_动态参数'!B5+E30*'01_动态参数'!B6+F30*'01_动态参数'!B7) | H30: =IF(A30="","",IF(OR('03_衍生指标'!F29=1,'03_衍生指标'!G29=0,'03_衍生指标'!E29=0,AND('03_衍生指标'!H29=1,'01_动态参数'!B16=1)),"否决","通过")) | I30: =IF(A30="","",IF(H30="否决","淘汰",IF(G30>=8,"S",IF(G30>=7,"A",IF(G30>=6,"B",IF(G30>=5,"C","淘汰")))))) | J30: =IF(A30="","",IF(H30="否决","触发否决："&IF('03_衍生指标'!F29=1,"评分数超限 ","")&IF('03_衍生指标'!G29=0,"增长率不达标 ","")&IF('03_衍生指标'!E29=0,"毛利率不足 ","")&IF(AND('03_衍生指标'!H29=1,'01_动态参数'!B16=1),"自营不接受",""),"推荐：竞争/增长/利润/门槛综合达标")) | K30: ='02_ASIN原始数据'!C29 | L30: ='02_ASIN原始数据'!D29
A31: ='03_衍生指标'!A30 | B31: ='02_ASIN原始数据'!B30 | C31: ='03_衍生指标'!J30 | D31: ='03_衍生指标'!K30 | E31: ='03_衍生指标'!L30 | F31: ='03_衍生指标'!M30 | G31: =IF(A31="","",C31*'01_动态参数'!B4+D31*'01_动态参数'!B5+E31*'01_动态参数'!B6+F31*'01_动态参数'!B7) | H31: =IF(A31="","",IF(OR('03_衍生指标'!F30=1,'03_衍生指标'!G30=0,'03_衍生指标'!E30=0,AND('03_衍生指标'!H30=1,'01_动态参数'!B16=1)),"否决","通过")) | I31: =IF(A31="","",IF(H31="否决","淘汰",IF(G31>=8,"S",IF(G31>=7,"A",IF(G31>=6,"B",IF(G31>=5,"C","淘汰")))))) | J31: =IF(A31="","",IF(H31="否决","触发否决："&IF('03_衍生指标'!F30=1,"评分数超限 ","")&IF('03_衍生指标'!G30=0,"增长率不达标 ","")&IF('03_衍生指标'!E30=0,"毛利率不足 ","")&IF(AND('03_衍生指标'!H30=1,'01_动态参数'!B16=1),"自营不接受",""),"推荐：竞争/增长/利润/门槛综合达标")) | K31: ='02_ASIN原始数据'!C30 | L31: ='02_ASIN原始数据'!D30
A32: ='03_衍生指标'!A31 | B32: ='02_ASIN原始数据'!B31 | C32: ='03_衍生指标'!J31 | D32: ='03_衍生指标'!K31 | E32: ='03_衍生指标'!L31 | F32: ='03_衍生指标'!M31 | G32: =IF(A32="","",C32*'01_动态参数'!B4+D32*'01_动态参数'!B5+E32*'01_动态参数'!B6+F32*'01_动态参数'!B7) | H32: =IF(A32="","",IF(OR('03_衍生指标'!F31=1,'03_衍生指标'!G31=0,'03_衍生指标'!E31=0,AND('03_衍生指标'!H31=1,'01_动态参数'!B16=1)),"否决","通过")) | I32: =IF(A32="","",IF(H32="否决","淘汰",IF(G32>=8,"S",IF(G32>=7,"A",IF(G32>=6,"B",IF(G32>=5,"C","淘汰")))))) | J32: =IF(A32="","",IF(H32="否决","触发否决："&IF('03_衍生指标'!F31=1,"评分数超限 ","")&IF('03_衍生指标'!G31=0,"增长率不达标 ","")&IF('03_衍生指标'!E31=0,"毛利率不足 ","")&IF(AND('03_衍生指标'!H31=1,'01_动态参数'!B16=1),"自营不接受",""),"推荐：竞争/增长/利润/门槛综合达标")) | K32: ='02_ASIN原始数据'!C31 | L32: ='02_ASIN原始数据'!D31
A33: ='03_衍生指标'!A32 | B33: ='02_ASIN原始数据'!B32 | C33: ='03_衍生指标'!J32 | D33: ='03_衍生指标'!K32 | E33: ='03_衍生指标'!L32 | F33: ='03_衍生指标'!M32 | G33: =IF(A33="","",C33*'01_动态参数'!B4+D33*'01_动态参数'!B5+E33*'01_动态参数'!B6+F33*'01_动态参数'!B7) | H33: =IF(A33="","",IF(OR('03_衍生指标'!F32=1,'03_衍生指标'!G32=0,'03_衍生指标'!E32=0,AND('03_衍生指标'!H32=1,'01_动态参数'!B16=1)),"否决","通过")) | I33: =IF(A33="","",IF(H33="否决","淘汰",IF(G33>=8,"S",IF(G33>=7,"A",IF(G33>=6,"B",IF(G33>=5,"C","淘汰")))))) | J33: =IF(A33="","",IF(H33="否决","触发否决："&IF('03_衍生指标'!F32=1,"评分数超限 ","")&IF('03_衍生指标'!G32=0,"增长率不达标 ","")&IF('03_衍生指标'!E32=0,"毛利率不足 ","")&IF(AND('03_衍生指标'!H32=1,'01_动态参数'!B16=1),"自营不接受",""),"推荐：竞争/增长/利润/门槛综合达标")) | K33: ='02_ASIN原始数据'!C32 | L33: ='02_ASIN原始数据'!D32
A34: ='03_衍生指标'!A33 | B34: ='02_ASIN原始数据'!B33 | C34: ='03_衍生指标'!J33 | D34: ='03_衍生指标'!K33 | E34: ='03_衍生指标'!L33 | F34: ='03_衍生指标'!M33 | G34: =IF(A34="","",C34*'01_动态参数'!B4+D34*'01_动态参数'!B5+E34*'01_动态参数'!B6+F34*'01_动态参数'!B7) | H34: =IF(A34="","",IF(OR('03_衍生指标'!F33=1,'03_衍生指标'!G33=0,'03_衍生指标'!E33=0,AND('03_衍生指标'!H33=1,'01_动态参数'!B16=1)),"否决","通过")) | I34: =IF(A34="","",IF(H34="否决","淘汰",IF(G34>=8,"S",IF(G34>=7,"A",IF(G34>=6,"B",IF(G34>=5,"C","淘汰")))))) | J34: =IF(A34="","",IF(H34="否决","触发否决："&IF('03_衍生指标'!F33=1,"评分数超限 ","")&IF('03_衍生指标'!G33=0,"增长率不达标 ","")&IF('03_衍生指标'!E33=0,"毛利率不足 ","")&IF(AND('03_衍生指标'!H33=1,'01_动态参数'!B16=1),"自营不接受",""),"推荐：竞争/增长/利润/门槛综合达标")) | K34: ='02_ASIN原始数据'!C33 | L34: ='02_ASIN原始数据'!D33
A35: ='03_衍生指标'!A34 | B35: ='02_ASIN原始数据'!B34 | C35: ='03_衍生指标'!J34 | D35: ='03_衍生指标'!K34 | E35: ='03_衍生指标'!L34 | F35: ='03_衍生指标'!M34 | G35: =IF(A35="","",C35*'01_动态参数'!B4+D35*'01_动态参数'!B5+E35*'01_动态参数'!B6+F35*'01_动态参数'!B7) | H35: =IF(A35="","",IF(OR('03_衍生指标'!F34=1,'03_衍生指标'!G34=0,'03_衍生指标'!E34=0,AND('03_衍生指标'!H34=1,'01_动态参数'!B16=1)),"否决","通过")) | I35: =IF(A35="","",IF(H35="否决","淘汰",IF(G35>=8,"S",IF(G35>=7,"A",IF(G35>=6,"B",IF(G35>=5,"C","淘汰")))))) | J35: =IF(A35="","",IF(H35="否决","触发否决："&IF('03_衍生指标'!F34=1,"评分数超限 ","")&IF('03_衍生指标'!G34=0,"增长率不达标 ","")&IF('03_衍生指标'!E34=0,"毛利率不足 ","")&IF(AND('03_衍生指标'!H34=1,'01_动态参数'!B16=1),"自营不接受",""),"推荐：竞争/增长/利润/门槛综合达标")) | K35: ='02_ASIN原始数据'!C34 | L35: ='02_ASIN原始数据'!D34
A36: ='03_衍生指标'!A35 | B36: ='02_ASIN原始数据'!B35 | C36: ='03_衍生指标'!J35 | D36: ='03_衍生指标'!K35 | E36: ='03_衍生指标'!L35 | F36: ='03_衍生指标'!M35 | G36: =IF(A36="","",C36*'01_动态参数'!B4+D36*'01_动态参数'!B5+E36*'01_动态参数'!B6+F36*'01_动态参数'!B7) | H36: =IF(A36="","",IF(OR('03_衍生指标'!F35=1,'03_衍生指标'!G35=0,'03_衍生指标'!E35=0,AND('03_衍生指标'!H35=1,'01_动态参数'!B16=1)),"否决","通过")) | I36: =IF(A36="","",IF(H36="否决","淘汰",IF(G36>=8,"S",IF(G36>=7,"A",IF(G36>=6,"B",IF(G36>=5,"C","淘汰")))))) | J36: =IF(A36="","",IF(H36="否决","触发否决："&IF('03_衍生指标'!F35=1,"评分数超限 ","")&IF('03_衍生指标'!G35=0,"增长率不达标 ","")&IF('03_衍生指标'!E35=0,"毛利率不足 ","")&IF(AND('03_衍生指标'!H35=1,'01_动态参数'!B16=1),"自营不接受",""),"推荐：竞争/增长/利润/门槛综合达标")) | K36: ='02_ASIN原始数据'!C35 | L36: ='02_ASIN原始数据'!D35
A37: ='03_衍生指标'!A36 | B37: ='02_ASIN原始数据'!B36 | C37: ='03_衍生指标'!J36 | D37: ='03_衍生指标'!K36 | E37: ='03_衍生指标'!L36 | F37: ='03_衍生指标'!M36 | G37: =IF(A37="","",C37*'01_动态参数'!B4+D37*'01_动态参数'!B5+E37*'01_动态参数'!B6+F37*'01_动态参数'!B7) | H37: =IF(A37="","",IF(OR('03_衍生指标'!F36=1,'03_衍生指标'!G36=0,'03_衍生指标'!E36=0,AND('03_衍生指标'!H36=1,'01_动态参数'!B16=1)),"否决","通过")) | I37: =IF(A37="","",IF(H37="否决","淘汰",IF(G37>=8,"S",IF(G37>=7,"A",IF(G37>=6,"B",IF(G37>=5,"C","淘汰")))))) | J37: =IF(A37="","",IF(H37="否决","触发否决："&IF('03_衍生指标'!F36=1,"评分数超限 ","")&IF('03_衍生指标'!G36=0,"增长率不达标 ","")&IF('03_衍生指标'!E36=0,"毛利率不足 ","")&IF(AND('03_衍生指标'!H36=1,'01_动态参数'!B16=1),"自营不接受",""),"推荐：竞争/增长/利润/门槛综合达标")) | K37: ='02_ASIN原始数据'!C36 | L37: ='02_ASIN原始数据'!D36
A38: ='03_衍生指标'!A37 | B38: ='02_ASIN原始数据'!B37 | C38: ='03_衍生指标'!J37 | D38: ='03_衍生指标'!K37 | E38: ='03_衍生指标'!L37 | F38: ='03_衍生指标'!M37 | G38: =IF(A38="","",C38*'01_动态参数'!B4+D38*'01_动态参数'!B5+E38*'01_动态参数'!B6+F38*'01_动态参数'!B7) | H38: =IF(A38="","",IF(OR('03_衍生指标'!F37=1,'03_衍生指标'!G37=0,'03_衍生指标'!E37=0,AND('03_衍生指标'!H37=1,'01_动态参数'!B16=1)),"否决","通过")) | I38: =IF(A38="","",IF(H38="否决","淘汰",IF(G38>=8,"S",IF(G38>=7,"A",IF(G38>=6,"B",IF(G38>=5,"C","淘汰")))))) | J38: =IF(A38="","",IF(H38="否决","触发否决："&IF('03_衍生指标'!F37=1,"评分数超限 ","")&IF('03_衍生指标'!G37=0,"增长率不达标 ","")&IF('03_衍生指标'!E37=0,"毛利率不足 ","")&IF(AND('03_衍生指标'!H37=1,'01_动态参数'!B16=1),"自营不接受",""),"推荐：竞争/增长/利润/门槛综合达标")) | K38: ='02_ASIN原始数据'!C37 | L38: ='02_ASIN原始数据'!D37
A39: ='03_衍生指标'!A38 | B39: ='02_ASIN原始数据'!B38 | C39: ='03_衍生指标'!J38 | D39: ='03_衍生指标'!K38 | E39: ='03_衍生指标'!L38 | F39: ='03_衍生指标'!M38 | G39: =IF(A39="","",C39*'01_动态参数'!B4+D39*'01_动态参数'!B5+E39*'01_动态参数'!B6+F39*'01_动态参数'!B7) | H39: =IF(A39="","",IF(OR('03_衍生指标'!F38=1,'03_衍生指标'!G38=0,'03_衍生指标'!E38=0,AND('03_衍生指标'!H38=1,'01_动态参数'!B16=1)),"否决","通过")) | I39: =IF(A39="","",IF(H39="否决","淘汰",IF(G39>=8,"S",IF(G39>=7,"A",IF(G39>=6,"B",IF(G39>=5,"C","淘汰")))))) | J39: =IF(A39="","",IF(H39="否决","触发否决："&IF('03_衍生指标'!F38=1,"评分数超限 ","")&IF('03_衍生指标'!G38=0,"增长率不达标 ","")&IF('03_衍生指标'!E38=0,"毛利率不足 ","")&IF(AND('03_衍生指标'!H38=1,'01_动态参数'!B16=1),"自营不接受",""),"推荐：竞争/增长/利润/门槛综合达标")) | K39: ='02_ASIN原始数据'!C38 | L39: ='02_ASIN原始数据'!D38
A40: ='03_衍生指标'!A39 | B40: ='02_ASIN原始数据'!B39 | C40: ='03_衍生指标'!J39 | D40: ='03_衍生指标'!K39 | E40: ='03_衍生指标'!L39 | F40: ='03_衍生指标'!M39 | G40: =IF(A40="","",C40*'01_动态参数'!B4+D40*'01_动态参数'!B5+E40*'01_动态参数'!B6+F40*'01_动态参数'!B7) | H40: =IF(A40="","",IF(OR('03_衍生指标'!F39=1,'03_衍生指标'!G39=0,'03_衍生指标'!E39=0,AND('03_衍生指标'!H39=1,'01_动态参数'!B16=1)),"否决","通过")) | I40: =IF(A40="","",IF(H40="否决","淘汰",IF(G40>=8,"S",IF(G40>=7,"A",IF(G40>=6,"B",IF(G40>=5,"C","淘汰")))))) | J40: =IF(A40="","",IF(H40="否决","触发否决："&IF('03_衍生指标'!F39=1,"评分数超限 ","")&IF('03_衍生指标'!G39=0,"增长率不达标 ","")&IF('03_衍生指标'!E39=0,"毛利率不足 ","")&IF(AND('03_衍生指标'!H39=1,'01_动态参数'!B16=1),"自营不接受",""),"推荐：竞争/增长/利润/门槛综合达标")) | K40: ='02_ASIN原始数据'!C39 | L40: ='02_ASIN原始数据'!D39
A41: ='03_衍生指标'!A40 | B41: ='02_ASIN原始数据'!B40 | C41: ='03_衍生指标'!J40 | D41: ='03_衍生指标'!K40 | E41: ='03_衍生指标'!L40 | F41: ='03_衍生指标'!M40 | G41: =IF(A41="","",C41*'01_动态参数'!B4+D41*'01_动态参数'!B5+E41*'01_动态参数'!B6+F41*'01_动态参数'!B7) | H41: =IF(A41="","",IF(OR('03_衍生指标'!F40=1,'03_衍生指标'!G40=0,'03_衍生指标'!E40=0,AND('03_衍生指标'!H40=1,'01_动态参数'!B16=1)),"否决","通过")) | I41: =IF(A41="","",IF(H41="否决","淘汰",IF(G41>=8,"S",IF(G41>=7,"A",IF(G41>=6,"B",IF(G41>=5,"C","淘汰")))))) | J41: =IF(A41="","",IF(H41="否决","触发否决："&IF('03_衍生指标'!F40=1,"评分数超限 ","")&IF('03_衍生指标'!G40=0,"增长率不达标 ","")&IF('03_衍生指标'!E40=0,"毛利率不足 ","")&IF(AND('03_衍生指标'!H40=1,'01_动态参数'!B16=1),"自营不接受",""),"推荐：竞争/增长/利润/门槛综合达标")) | K41: ='02_ASIN原始数据'!C40 | L41: ='02_ASIN原始数据'!D40
A42: ='03_衍生指标'!A41 | B42: ='02_ASIN原始数据'!B41 | C42: ='03_衍生指标'!J41 | D42: ='03_衍生指标'!K41 | E42: ='03_衍生指标'!L41 | F42: ='03_衍生指标'!M41 | G42: =IF(A42="","",C42*'01_动态参数'!B4+D42*'01_动态参数'!B5+E42*'01_动态参数'!B6+F42*'01_动态参数'!B7) | H42: =IF(A42="","",IF(OR('03_衍生指标'!F41=1,'03_衍生指标'!G41=0,'03_衍生指标'!E41=0,AND('03_衍生指标'!H41=1,'01_动态参数'!B16=1)),"否决","通过")) | I42: =IF(A42="","",IF(H42="否决","淘汰",IF(G42>=8,"S",IF(G42>=7,"A",IF(G42>=6,"B",IF(G42>=5,"C","淘汰")))))) | J42: =IF(A42="","",IF(H42="否决","触发否决："&IF('03_衍生指标'!F41=1,"评分数超限 ","")&IF('03_衍生指标'!G41=0,"增长率不达标 ","")&IF('03_衍生指标'!E41=0,"毛利率不足 ","")&IF(AND('03_衍生指标'!H41=1,'01_动态参数'!B16=1),"自营不接受",""),"推荐：竞争/增长/利润/门槛综合达标")) | K42: ='02_ASIN原始数据'!C41 | L42: ='02_ASIN原始数据'!D41
A43: ='03_衍生指标'!A42 | B43: ='02_ASIN原始数据'!B42 | C43: ='03_衍生指标'!J42 | D43: ='03_衍生指标'!K42 | E43: ='03_衍生指标'!L42 | F43: ='03_衍生指标'!M42 | G43: =IF(A43="","",C43*'01_动态参数'!B4+D43*'01_动态参数'!B5+E43*'01_动态参数'!B6+F43*'01_动态参数'!B7) | H43: =IF(A43="","",IF(OR('03_衍生指标'!F42=1,'03_衍生指标'!G42=0,'03_衍生指标'!E42=0,AND('03_衍生指标'!H42=1,'01_动态参数'!B16=1)),"否决","通过")) | I43: =IF(A43="","",IF(H43="否决","淘汰",IF(G43>=8,"S",IF(G43>=7,"A",IF(G43>=6,"B",IF(G43>=5,"C","淘汰")))))) | J43: =IF(A43="","",IF(H43="否决","触发否决："&IF('03_衍生指标'!F42=1,"评分数超限 ","")&IF('03_衍生指标'!G42=0,"增长率不达标 ","")&IF('03_衍生指标'!E42=0,"毛利率不足 ","")&IF(AND('03_衍生指标'!H42=1,'01_动态参数'!B16=1),"自营不接受",""),"推荐：竞争/增长/利润/门槛综合达标")) | K43: ='02_ASIN原始数据'!C42 | L43: ='02_ASIN原始数据'!D42
A44: ='03_衍生指标'!A43 | B44: ='02_ASIN原始数据'!B43 | C44: ='03_衍生指标'!J43 | D44: ='03_衍生指标'!K43 | E44: ='03_衍生指标'!L43 | F44: ='03_衍生指标'!M43 | G44: =IF(A44="","",C44*'01_动态参数'!B4+D44*'01_动态参数'!B5+E44*'01_动态参数'!B6+F44*'01_动态参数'!B7) | H44: =IF(A44="","",IF(OR('03_衍生指标'!F43=1,'03_衍生指标'!G43=0,'03_衍生指标'!E43=0,AND('03_衍生指标'!H43=1,'01_动态参数'!B16=1)),"否决","通过")) | I44: =IF(A44="","",IF(H44="否决","淘汰",IF(G44>=8,"S",IF(G44>=7,"A",IF(G44>=6,"B",IF(G44>=5,"C","淘汰")))))) | J44: =IF(A44="","",IF(H44="否决","触发否决："&IF('03_衍生指标'!F43=1,"评分数超限 ","")&IF('03_衍生指标'!G43=0,"增长率不达标 ","")&IF('03_衍生指标'!E43=0,"毛利率不足 ","")&IF(AND('03_衍生指标'!H43=1,'01_动态参数'!B16=1),"自营不接受",""),"推荐：竞争/增长/利润/门槛综合达标")) | K44: ='02_ASIN原始数据'!C43 | L44: ='02_ASIN原始数据'!D43
A45: ='03_衍生指标'!A44 | B45: ='02_ASIN原始数据'!B44 | C45: ='03_衍生指标'!J44 | D45: ='03_衍生指标'!K44 | E45: ='03_衍生指标'!L44 | F45: ='03_衍生指标'!M44 | G45: =IF(A45="","",C45*'01_动态参数'!B4+D45*'01_动态参数'!B5+E45*'01_动态参数'!B6+F45*'01_动态参数'!B7) | H45: =IF(A45="","",IF(OR('03_衍生指标'!F44=1,'03_衍生指标'!G44=0,'03_衍生指标'!E44=0,AND('03_衍生指标'!H44=1,'01_动态参数'!B16=1)),"否决","通过")) | I45: =IF(A45="","",IF(H45="否决","淘汰",IF(G45>=8,"S",IF(G45>=7,"A",IF(G45>=6,"B",IF(G45>=5,"C","淘汰")))))) | J45: =IF(A45="","",IF(H45="否决","触发否决："&IF('03_衍生指标'!F44=1,"评分数超限 ","")&IF('03_衍生指标'!G44=0,"增长率不达标 ","")&IF('03_衍生指标'!E44=0,"毛利率不足 ","")&IF(AND('03_衍生指标'!H44=1,'01_动态参数'!B16=1),"自营不接受",""),"推荐：竞争/增长/利润/门槛综合达标")) | K45: ='02_ASIN原始数据'!C44 | L45: ='02_ASIN原始数据'!D44
A46: ='03_衍生指标'!A45 | B46: ='02_ASIN原始数据'!B45 | C46: ='03_衍生指标'!J45 | D46: ='03_衍生指标'!K45 | E46: ='03_衍生指标'!L45 | F46: ='03_衍生指标'!M45 | G46: =IF(A46="","",C46*'01_动态参数'!B4+D46*'01_动态参数'!B5+E46*'01_动态参数'!B6+F46*'01_动态参数'!B7) | H46: =IF(A46="","",IF(OR('03_衍生指标'!F45=1,'03_衍生指标'!G45=0,'03_衍生指标'!E45=0,AND('03_衍生指标'!H45=1,'01_动态参数'!B16=1)),"否决","通过")) | I46: =IF(A46="","",IF(H46="否决","淘汰",IF(G46>=8,"S",IF(G46>=7,"A",IF(G46>=6,"B",IF(G46>=5,"C","淘汰")))))) | J46: =IF(A46="","",IF(H46="否决","触发否决："&IF('03_衍生指标'!F45=1,"评分数超限 ","")&IF('03_衍生指标'!G45=0,"增长率不达标 ","")&IF('03_衍生指标'!E45=0,"毛利率不足 ","")&IF(AND('03_衍生指标'!H45=1,'01_动态参数'!B16=1),"自营不接受",""),"推荐：竞争/增长/利润/门槛综合达标")) | K46: ='02_ASIN原始数据'!C45 | L46: ='02_ASIN原始数据'!D45
A47: ='03_衍生指标'!A46 | B47: ='02_ASIN原始数据'!B46 | C47: ='03_衍生指标'!J46 | D47: ='03_衍生指标'!K46 | E47: ='03_衍生指标'!L46 | F47: ='03_衍生指标'!M46 | G47: =IF(A47="","",C47*'01_动态参数'!B4+D47*'01_动态参数'!B5+E47*'01_动态参数'!B6+F47*'01_动态参数'!B7) | H47: =IF(A47="","",IF(OR('03_衍生指标'!F46=1,'03_衍生指标'!G46=0,'03_衍生指标'!E46=0,AND('03_衍生指标'!H46=1,'01_动态参数'!B16=1)),"否决","通过")) | I47: =IF(A47="","",IF(H47="否决","淘汰",IF(G47>=8,"S",IF(G47>=7,"A",IF(G47>=6,"B",IF(G47>=5,"C","淘汰")))))) | J47: =IF(A47="","",IF(H47="否决","触发否决："&IF('03_衍生指标'!F46=1,"评分数超限 ","")&IF('03_衍生指标'!G46=0,"增长率不达标 ","")&IF('03_衍生指标'!E46=0,"毛利率不足 ","")&IF(AND('03_衍生指标'!H46=1,'01_动态参数'!B16=1),"自营不接受",""),"推荐：竞争/增长/利润/门槛综合达标")) | K47: ='02_ASIN原始数据'!C46 | L47: ='02_ASIN原始数据'!D46
A48: ='03_衍生指标'!A47 | B48: ='02_ASIN原始数据'!B47 | C48: ='03_衍生指标'!J47 | D48: ='03_衍生指标'!K47 | E48: ='03_衍生指标'!L47 | F48: ='03_衍生指标'!M47 | G48: =IF(A48="","",C48*'01_动态参数'!B4+D48*'01_动态参数'!B5+E48*'01_动态参数'!B6+F48*'01_动态参数'!B7) | H48: =IF(A48="","",IF(OR('03_衍生指标'!F47=1,'03_衍生指标'!G47=0,'03_衍生指标'!E47=0,AND('03_衍生指标'!H47=1,'01_动态参数'!B16=1)),"否决","通过")) | I48: =IF(A48="","",IF(H48="否决","淘汰",IF(G48>=8,"S",IF(G48>=7,"A",IF(G48>=6,"B",IF(G48>=5,"C","淘汰")))))) | J48: =IF(A48="","",IF(H48="否决","触发否决："&IF('03_衍生指标'!F47=1,"评分数超限 ","")&IF('03_衍生指标'!G47=0,"增长率不达标 ","")&IF('03_衍生指标'!E47=0,"毛利率不足 ","")&IF(AND('03_衍生指标'!H47=1,'01_动态参数'!B16=1),"自营不接受",""),"推荐：竞争/增长/利润/门槛综合达标")) | K48: ='02_ASIN原始数据'!C47 | L48: ='02_ASIN原始数据'!D47
A49: ='03_衍生指标'!A48 | B49: ='02_ASIN原始数据'!B48 | C49: ='03_衍生指标'!J48 | D49: ='03_衍生指标'!K48 | E49: ='03_衍生指标'!L48 | F49: ='03_衍生指标'!M48 | G49: =IF(A49="","",C49*'01_动态参数'!B4+D49*'01_动态参数'!B5+E49*'01_动态参数'!B6+F49*'01_动态参数'!B7) | H49: =IF(A49="","",IF(OR('03_衍生指标'!F48=1,'03_衍生指标'!G48=0,'03_衍生指标'!E48=0,AND('03_衍生指标'!H48=1,'01_动态参数'!B16=1)),"否决","通过")) | I49: =IF(A49="","",IF(H49="否决","淘汰",IF(G49>=8,"S",IF(G49>=7,"A",IF(G49>=6,"B",IF(G49>=5,"C","淘汰")))))) | J49: =IF(A49="","",IF(H49="否决","触发否决："&IF('03_衍生指标'!F48=1,"评分数超限 ","")&IF('03_衍生指标'!G48=0,"增长率不达标 ","")&IF('03_衍生指标'!E48=0,"毛利率不足 ","")&IF(AND('03_衍生指标'!H48=1,'01_动态参数'!B16=1),"自营不接受",""),"推荐：竞争/增长/利润/门槛综合达标")) | K49: ='02_ASIN原始数据'!C48 | L49: ='02_ASIN原始数据'!D48
A50: ='03_衍生指标'!A49 | B50: ='02_ASIN原始数据'!B49 | C50: ='03_衍生指标'!J49 | D50: ='03_衍生指标'!K49 | E50: ='03_衍生指标'!L49 | F50: ='03_衍生指标'!M49 | G50: =IF(A50="","",C50*'01_动态参数'!B4+D50*'01_动态参数'!B5+E50*'01_动态参数'!B6+F50*'01_动态参数'!B7) | H50: =IF(A50="","",IF(OR('03_衍生指标'!F49=1,'03_衍生指标'!G49=0,'03_衍生指标'!E49=0,AND('03_衍生指标'!H49=1,'01_动态参数'!B16=1)),"否决","通过")) | I50: =IF(A50="","",IF(H50="否决","淘汰",IF(G50>=8,"S",IF(G50>=7,"A",IF(G50>=6,"B",IF(G50>=5,"C","淘汰")))))) | J50: =IF(A50="","",IF(H50="否决","触发否决："&IF('03_衍生指标'!F49=1,"评分数超限 ","")&IF('03_衍生指标'!G49=0,"增长率不达标 ","")&IF('03_衍生指标'!E49=0,"毛利率不足 ","")&IF(AND('03_衍生指标'!H49=1,'01_动态参数'!B16=1),"自营不接受",""),"推荐：竞争/增长/利润/门槛综合达标")) | K50: ='02_ASIN原始数据'!C49 | L50: ='02_ASIN原始数据'!D49
A51: ='03_衍生指标'!A50 | B51: ='02_ASIN原始数据'!B50 | C51: ='03_衍生指标'!J50 | D51: ='03_衍生指标'!K50 | E51: ='03_衍生指标'!L50 | F51: ='03_衍生指标'!M50 | G51: =IF(A51="","",C51*'01_动态参数'!B4+D51*'01_动态参数'!B5+E51*'01_动态参数'!B6+F51*'01_动态参数'!B7) | H51: =IF(A51="","",IF(OR('03_衍生指标'!F50=1,'03_衍生指标'!G50=0,'03_衍生指标'!E50=0,AND('03_衍生指标'!H50=1,'01_动态参数'!B16=1)),"否决","通过")) | I51: =IF(A51="","",IF(H51="否决","淘汰",IF(G51>=8,"S",IF(G51>=7,"A",IF(G51>=6,"B",IF(G51>=5,"C","淘汰")))))) | J51: =IF(A51="","",IF(H51="否决","触发否决："&IF('03_衍生指标'!F50=1,"评分数超限 ","")&IF('03_衍生指标'!G50=0,"增长率不达标 ","")&IF('03_衍生指标'!E50=0,"毛利率不足 ","")&IF(AND('03_衍生指标'!H50=1,'01_动态参数'!B16=1),"自营不接受",""),"推荐：竞争/增长/利润/门槛综合达标")) | K51: ='02_ASIN原始数据'!C50 | L51: ='02_ASIN原始数据'!D50
A52: ='03_衍生指标'!A51 | B52: ='02_ASIN原始数据'!B51 | C52: ='03_衍生指标'!J51 | D52: ='03_衍生指标'!K51 | E52: ='03_衍生指标'!L51 | F52: ='03_衍生指标'!M51 | G52: =IF(A52="","",C52*'01_动态参数'!B4+D52*'01_动态参数'!B5+E52*'01_动态参数'!B6+F52*'01_动态参数'!B7) | H52: =IF(A52="","",IF(OR('03_衍生指标'!F51=1,'03_衍生指标'!G51=0,'03_衍生指标'!E51=0,AND('03_衍生指标'!H51=1,'01_动态参数'!B16=1)),"否决","通过")) | I52: =IF(A52="","",IF(H52="否决","淘汰",IF(G52>=8,"S",IF(G52>=7,"A",IF(G52>=6,"B",IF(G52>=5,"C","淘汰")))))) | J52: =IF(A52="","",IF(H52="否决","触发否决："&IF('03_衍生指标'!F51=1,"评分数超限 ","")&IF('03_衍生指标'!G51=0,"增长率不达标 ","")&IF('03_衍生指标'!E51=0,"毛利率不足 ","")&IF(AND('03_衍生指标'!H51=1,'01_动态参数'!B16=1),"自营不接受",""),"推荐：竞争/增长/利润/门槛综合达标")) | K52: ='02_ASIN原始数据'!C51 | L52: ='02_ASIN原始数据'!D51
A53: ='03_衍生指标'!A52 | B53: ='02_ASIN原始数据'!B52 | C53: ='03_衍生指标'!J52 | D53: ='03_衍生指标'!K52 | E53: ='03_衍生指标'!L52 | F53: ='03_衍生指标'!M52 | G53: =IF(A53="","",C53*'01_动态参数'!B4+D53*'01_动态参数'!B5+E53*'01_动态参数'!B6+F53*'01_动态参数'!B7) | H53: =IF(A53="","",IF(OR('03_衍生指标'!F52=1,'03_衍生指标'!G52=0,'03_衍生指标'!E52=0,AND('03_衍生指标'!H52=1,'01_动态参数'!B16=1)),"否决","通过")) | I53: =IF(A53="","",IF(H53="否决","淘汰",IF(G53>=8,"S",IF(G53>=7,"A",IF(G53>=6,"B",IF(G53>=5,"C","淘汰")))))) | J53: =IF(A53="","",IF(H53="否决","触发否决："&IF('03_衍生指标'!F52=1,"评分数超限 ","")&IF('03_衍生指标'!G52=0,"增长率不达标 ","")&IF('03_衍生指标'!E52=0,"毛利率不足 ","")&IF(AND('03_衍生指标'!H52=1,'01_动态参数'!B16=1),"自营不接受",""),"推荐：竞争/增长/利润/门槛综合达标")) | K53: ='02_ASIN原始数据'!C52 | L53: ='02_ASIN原始数据'!D52

Sheet 05_推荐清单
A1: 推荐清单（仅显示「通过」且总分≥6 的 ASIN，按总分降序。使用 FILTER 动态数组，需 Excel 365/2021+）
A3: 说明：如果您的 Excel 版本不支持 FILTER 动态数组，请手动到「04_最终评分」按「一票否决=通过」和「加权总分≥6」筛选，再按总分降序排序。
A5: asin | B5: title | C5: 加权总分 | D5: 推荐等级 | E5: 低竞争 | F5: 生命周期 | G5: 利润健康 | H5: 准入门槛 | I5: 自动理由 | J5: brand | K5: price
A6: =IFERROR(FILTER('04_最终评分'!A4:L53,('04_最终评分'!H4:H53="通过")*('04_最终评分'!G4:G53>=6),"无符合条件的产品（请检查期望配置或数据）"),"无符合条件的产品")
