Workbook

Sheet 封面
A1: 可比公司分析：单一Excel决策与审计模型
A4: 本工作簿是唯一正式用户交付物；定量结论、定性说明、来源和检查均在簿内。
A6: 估值基准日 | B6: 2026-06-30
A7: 目标公司 | B7: 目标示例公司（TARGET）
A8: 主估值指标 | B8: 市净率（P/B）
A9: 数据等级 | B9: B
A10: 默认交付策略 | B10: 只交付Excel；独立Markdown仅在用户明确要求时额外生成

Sheet 结论摘要
A1: 项目 | B1: 数值/结论 | C1: 解释 | D1: 追溯位置
A2: 模型状态 | B2: ='模型检查'!F7 | C2: 只有PASS才允许发布正式估值区间 | D2: 模型检查
A3: 估值基准日 | B3: 2026-06-30 | C3: 统一价格、股本和汇率日期 | D3: 历史数据与口径
A4: 目标公司 | B4: 目标示例公司 | C4: TARGET | D4: 目标公司
A5: 主估值指标 | B5: 市净率（P/B） | C5: 由行业与阶段路由确定 | D5: 假设与方法
A6: 当前股价 | B6: ='隐含估值'!I12 | C6: 未复权估值日收盘价 | D6: 隐含估值
A7: P25隐含价值 | B7: =MIN('隐含估值'!F12:'隐含估值'!H12) | C7: 考虑收益率指标方向 | D7: 隐含估值
A8: 中位数隐含价值 | B8: ='隐含估值'!G12 | C8: 核心样本中位数锚 | D8: 隐含估值
A9: P75隐含价值 | B9: =MAX('隐含估值'!F12:'隐含估值'!H12) | C9: 考虑收益率指标方向 | D9: 隐含估值
A10: 中位数上涨/下跌空间 | B10: =IFERROR(B8/B6-1,"") | C10: 相对估值基准日股价 | D10: 隐含估值
A11: 结论 | B11: 结构测试示例，不形成真实估值结论 | C11: 定性结论不得替代公式结果 | D11: 结论依据
A12: 同行比较 | B12: 增长、盈利、现金转化和风险逐项比较完成 | C12: 解释增长、盈利、现金转化与风险 | D12: 结论依据
A13: 溢折价逻辑 | B13: 未给予无依据溢价 | C13: 禁止无证据百分比加减 | D13: 结论依据

Sheet 原始数据与计算
A1: 公司 | B1: 代码 | C1: 分类 | D1: 股价 | E1: 稀释股数 | F1: 债务 | G1: 现金 | H1: 优先股 | I1: 少数股东权益 | J1: 债务类调整 | K1: 非经营投资 | L1: LTM收入 | M1: NTM收入 | N1: LTM EBITDA | O1: NTM EBITDA | P1: LTM净利润 | Q1: NTM净利润 | R1: LTM自由现金流 | S1: NTM自由现金流 | T1: 普通股权益 | U1: 账面价值股数 | V1: 平均普通股权益 | W1: 市值 | X1: 企业价值 | Y1: LTM EV/收入 | Z1: NTM EV/收入 | AA1: LTM EV/EBITDA | AB1: NTM EV/EBITDA | AC1: LTM P/E | AD1: NTM P/E | AE1: LTM P/S | AF1: NTM P/S | AG1: LTM FCF收益率 | AH1: NTM FCF收益率 | AI1: P/B | AJ1: LTM ROE
A2: 目标示例公司 | B2: TARGET | C2: Target | D2: 10 | E2: 100 | F2: 0 | G2: 0 | H2: 0 | I2: 0 | J2: 0 | K2: 0 | P2: 100 | T2: 1000 | U2: 100 | V2: 1000 | W2: =D2*E2 | X2: =W2+F2-G2+H2+I2+J2-K2 | Y2: =IFERROR(X2/L2,"") | Z2: =IFERROR(X2/M2,"") | AA2: =IFERROR(X2/N2,"") | AB2: =IFERROR(X2/O2,"") | AC2: =IFERROR(W2/P2,"") | AD2: =IFERROR(W2/Q2,"") | AE2: =IFERROR(W2/L2,"") | AF2: =IFERROR(W2/M2,"") | AG2: =IFERROR(R2/W2,"") | AH2: =IFERROR(S2/W2,"") | AI2: =IFERROR(D2/(T2/U2),"") | AJ2: =IFERROR(P2/V2,"")
A3: 核心示例公司1 | B3: CORE1 | C3: Core | D3: 11 | E3: 100 | F3: 0 | G3: 0 | H3: 0 | I3: 0 | J3: 0 | K3: 0 | P3: 100 | T3: 1000 | U3: 100 | V3: 1000 | W3: =D3*E3 | X3: =W3+F3-G3+H3+I3+J3-K3 | Y3: =IFERROR(X3/L3,"") | Z3: =IFERROR(X3/M3,"") | AA3: =IFERROR(X3/N3,"") | AB3: =IFERROR(X3/O3,"") | AC3: =IFERROR(W3/P3,"") | AD3: =IFERROR(W3/Q3,"") | AE3: =IFERROR(W3/L3,"") | AF3: =IFERROR(W3/M3,"") | AG3: =IFERROR(R3/W3,"") | AH3: =IFERROR(S3/W3,"") | AI3: =IFERROR(D3/(T3/U3),"") | AJ3: =IFERROR(P3/V3,"")
A4: 核心示例公司2 | B4: CORE2 | C4: Core | D4: 12 | E4: 100 | F4: 0 | G4: 0 | H4: 0 | I4: 0 | J4: 0 | K4: 0 | P4: 100 | T4: 1000 | U4: 100 | V4: 1000 | W4: =D4*E4 | X4: =W4+F4-G4+H4+I4+J4-K4 | Y4: =IFERROR(X4/L4,"") | Z4: =IFERROR(X4/M4,"") | AA4: =IFERROR(X4/N4,"") | AB4: =IFERROR(X4/O4,"") | AC4: =IFERROR(W4/P4,"") | AD4: =IFERROR(W4/Q4,"") | AE4: =IFERROR(W4/L4,"") | AF4: =IFERROR(W4/M4,"") | AG4: =IFERROR(R4/W4,"") | AH4: =IFERROR(S4/W4,"") | AI4: =IFERROR(D4/(T4/U4),"") | AJ4: =IFERROR(P4/V4,"")
A5: 核心示例公司3 | B5: CORE3 | C5: Core | D5: 13 | E5: 100 | F5: 0 | G5: 0 | H5: 0 | I5: 0 | J5: 0 | K5: 0 | P5: 100 | T5: 1000 | U5: 100 | V5: 1000 | W5: =D5*E5 | X5: =W5+F5-G5+H5+I5+J5-K5 | Y5: =IFERROR(X5/L5,"") | Z5: =IFERROR(X5/M5,"") | AA5: =IFERROR(X5/N5,"") | AB5: =IFERROR(X5/O5,"") | AC5: =IFERROR(W5/P5,"") | AD5: =IFERROR(W5/Q5,"") | AE5: =IFERROR(W5/L5,"") | AF5: =IFERROR(W5/M5,"") | AG5: =IFERROR(R5/W5,"") | AH5: =IFERROR(S5/W5,"") | AI5: =IFERROR(D5/(T5/U5),"") | AJ5: =IFERROR(P5/V5,"")

Sheet 目标公司
A1: 项目 | B1: 数值 | C1: 单位/口径 | D1: 来源定位
A2: 公司 | B2: ='原始数据与计算'!A2 | C2: 文本 | D2: 原始数据与计算
A3: 代码 | B3: ='原始数据与计算'!B2 | C3: 文本 | D3: 原始数据与计算
A4: 股价 | B4: ='原始数据与计算'!D2 | C4: 每股 | D4: 原始数据与计算
A5: 完全稀释股数 | B5: ='原始数据与计算'!E2 | C5: 股数 | D5: 标准化调整
A6: 市值 | B6: ='原始数据与计算'!W2 | C6: 金额 | D6: 市值与EV桥
A7: 企业价值 | B7: ='原始数据与计算'!X2 | C7: 金额 | D7: 市值与EV桥
A8: 主估值指标 | B8: 市净率（P/B） | C8: 方法 | D8: 假设与方法
A9: 当前主指标 | B9: ='原始数据与计算'!AI2 | C9: 倍数/收益率 | D9: 交易倍数

Sheet 同行筛选
A1: 公司 | B1: 代码 | C1: 分类 | D1: 同行角色 | E1: 业务重合 | F1: 商业模式 | G1: 收入结构 | H1: 市值带 | I1: 加权得分 | J1: 数据质量 | K1: 纳入理由 | L1: 分类理由 | M1: 指标理由
A2: 核心示例公司1 | B2: CORE1 | C2: Core | D2: Commercial Core | E2: 5 | F2: 4 | G2: 4 | H2: 4 | I2: 4.35 | J2: Pass | K2: 产品、客户和商业模式可比 | L2: 满足核心评分和数据质量门槛 | M2: 采用P/B并结合ROE解释差异
A3: 核心示例公司2 | B3: CORE2 | C3: Core | D3: Commercial Core | E3: 5 | F3: 4 | G3: 4 | H3: 4 | I3: 4.35 | J3: Pass | K3: 产品、客户和商业模式可比 | L3: 满足核心评分和数据质量门槛 | M3: 采用P/B并结合ROE解释差异
A4: 核心示例公司3 | B4: CORE3 | C4: Core | D4: Commercial Core | E4: 5 | F4: 4 | G4: 4 | H4: 4 | I4: 4.35 | J4: Pass | K4: 产品、客户和商业模式可比 | L4: 满足核心评分和数据质量门槛 | M4: 采用P/B并结合ROE解释差异

Sheet 历史数据与口径
A1: 公司 | B1: 代码 | C1: 股价日期 | D1: 股数日期 | E1: 资产负债表日 | F1: 预测快照日 | G1: 价格口径 | H1: 股本来源 | I1: 基本面来源 | J1: 公司行动来源
A2: 目标示例公司 | B2: TARGET | C2: 2026-06-30 | D2: 2026-06-30 | E2: 2026-03-31 | G2: unadjusted_close | H2: SRC-DEMO | I2: SRC-DEMO | J2: SRC-DEMO
A3: 核心示例公司1 | B3: CORE1 | C3: 2026-06-30 | D3: 2026-06-30 | E3: 2026-03-31 | G3: unadjusted_close | H3: SRC-DEMO | I3: SRC-DEMO | J3: SRC-DEMO
A4: 核心示例公司2 | B4: CORE2 | C4: 2026-06-30 | D4: 2026-06-30 | E4: 2026-03-31 | G4: unadjusted_close | H4: SRC-DEMO | I4: SRC-DEMO | J4: SRC-DEMO
A5: 核心示例公司3 | B5: CORE3 | C5: 2026-06-30 | D5: 2026-06-30 | E5: 2026-03-31 | G5: unadjusted_close | H5: SRC-DEMO | I5: SRC-DEMO | J5: SRC-DEMO

Sheet 标准化调整
A1: 公司 | B1: 报告股数 | C1: 期权增量 | D1: 限制性股票 | E1: 可转债增量 | F1: 其他稀释 | G1: 已完成发行 | H1: 已完成回购 | I1: 完全稀释股数 | J1: 债务类净调整
A2: 目标示例公司 | B2: 100 | C2: 0 | D2: 0 | E2: 0 | F2: 0 | G2: 0 | H2: 0 | I2: =B2+SUM(C2:G2)-H2 | J2: ='原始数据与计算'!X2-'原始数据与计算'!W2
A3: 核心示例公司1 | B3: 100 | C3: 0 | D3: 0 | E3: 0 | F3: 0 | G3: 0 | H3: 0 | I3: =B3+SUM(C3:G3)-H3 | J3: ='原始数据与计算'!X3-'原始数据与计算'!W3
A4: 核心示例公司2 | B4: 100 | C4: 0 | D4: 0 | E4: 0 | F4: 0 | G4: 0 | H4: 0 | I4: =B4+SUM(C4:G4)-H4 | J4: ='原始数据与计算'!X4-'原始数据与计算'!W4
A5: 核心示例公司3 | B5: 100 | C5: 0 | D5: 0 | E5: 0 | F5: 0 | G5: 0 | H5: 0 | I5: =B5+SUM(C5:G5)-H5 | J5: ='原始数据与计算'!X5-'原始数据与计算'!W5

Sheet 市值与EV桥
A1: 公司 | B1: 分类 | C1: 股价 | D1: 稀释股数 | E1: 市值 | F1: 债务 | G1: 现金 | H1: 优先股 | I1: 少数股东 | J1: 债务类调整 | K1: 非经营投资 | L1: 净债务及类债务调整 | M1: 企业价值
A2: ='原始数据与计算'!A2 | B2: ='原始数据与计算'!C2 | C2: ='原始数据与计算'!D2 | D2: ='原始数据与计算'!E2 | E2: =C2*D2 | F2: ='原始数据与计算'!F2 | G2: ='原始数据与计算'!G2 | H2: ='原始数据与计算'!H2 | I2: ='原始数据与计算'!I2 | J2: ='原始数据与计算'!J2 | K2: ='原始数据与计算'!K2 | L2: =F2-G2+H2+I2+J2-K2 | M2: =E2+L2
A3: ='原始数据与计算'!A3 | B3: ='原始数据与计算'!C3 | C3: ='原始数据与计算'!D3 | D3: ='原始数据与计算'!E3 | E3: =C3*D3 | F3: ='原始数据与计算'!F3 | G3: ='原始数据与计算'!G3 | H3: ='原始数据与计算'!H3 | I3: ='原始数据与计算'!I3 | J3: ='原始数据与计算'!J3 | K3: ='原始数据与计算'!K3 | L3: =F3-G3+H3+I3+J3-K3 | M3: =E3+L3
A4: ='原始数据与计算'!A4 | B4: ='原始数据与计算'!C4 | C4: ='原始数据与计算'!D4 | D4: ='原始数据与计算'!E4 | E4: =C4*D4 | F4: ='原始数据与计算'!F4 | G4: ='原始数据与计算'!G4 | H4: ='原始数据与计算'!H4 | I4: ='原始数据与计算'!I4 | J4: ='原始数据与计算'!J4 | K4: ='原始数据与计算'!K4 | L4: =F4-G4+H4+I4+J4-K4 | M4: =E4+L4
A5: ='原始数据与计算'!A5 | B5: ='原始数据与计算'!C5 | C5: ='原始数据与计算'!D5 | D5: ='原始数据与计算'!E5 | E5: =C5*D5 | F5: ='原始数据与计算'!F5 | G5: ='原始数据与计算'!G5 | H5: ='原始数据与计算'!H5 | I5: ='原始数据与计算'!I5 | J5: ='原始数据与计算'!J5 | K5: ='原始数据与计算'!K5 | L5: =F5-G5+H5+I5+J5-K5 | M5: =E5+L5

Sheet 交易倍数
A1: 公司 | B1: 分类 | C1: ltm_ev_revenue | D1: ntm_ev_revenue | E1: ltm_ev_ebitda | F1: ntm_ev_ebitda | G1: ltm_pe | H1: ntm_pe | I1: ltm_ps | J1: ntm_ps | K1: ltm_fcf_yield | L1: ntm_fcf_yield | M1: price_to_book | N1: ltm_roe
A2: ='原始数据与计算'!A2 | B2: ='原始数据与计算'!C2 | C2: ='原始数据与计算'!Y2 | D2: ='原始数据与计算'!Z2 | E2: ='原始数据与计算'!AA2 | F2: ='原始数据与计算'!AB2 | G2: ='原始数据与计算'!AC2 | H2: ='原始数据与计算'!AD2 | I2: ='原始数据与计算'!AE2 | J2: ='原始数据与计算'!AF2 | ... N2: ='原始数据与计算'!AJ2
A3: ='原始数据与计算'!A3 | B3: ='原始数据与计算'!C3 | C3: ='原始数据与计算'!Y3 | D3: ='原始数据与计算'!Z3 | E3: ='原始数据与计算'!AA3 | F3: ='原始数据与计算'!AB3 | G3: ='原始数据与计算'!AC3 | H3: ='原始数据与计算'!AD3 | I3: ='原始数据与计算'!AE3 | J3: ='原始数据与计算'!AF3 | ... N3: ='原始数据与计算'!AJ3
A4: ='原始数据与计算'!A4 | B4: ='原始数据与计算'!C4 | C4: ='原始数据与计算'!Y4 | D4: ='原始数据与计算'!Z4 | E4: ='原始数据与计算'!AA4 | F4: ='原始数据与计算'!AB4 | G4: ='原始数据与计算'!AC4 | H4: ='原始数据与计算'!AD4 | I4: ='原始数据与计算'!AE4 | J4: ='原始数据与计算'!AF4 | ... N4: ='原始数据与计算'!AJ4
A5: ='原始数据与计算'!A5 | B5: ='原始数据与计算'!C5 | C5: ='原始数据与计算'!Y5 | D5: ='原始数据与计算'!Z5 | E5: ='原始数据与计算'!AA5 | F5: ='原始数据与计算'!AB5 | G5: ='原始数据与计算'!AC5 | H5: ='原始数据与计算'!AD5 | I5: ='原始数据与计算'!AE5 | J5: ='原始数据与计算'!AF5 | ... N5: ='原始数据与计算'!AJ5

Sheet 核心样本
A1: 公司 | B1: ltm_ev_revenue | C1: ntm_ev_revenue | D1: ltm_ev_ebitda | E1: ntm_ev_ebitda | F1: ltm_pe | G1: ntm_pe | H1: ltm_ps | I1: ntm_ps | J1: ltm_fcf_yield | K1: ntm_fcf_yield | L1: price_to_book | M1: ltm_roe
A2: ='原始数据与计算'!A3 | B2: ='原始数据与计算'!Y3 | C2: ='原始数据与计算'!Z3 | D2: ='原始数据与计算'!AA3 | E2: ='原始数据与计算'!AB3 | F2: ='原始数据与计算'!AC3 | G2: ='原始数据与计算'!AD3 | H2: ='原始数据与计算'!AE3 | I2: ='原始数据与计算'!AF3 | ... M2: ='原始数据与计算'!AJ3
A3: ='原始数据与计算'!A4 | B3: ='原始数据与计算'!Y4 | C3: ='原始数据与计算'!Z4 | D3: ='原始数据与计算'!AA4 | E3: ='原始数据与计算'!AB4 | F3: ='原始数据与计算'!AC4 | G3: ='原始数据与计算'!AD4 | H3: ='原始数据与计算'!AE4 | I3: ='原始数据与计算'!AF4 | ... M3: ='原始数据与计算'!AJ4
A4: ='原始数据与计算'!A5 | B4: ='原始数据与计算'!Y5 | C4: ='原始数据与计算'!Z5 | D4: ='原始数据与计算'!AA5 | E4: ='原始数据与计算'!AB5 | F4: ='原始数据与计算'!AC5 | G4: ='原始数据与计算'!AD5 | H4: ='原始数据与计算'!AE5 | I4: ='原始数据与计算'!AF5 | ... M4: ='原始数据与计算'!AJ5

Sheet 同行统计
A1: 指标 | B1: 样本数 | C1: P25 | D1: 中位数 | E1: P75 | F1: 是否稳健
A2: ltm_ev_revenue | B2: =COUNT('核心样本'!B2:B4) | C2: =IFERROR(PERCENTILE('核心样本'!B2:B4,0.25),"") | D2: =IFERROR(MEDIAN('核心样本'!B2:B4),"") | E2: =IFERROR(PERCENTILE('核心样本'!B2:B4,0.75),"") | F2: =IF(B2>=3,"是","否")
A3: ntm_ev_revenue | B3: =COUNT('核心样本'!C2:C4) | C3: =IFERROR(PERCENTILE('核心样本'!C2:C4,0.25),"") | D3: =IFERROR(MEDIAN('核心样本'!C2:C4),"") | E3: =IFERROR(PERCENTILE('核心样本'!C2:C4,0.75),"") | F3: =IF(B3>=3,"是","否")
A4: ltm_ev_ebitda | B4: =COUNT('核心样本'!D2:D4) | C4: =IFERROR(PERCENTILE('核心样本'!D2:D4,0.25),"") | D4: =IFERROR(MEDIAN('核心样本'!D2:D4),"") | E4: =IFERROR(PERCENTILE('核心样本'!D2:D4,0.75),"") | F4: =IF(B4>=3,"是","否")
A5: ntm_ev_ebitda | B5: =COUNT('核心样本'!E2:E4) | C5: =IFERROR(PERCENTILE('核心样本'!E2:E4,0.25),"") | D5: =IFERROR(MEDIAN('核心样本'!E2:E4),"") | E5: =IFERROR(PERCENTILE('核心样本'!E2:E4,0.75),"") | F5: =IF(B5>=3,"是","否")
A6: ltm_pe | B6: =COUNT('核心样本'!F2:F4) | C6: =IFERROR(PERCENTILE('核心样本'!F2:F4,0.25),"") | D6: =IFERROR(MEDIAN('核心样本'!F2:F4),"") | E6: =IFERROR(PERCENTILE('核心样本'!F2:F4,0.75),"") | F6: =IF(B6>=3,"是","否")
A7: ntm_pe | B7: =COUNT('核心样本'!G2:G4) | C7: =IFERROR(PERCENTILE('核心样本'!G2:G4,0.25),"") | D7: =IFERROR(MEDIAN('核心样本'!G2:G4),"") | E7: =IFERROR(PERCENTILE('核心样本'!G2:G4,0.75),"") | F7: =IF(B7>=3,"是","否")
A8: ltm_ps | B8: =COUNT('核心样本'!H2:H4) | C8: =IFERROR(PERCENTILE('核心样本'!H2:H4,0.25),"") | D8: =IFERROR(MEDIAN('核心样本'!H2:H4),"") | E8: =IFERROR(PERCENTILE('核心样本'!H2:H4,0.75),"") | F8: =IF(B8>=3,"是","否")
A9: ntm_ps | B9: =COUNT('核心样本'!I2:I4) | C9: =IFERROR(PERCENTILE('核心样本'!I2:I4,0.25),"") | D9: =IFERROR(MEDIAN('核心样本'!I2:I4),"") | E9: =IFERROR(PERCENTILE('核心样本'!I2:I4,0.75),"") | F9: =IF(B9>=3,"是","否")
A10: ltm_fcf_yield | B10: =COUNT('核心样本'!J2:J4) | C10: =IFERROR(PERCENTILE('核心样本'!J2:J4,0.25),"") | D10: =IFERROR(MEDIAN('核心样本'!J2:J4),"") | E10: =IFERROR(PERCENTILE('核心样本'!J2:J4,0.75),"") | F10: =IF(B10>=3,"是","否")
A11: ntm_fcf_yield | B11: =COUNT('核心样本'!K2:K4) | C11: =IFERROR(PERCENTILE('核心样本'!K2:K4,0.25),"") | D11: =IFERROR(MEDIAN('核心样本'!K2:K4),"") | E11: =IFERROR(PERCENTILE('核心样本'!K2:K4,0.75),"") | F11: =IF(B11>=3,"是","否")
A12: price_to_book | B12: =COUNT('核心样本'!L2:L4) | C12: =IFERROR(PERCENTILE('核心样本'!L2:L4,0.25),"") | D12: =IFERROR(MEDIAN('核心样本'!L2:L4),"") | E12: =IFERROR(PERCENTILE('核心样本'!L2:L4,0.75),"") | F12: =IF(B12>=3,"是","否")
A13: ltm_roe | B13: =COUNT('核心样本'!M2:M4) | C13: =IFERROR(PERCENTILE('核心样本'!M2:M4,0.25),"") | D13: =IFERROR(MEDIAN('核心样本'!M2:M4),"") | E13: =IFERROR(PERCENTILE('核心样本'!M2:M4,0.75),"") | F13: =IF(B13>=3,"是","否")

Sheet 隐含估值
A1: 指标 | B1: P25锚 | C1: 中位数锚 | D1: P75锚 | E1: 目标基本面 | F1: P25隐含每股价值 | G1: 中位数隐含每股价值 | H1: P75隐含每股价值 | I1: 当前股价 | J1: 中位数空间
A2: ltm_ev_revenue | B2: ='同行统计'!C2 | C2: ='同行统计'!D2 | D2: ='同行统计'!E2 | E2: ='原始数据与计算'!L2 | F2: =IFERROR((B2*E2-('原始数据与计算'!X2-'原始数据与计算'!W2))/'原始数据与计算'!E2,"") | G2: =IFERROR((C2*E2-('原始数据与计算'!X2-'原始数据与计算'!W2))/'原始数据与计算'!E2,"") | H2: =IFERROR((D2*E2-('原始数据与计算'!X2-'原始数据与计算'!W2))/'原始数据与计算'!E2,"") | I2: ='原始数据与计算'!D2 | J2: =IFERROR(G2/I2-1,"")
A3: ntm_ev_revenue | B3: ='同行统计'!C3 | C3: ='同行统计'!D3 | D3: ='同行统计'!E3 | E3: ='原始数据与计算'!M2 | F3: =IFERROR((B3*E3-('原始数据与计算'!X2-'原始数据与计算'!W2))/'原始数据与计算'!E2,"") | G3: =IFERROR((C3*E3-('原始数据与计算'!X2-'原始数据与计算'!W2))/'原始数据与计算'!E2,"") | H3: =IFERROR((D3*E3-('原始数据与计算'!X2-'原始数据与计算'!W2))/'原始数据与计算'!E2,"") | I3: ='原始数据与计算'!D2 | J3: =IFERROR(G3/I3-1,"")
A4: ltm_ev_ebitda | B4: ='同行统计'!C4 | C4: ='同行统计'!D4 | D4: ='同行统计'!E4 | E4: ='原始数据与计算'!N2 | F4: =IFERROR((B4*E4-('原始数据与计算'!X2-'原始数据与计算'!W2))/'原始数据与计算'!E2,"") | G4: =IFERROR((C4*E4-('原始数据与计算'!X2-'原始数据与计算'!W2))/'原始数据与计算'!E2,"") | H4: =IFERROR((D4*E4-('原始数据与计算'!X2-'原始数据与计算'!W2))/'原始数据与计算'!E2,"") | I4: ='原始数据与计算'!D2 | J4: =IFERROR(G4/I4-1,"")
A5: ntm_ev_ebitda | B5: ='同行统计'!C5 | C5: ='同行统计'!D5 | D5: ='同行统计'!E5 | E5: ='原始数据与计算'!O2 | F5: =IFERROR((B5*E5-('原始数据与计算'!X2-'原始数据与计算'!W2))/'原始数据与计算'!E2,"") | G5: =IFERROR((C5*E5-('原始数据与计算'!X2-'原始数据与计算'!W2))/'原始数据与计算'!E2,"") | H5: =IFERROR((D5*E5-('原始数据与计算'!X2-'原始数据与计算'!W2))/'原始数据与计算'!E2,"") | I5: ='原始数据与计算'!D2 | J5: =IFERROR(G5/I5-1,"")
A6: ltm_pe | B6: ='同行统计'!C6 | C6: ='同行统计'!D6 | D6: ='同行统计'!E6 | E6: ='原始数据与计算'!P2 | F6: =IFERROR(B6*E6/'原始数据与计算'!E2,"") | G6: =IFERROR(C6*E6/'原始数据与计算'!E2,"") | H6: =IFERROR(D6*E6/'原始数据与计算'!E2,"") | I6: ='原始数据与计算'!D2 | J6: =IFERROR(G6/I6-1,"")
A7: ntm_pe | B7: ='同行统计'!C7 | C7: ='同行统计'!D7 | D7: ='同行统计'!E7 | E7: ='原始数据与计算'!Q2 | F7: =IFERROR(B7*E7/'原始数据与计算'!E2,"") | G7: =IFERROR(C7*E7/'原始数据与计算'!E2,"") | H7: =IFERROR(D7*E7/'原始数据与计算'!E2,"") | I7: ='原始数据与计算'!D2 | J7: =IFERROR(G7/I7-1,"")
A8: ltm_ps | B8: ='同行统计'!C8 | C8: ='同行统计'!D8 | D8: ='同行统计'!E8 | E8: ='原始数据与计算'!L2 | F8: =IFERROR(B8*E8/'原始数据与计算'!E2,"") | G8: =IFERROR(C8*E8/'原始数据与计算'!E2,"") | H8: =IFERROR(D8*E8/'原始数据与计算'!E2,"") | I8: ='原始数据与计算'!D2 | J8: =IFERROR(G8/I8-1,"")
A9: ntm_ps | B9: ='同行统计'!C9 | C9: ='同行统计'!D9 | D9: ='同行统计'!E9 | E9: ='原始数据与计算'!M2 | F9: =IFERROR(B9*E9/'原始数据与计算'!E2,"") | G9: =IFERROR(C9*E9/'原始数据与计算'!E2,"") | H9: =IFERROR(D9*E9/'原始数据与计算'!E2,"") | I9: ='原始数据与计算'!D2 | J9: =IFERROR(G9/I9-1,"")
A10: ltm_fcf_yield | B10: ='同行统计'!C10 | C10: ='同行统计'!D10 | D10: ='同行统计'!E10 | E10: ='原始数据与计算'!R2 | F10: =IFERROR(E10/B10/'原始数据与计算'!E2,"") | G10: =IFERROR(E10/C10/'原始数据与计算'!E2,"") | H10: =IFERROR(E10/D10/'原始数据与计算'!E2,"") | I10: ='原始数据与计算'!D2 | J10: =IFERROR(G10/I10-1,"")
A11: ntm_fcf_yield | B11: ='同行统计'!C11 | C11: ='同行统计'!D11 | D11: ='同行统计'!E11 | E11: ='原始数据与计算'!S2 | F11: =IFERROR(E11/B11/'原始数据与计算'!E2,"") | G11: =IFERROR(E11/C11/'原始数据与计算'!E2,"") | H11: =IFERROR(E11/D11/'原始数据与计算'!E2,"") | I11: ='原始数据与计算'!D2 | J11: =IFERROR(G11/I11-1,"")
A12: price_to_book | B12: ='同行统计'!C12 | C12: ='同行统计'!D12 | D12: ='同行统计'!E12 | E12: ='原始数据与计算'!D2/'原始数据与计算'!AI2 | F12: =IFERROR(B12*E12,"") | G12: =IFERROR(C12*E12,"") | H12: =IFERROR(D12*E12,"") | I12: ='原始数据与计算'!D2 | J12: =IFERROR(G12/I12-1,"")

Sheet 情景与敏感性
A1: 基本面因子/估值锚因子 | B1: 0.8 | C1: 0.9 | D1: 1 | E1: 1.1 | F1: 1.2
A2: 0.8 | B2: =IFERROR('隐含估值'!C12*B1*'隐含估值'!E12*$A2,"") | C2: =IFERROR('隐含估值'!C12*C1*'隐含估值'!E12*$A2,"") | D2: =IFERROR('隐含估值'!C12*D1*'隐含估值'!E12*$A2,"") | E2: =IFERROR('隐含估值'!C12*E1*'隐含估值'!E12*$A2,"") | F2: =IFERROR('隐含估值'!C12*F1*'隐含估值'!E12*$A2,"")
A3: 0.9 | B3: =IFERROR('隐含估值'!C12*B1*'隐含估值'!E12*$A3,"") | C3: =IFERROR('隐含估值'!C12*C1*'隐含估值'!E12*$A3,"") | D3: =IFERROR('隐含估值'!C12*D1*'隐含估值'!E12*$A3,"") | E3: =IFERROR('隐含估值'!C12*E1*'隐含估值'!E12*$A3,"") | F3: =IFERROR('隐含估值'!C12*F1*'隐含估值'!E12*$A3,"")
A4: 1 | B4: =IFERROR('隐含估值'!C12*B1*'隐含估值'!E12*$A4,"") | C4: =IFERROR('隐含估值'!C12*C1*'隐含估值'!E12*$A4,"") | D4: =IFERROR('隐含估值'!C12*D1*'隐含估值'!E12*$A4,"") | E4: =IFERROR('隐含估值'!C12*E1*'隐含估值'!E12*$A4,"") | F4: =IFERROR('隐含估值'!C12*F1*'隐含估值'!E12*$A4,"")
A5: 1.1 | B5: =IFERROR('隐含估值'!C12*B1*'隐含估值'!E12*$A5,"") | C5: =IFERROR('隐含估值'!C12*C1*'隐含估值'!E12*$A5,"") | D5: =IFERROR('隐含估值'!C12*D1*'隐含估值'!E12*$A5,"") | E5: =IFERROR('隐含估值'!C12*E1*'隐含估值'!E12*$A5,"") | F5: =IFERROR('隐含估值'!C12*F1*'隐含估值'!E12*$A5,"")
A6: 1.2 | B6: =IFERROR('隐含估值'!C12*B1*'隐含估值'!E12*$A6,"") | C6: =IFERROR('隐含估值'!C12*C1*'隐含估值'!E12*$A6,"") | D6: =IFERROR('隐含估值'!C12*D1*'隐含估值'!E12*$A6,"") | E6: =IFERROR('隐含估值'!C12*E1*'隐含估值'!E12*$A6,"") | F6: =IFERROR('隐含估值'!C12*F1*'隐含估值'!E12*$A6,"")
A8: 说明 | B8: 每个格子均重新应用目标基本面与估值锚，不是对最终价格的静态粘贴。

Sheet 市场隐含预期
A1: 项目 | B1: 数值 | C1: 公式含义
A2: 当前主指标 | B2: ='原始数据与计算'!AI2 | C2: 目标公司当前市场倍数或收益率
A3: 核心同行中位数 | B3: ='同行统计'!D12 | C3: 核心样本中位数
A4: 当前相对中位数溢折价 | B4: =IFERROR(B2/B3-1,"") | C4: 正数为溢价，负数为折价；收益率指标需反向解释

Sheet 假设与方法
A1: 假设编号 | B1: 主题 | C1: 内容 | D1: 模型使用位置
A2: ASM-COMP-001 | B2: 主估值指标 | C2: 市净率（P/B） | D2: 隐含估值、情景与敏感性
A3: ASM-COMP-002 | B3: 次要指标 | C3: ltm_pe | D3: 交叉检查
A4: ASM-COMP-003 | B4: 弃用指标 | C4: ltm_ev_ebitda | D4: 方法限制
A5: ASM-COMP-004 | B5: 溢折价原则 | C5: 未给予无依据溢价 | D5: 结论摘要

Sheet 数据质量与失效条件
A1: 类型 | B1: 编号 | C1: 内容 | D1: 处理要求
A2: 失效条件 | B2: INV-001 | C2: 资产质量恶化 | D2: 到达观察时点后更新模型并重新发布
A3: 失效条件 | B3: INV-002 | C3: ROE下降 | D3: 到达观察时点后更新模型并重新发布
A4: 失效条件 | B4: INV-003 | C4: 资本补充超预期 | D4: 到达观察时点后更新模型并重新发布
A5: 警告 | B5: WRN-001 | C5: 市净率—净资产收益率（P/B–ROE）交叉检查仅有 3 个有效核心可比公司观测值，未运行回归 | D5: 评估影响并在摘要中披露

Sheet 数据来源
A1: 来源ID | B1: 标题 | C1: 发布日期 | D1: URL/定位 | E1: 备注
A2: SRC-DEMO | B2: 结构测试数据，不代表真实公司 | C2: 2026-06-30

Sheet 结论依据
A1: 主题 | B1: 分析结论 | C1: 数值来源
A2: 总体结论 | B2: 结构测试示例，不形成真实估值结论 | C2: 结论摘要及隐含估值
A3: 同行比较 | B3: 增长、盈利、现金转化和风险逐项比较完成 | C3: 同行筛选、交易倍数
A4: 溢折价逻辑 | B4: 未给予无依据溢价 | C4: 假设与方法、市场隐含预期

Sheet 模型检查
A1: 检查项 | B1: 实际值 | C1: 期望值 | D1: 差异 | E1: 容差 | F1: 状态 | G1: 修复提示
A2: 目标公司唯一 | B2: =COUNTIF('原始数据与计算'!C2:C5,"Target") | C2: 1 | D2: =B2-C2 | E2: 0 | F2: =IF(ABS(D2)<=E2,"PASS","FAIL") | G2: 目标公司分类必须且只能出现一次
A3: 主指标有效核心样本 | B3: ='同行统计'!B12 | C3: 3 | D3: =B3-C3 | E3: 0 | F3: =IF(B3>=C3,"PASS","FAIL") | G3: 至少需要三家有效核心可比公司
A4: 目标市值重算 | B4: ='原始数据与计算'!W2 | C4: ='原始数据与计算'!D2*'原始数据与计算'!E2 | D4: =B4-C4 | E4: 1e-06 | F4: =IF(ABS(D4)<=E4,"PASS","FAIL") | G4: 检查股价与完全稀释股数
A5: 目标EV重算 | B5: ='原始数据与计算'!X2 | C5: ='原始数据与计算'!W2+'原始数据与计算'!F2-'原始数据与计算'!G2+'原始数据与计算'!H2+'原始数据与计算'!I2+'原始数据与计算'!J2-'原始数据与计算'!K2 | D5: =B5-C5 | E5: 1e-06 | F5: =IF(ABS(D5)<=E5,"PASS","FAIL") | G5: 检查债务、现金、租赁及非经营投资口径
A6: 敏感性公式数量 | B6: =COUNT('情景与敏感性'!B2:F6) | C6: 25 | D6: =B6-C6 | E6: 0 | F6: =IF(ABS(D6)<=E6,"PASS","FAIL") | G6: 25个敏感性格均须为公式
A7: 模型总体状态 | B7: =COUNTIF(F2:F6,"FAIL") | C7: 0 | D7: =B7-C7 | E7: 0 | F7: =IF(B7=0,"PASS","FAIL") | G7: 任一检查失败即阻断结论
