Workbook

Sheet 封面
A1: 杠杆收购（LBO）：单一Excel决策与审计模型
A4: 本工作簿是唯一正式用户交付物；交易逻辑、回报、风险、来源和检查均在簿内。
A6: 目标公司 | B6: 结构验证示例公司（DEMO）
A7: 估值/交易基准日 | B7: 2026-07-16
A8: 报告币种 | B8: USD
A9: 默认退出窗口 | B9: 第3年至第7年
A10: 默认交付策略 | B10: 只交付Excel；独立Markdown仅在用户明确要求时额外生成

Sheet 交易摘要
A1: 项目 | B1: 数值/结论 | C1: 解释 | D1: 追溯位置
A2: 模型状态 | B2: ='模型检查'!F8 | C2: 只有PASS才允许发布MOIC、IRR和最高收购价 | D2: 模型检查
A3: 目标公司 | B3: 结构验证示例公司 | C3: DEMO | D3: 封面
A4: 交易基准日 | B4: 2026-07-16 | C4: USD | D4: 交易与融资假设
A5: 股权购买价 | B5: ='交易与融资假设'!B2 | C5: 金额 | D5: 交易与融资假设
A6: 进入企业价值 | B6: ='交易与融资假设'!B17 | C6: 金额 | D6: 交易与融资假设
A7: 进入倍数 | B7: ='交易与融资假设'!B18 | C7: 企业价值/EBITDA | D7: 交易与融资假设
A8: 财务投资人股权 | B8: ='Sources & Uses'!D5 | C8: 金额 | D8: Sources & Uses
A9: 基准退出年 | B9: 5 | C9: 持有期 | D9: 退出回报
A10: 基准退出倍数 | B10: 7.625 | C10: 倍数 | D10: 退出回报
A11: 基准MOIC | B11: ='退出回报'!N9 | C11: 投资资本倍数 | D11: 退出回报
A12: 基准XIRR | B12: ='退出回报'!P9 | C12: 按实际周年日期计算 | D12: 退出回报
A13: 基准利润 | B13: ='退出回报'!M9 | C13: 退出所得减累计投入 | D13: 退出回报
A14: 核心回报来源 | B14: 详见回报归因 | C14: EBITDA增长、倍数变化、净债务偿还及费用 | D14: 回报归因

Sheet 交易与融资假设
A1: 字段 | B1: 数值 | C1: 单位/说明 | D1: 来源/假设编号
A2: 股权购买价 | B2: 1000 | C2: 金额 | D2: 交易假设
A3: 需偿还债务 | B3: 300 | C3: 金额 | D3: 交易假设
A4: 目标现金使用 | B4: 40 | C4: 金额 | D4: 交易假设
A5: 交易费用 | B5: 20 | C5: 金额 | D5: 交易假设
A6: 融资费用 | B6: 10 | C6: 金额 | D6: 融资假设
A7: 最低现金 | B7: 30 | C7: 金额 | D7: 流动性假设
A8: 管理层滚存 | B8: 50 | C8: 金额 | D8: 交易假设
A9: 进入EBITDA | B9: 160 | C9: 金额 | D9: 经营假设
A10: 退出费用率 | B10: 0.01 | C10: 百分比 | D10: 退出假设
A11: 退出债务类调整 | B11: 0 | C11: 金额 | D11: 退出假设
A12: 交易基准日 | B12: 46219 | C12: 日期 | D12: 估值基准
A13: 收购现金 | B13: 80 | C13: 金额 | D13: 交易假设
... A16: 其他债务类项目 | B16: 0 | C16: 金额 | D16: 估值调整
A17: 进入企业价值 | B17: =B2+B3-B13+B14+B15+B16 | C17: 金额 | D17: 股权购买价+净债务+类债务调整
A18: 进入倍数 | B18: =IFERROR(B17/B9,"") | C18: 倍数 | D18: 进入企业价值/进入EBITDA

Sheet Sources & Uses
A1: 用途 | B1: 金额 | C1: 资金来源 | D1: 金额
A2: 股权购买价 | B2: ='交易与融资假设'!B2 | C2: 新债务 | D2: =SUM('债务假设'!B2:B200)
A3: 需偿还债务 | B3: ='交易与融资假设'!B3 | C3: 目标现金使用 | D3: ='交易与融资假设'!B4
A4: 优先股偿还 | B4: 0 | C4: 管理层滚存 | D4: ='交易与融资假设'!B8
A5: 其他债务类偿还 | B5: 0 | C5: 财务投资人股权 | D5: =B9-SUM(D2:D4)
A6: 交易费用 | B6: ='交易与融资假设'!B5
A7: 融资费用 | B7: ='交易与融资假设'!B6
A8: 最低现金 | B8: ='交易与融资假设'!B7
A9: 总用途 | B9: =SUM(B2:B8) | C9: 总来源 | D9: =SUM(D2:D5)
A10: 平衡检查 | B10: =D9-B9

Sheet 债务假设
A1: 债务层级 | B1: 期初余额 | C1: 现金利率 | D1: PIK利率 | E1: 强制摊还率 | F1: 偿还优先级 | G1: 是否循环额度 | H1: 承诺额度 | I1: 到期年 | J1: 来源/假设编号
A2: Revolver | B2: 0 | C2: 0.09 | D2: 0 | E2: 0 | F2: 1 | G2: 1 | H2: 100 | I2: 5 | J2: 融资条款
A3: Term Loan | B3: 600 | C3: 0.08 | D3: 0 | E3: 0.01 | F3: 2 | G3: 0 | H3: 0 | I3: 7 | J3: 融资条款

Sheet 经营预测
A1: 年度 | B1: EBITDA | C1: 同比增长 | D1: 现金税 | E1: 资本开支 | F1: 营运资本增加 | G1: 其他现金成本 | H1: 后续股权投入 | I1: 计划财务投资人分红 | J1: 利息前可用于偿债现金
A2: 1 | B2: 168 | C2: =IFERROR(B2/'交易与融资假设'!B9-1,"") | D2: 19 | E2: 29 | F2: 5 | G2: 0 | H2: 0 | I2: 0 | J2: =B2-SUM(D2:G2)+H2/('Sources & Uses'!D5/('Sources & Uses'!D5+'交易与融资假设'!B8))
A3: 2 | B3: 176.4 | C3: =IFERROR(B3/B2-1,"") | D3: 20 | E3: 30 | F3: 5 | G3: 0 | H3: 0 | I3: 0 | J3: =B3-SUM(D3:G3)+H3/('Sources & Uses'!D5/('Sources & Uses'!D5+'交易与融资假设'!B8))
A4: 3 | B4: 185.22 | C4: =IFERROR(B4/B3-1,"") | D4: 21 | E4: 31 | F4: 5 | G4: 0 | H4: 0 | I4: 0 | J4: =B4-SUM(D4:G4)+H4/('Sources & Uses'!D5/('Sources & Uses'!D5+'交易与融资假设'!B8))
A5: 4 | B5: 194.481 | C5: =IFERROR(B5/B4-1,"") | D5: 22 | E5: 32 | F5: 5 | G5: 0 | H5: 0 | I5: 0 | J5: =B5-SUM(D5:G5)+H5/('Sources & Uses'!D5/('Sources & Uses'!D5+'交易与融资假设'!B8))
A6: 5 | B6: 204.20505 | C6: =IFERROR(B6/B5-1,"") | D6: 23 | E6: 33 | F6: 5 | G6: 0 | H6: 0 | I6: 0 | J6: =B6-SUM(D6:G6)+H6/('Sources & Uses'!D5/('Sources & Uses'!D5+'交易与融资假设'!B8))
A7: 6 | B7: 214.4153 | C7: =IFERROR(B7/B6-1,"") | D7: 24 | E7: 34 | F7: 5 | G7: 0 | H7: 0 | I7: 0 | J7: =B7-SUM(D7:G7)+H7/('Sources & Uses'!D5/('Sources & Uses'!D5+'交易与融资假设'!B8))
A8: 7 | B8: 225.13607 | C8: =IFERROR(B8/B7-1,"") | D8: 25 | E8: 35 | F8: 5 | G8: 0 | H8: 0 | I8: 0 | J8: =B8-SUM(D8:G8)+H8/('Sources & Uses'!D5/('Sources & Uses'!D5+'交易与融资假设'!B8))

Sheet 分层债务
A1: 年度 | B1: 债务层级 | C1: 期初余额 | D1: 现金利息 | E1: PIK利息 | F1: 强制摊还 | G1: 现金扫款 | H1: 循环额度提款 | I1: 期末余额
A2: ='经营预测'!A2 | B2: ='债务假设'!A2 | C2: ='债务假设'!B2 | D2: =C2*'债务假设'!C2 | E2: =C2*'债务假设'!D2 | F2: =MIN(C2+E2,IF(AND('债务假设'!I2<>"",A2>='债务假设'!I2),C2+E2,C2*'债务假设'!E2)) | G2: =MIN(MAX(0,'现金与利息'!B2-SUMIFS($D$2:$D$500,$A$2:$A$500,A2)-SUMIFS($F$2:$F$500,$A$2:$A$500,A2)-0),MAX(0,C2+E2-F2)) | H2: =MIN(MAX(0,SUMIFS($D$2:$D$500,$A$2:$A$500,A2)+SUMIFS($F$2:$F$500,$A$2:$A$500,A2)-'现金与利息'!B2),MAX(0,'债务假设'!H2-C2-E2)) | I2: =MAX(0,C2+E2+H2-F2-G2)
A3: ='经营预测'!A2 | B3: ='债务假设'!A3 | C3: ='债务假设'!B3 | D3: =C3*'债务假设'!C3 | E3: =C3*'债务假设'!D3 | F3: =MIN(C3+E3,IF(AND('债务假设'!I3<>"",A3>='债务假设'!I3),C3+E3,C3*'债务假设'!E3)) | G3: =MIN(MAX(0,'现金与利息'!B2-SUMIFS($D$2:$D$500,$A$2:$A$500,A3)-SUMIFS($F$2:$F$500,$A$2:$A$500,A3)-SUM(G2:G2)),MAX(0,C3+E3-F3)) | H3: ='债务假设'!H3*0 | I3: =MAX(0,C3+E3+H3-F3-G3)
A4: ='经营预测'!A3 | B4: ='债务假设'!A2 | C4: ='分层债务'!I2 | D4: =C4*'债务假设'!C2 | E4: =C4*'债务假设'!D2 | F4: =MIN(C4+E4,IF(AND('债务假设'!I2<>"",A4>='债务假设'!I2),C4+E4,C4*'债务假设'!E2)) | G4: =MIN(MAX(0,'现金与利息'!B3-SUMIFS($D$2:$D$500,$A$2:$A$500,A4)-SUMIFS($F$2:$F$500,$A$2:$A$500,A4)-0),MAX(0,C4+E4-F4)) | H4: =MIN(MAX(0,SUMIFS($D$2:$D$500,$A$2:$A$500,A4)+SUMIFS($F$2:$F$500,$A$2:$A$500,A4)-'现金与利息'!B3),MAX(0,'债务假设'!H2-C4-E4)) | I4: =MAX(0,C4+E4+H4-F4-G4)
A5: ='经营预测'!A3 | B5: ='债务假设'!A3 | C5: ='分层债务'!I3 | D5: =C5*'债务假设'!C3 | E5: =C5*'债务假设'!D3 | F5: =MIN(C5+E5,IF(AND('债务假设'!I3<>"",A5>='债务假设'!I3),C5+E5,C5*'债务假设'!E3)) | G5: =MIN(MAX(0,'现金与利息'!B3-SUMIFS($D$2:$D$500,$A$2:$A$500,A5)-SUMIFS($F$2:$F$500,$A$2:$A$500,A5)-SUM(G4:G4)),MAX(0,C5+E5-F5)) | H5: ='债务假设'!H3*0 | I5: =MAX(0,C5+E5+H5-F5-G5)
A6: ='经营预测'!A4 | B6: ='债务假设'!A2 | C6: ='分层债务'!I4 | D6: =C6*'债务假设'!C2 | E6: =C6*'债务假设'!D2 | F6: =MIN(C6+E6,IF(AND('债务假设'!I2<>"",A6>='债务假设'!I2),C6+E6,C6*'债务假设'!E2)) | G6: =MIN(MAX(0,'现金与利息'!B4-SUMIFS($D$2:$D$500,$A$2:$A$500,A6)-SUMIFS($F$2:$F$500,$A$2:$A$500,A6)-0),MAX(0,C6+E6-F6)) | H6: =MIN(MAX(0,SUMIFS($D$2:$D$500,$A$2:$A$500,A6)+SUMIFS($F$2:$F$500,$A$2:$A$500,A6)-'现金与利息'!B4),MAX(0,'债务假设'!H2-C6-E6)) | I6: =MAX(0,C6+E6+H6-F6-G6)
A7: ='经营预测'!A4 | B7: ='债务假设'!A3 | C7: ='分层债务'!I5 | D7: =C7*'债务假设'!C3 | E7: =C7*'债务假设'!D3 | F7: =MIN(C7+E7,IF(AND('债务假设'!I3<>"",A7>='债务假设'!I3),C7+E7,C7*'债务假设'!E3)) | G7: =MIN(MAX(0,'现金与利息'!B4-SUMIFS($D$2:$D$500,$A$2:$A$500,A7)-SUMIFS($F$2:$F$500,$A$2:$A$500,A7)-SUM(G6:G6)),MAX(0,C7+E7-F7)) | H7: ='债务假设'!H3*0 | I7: =MAX(0,C7+E7+H7-F7-G7)
A8: ='经营预测'!A5 | B8: ='债务假设'!A2 | C8: ='分层债务'!I6 | D8: =C8*'债务假设'!C2 | E8: =C8*'债务假设'!D2 | F8: =MIN(C8+E8,IF(AND('债务假设'!I2<>"",A8>='债务假设'!I2),C8+E8,C8*'债务假设'!E2)) | G8: =MIN(MAX(0,'现金与利息'!B5-SUMIFS($D$2:$D$500,$A$2:$A$500,A8)-SUMIFS($F$2:$F$500,$A$2:$A$500,A8)-0),MAX(0,C8+E8-F8)) | H8: =MIN(MAX(0,SUMIFS($D$2:$D$500,$A$2:$A$500,A8)+SUMIFS($F$2:$F$500,$A$2:$A$500,A8)-'现金与利息'!B5),MAX(0,'债务假设'!H2-C8-E8)) | I8: =MAX(0,C8+E8+H8-F8-G8)
A9: ='经营预测'!A5 | B9: ='债务假设'!A3 | C9: ='分层债务'!I7 | D9: =C9*'债务假设'!C3 | E9: =C9*'债务假设'!D3 | F9: =MIN(C9+E9,IF(AND('债务假设'!I3<>"",A9>='债务假设'!I3),C9+E9,C9*'债务假设'!E3)) | G9: =MIN(MAX(0,'现金与利息'!B5-SUMIFS($D$2:$D$500,$A$2:$A$500,A9)-SUMIFS($F$2:$F$500,$A$2:$A$500,A9)-SUM(G8:G8)),MAX(0,C9+E9-F9)) | H9: ='债务假设'!H3*0 | I9: =MAX(0,C9+E9+H9-F9-G9)
A10: ='经营预测'!A6 | B10: ='债务假设'!A2 | C10: ='分层债务'!I8 | D10: =C10*'债务假设'!C2 | E10: =C10*'债务假设'!D2 | F10: =MIN(C10+E10,IF(AND('债务假设'!I2<>"",A10>='债务假设'!I2),C10+E10,C10*'债务假设'!E2)) | G10: =MIN(MAX(0,'现金与利息'!B6-SUMIFS($D$2:$D$500,$A$2:$A$500,A10)-SUMIFS($F$2:$F$500,$A$2:$A$500,A10)-0),MAX(0,C10+E10-F10)) | H10: =MIN(MAX(0,SUMIFS($D$2:$D$500,$A$2:$A$500,A10)+SUMIFS($F$2:$F$500,$A$2:$A$500,A10)-'现金与利息'!B6),MAX(0,'债务假设'!H2-C10-E10)) | I10: =MAX(0,C10+E10+H10-F10-G10)
A11: ='经营预测'!A6 | B11: ='债务假设'!A3 | C11: ='分层债务'!I9 | D11: =C11*'债务假设'!C3 | E11: =C11*'债务假设'!D3 | F11: =MIN(C11+E11,IF(AND('债务假设'!I3<>"",A11>='债务假设'!I3),C11+E11,C11*'债务假设'!E3)) | G11: =MIN(MAX(0,'现金与利息'!B6-SUMIFS($D$2:$D$500,$A$2:$A$500,A11)-SUMIFS($F$2:$F$500,$A$2:$A$500,A11)-SUM(G10:G10)),MAX(0,C11+E11-F11)) | H11: ='债务假设'!H3*0 | I11: =MAX(0,C11+E11+H11-F11-G11)
A12: ='经营预测'!A7 | B12: ='债务假设'!A2 | C12: ='分层债务'!I10 | D12: =C12*'债务假设'!C2 | E12: =C12*'债务假设'!D2 | F12: =MIN(C12+E12,IF(AND('债务假设'!I2<>"",A12>='债务假设'!I2),C12+E12,C12*'债务假设'!E2)) | G12: =MIN(MAX(0,'现金与利息'!B7-SUMIFS($D$2:$D$500,$A$2:$A$500,A12)-SUMIFS($F$2:$F$500,$A$2:$A$500,A12)-0),MAX(0,C12+E12-F12)) | H12: =MIN(MAX(0,SUMIFS($D$2:$D$500,$A$2:$A$500,A12)+SUMIFS($F$2:$F$500,$A$2:$A$500,A12)-'现金与利息'!B7),MAX(0,'债务假设'!H2-C12-E12)) | I12: =MAX(0,C12+E12+H12-F12-G12)
A13: ='经营预测'!A7 | B13: ='债务假设'!A3 | C13: ='分层债务'!I11 | D13: =C13*'债务假设'!C3 | E13: =C13*'债务假设'!D3 | F13: =MIN(C13+E13,IF(AND('债务假设'!I3<>"",A13>='债务假设'!I3),C13+E13,C13*'债务假设'!E3)) | G13: =MIN(MAX(0,'现金与利息'!B7-SUMIFS($D$2:$D$500,$A$2:$A$500,A13)-SUMIFS($F$2:$F$500,$A$2:$A$500,A13)-SUM(G12:G12)),MAX(0,C13+E13-F13)) | H13: ='债务假设'!H3*0 | I13: =MAX(0,C13+E13+H13-F13-G13)
A14: ='经营预测'!A8 | B14: ='债务假设'!A2 | C14: ='分层债务'!I12 | D14: =C14*'债务假设'!C2 | E14: =C14*'债务假设'!D2 | F14: =MIN(C14+E14,IF(AND('债务假设'!I2<>"",A14>='债务假设'!I2),C14+E14,C14*'债务假设'!E2)) | G14: =MIN(MAX(0,'现金与利息'!B8-SUMIFS($D$2:$D$500,$A$2:$A$500,A14)-SUMIFS($F$2:$F$500,$A$2:$A$500,A14)-0),MAX(0,C14+E14-F14)) | H14: =MIN(MAX(0,SUMIFS($D$2:$D$500,$A$2:$A$500,A14)+SUMIFS($F$2:$F$500,$A$2:$A$500,A14)-'现金与利息'!B8),MAX(0,'债务假设'!H2-C14-E14)) | I14: =MAX(0,C14+E14+H14-F14-G14)
A15: ='经营预测'!A8 | B15: ='债务假设'!A3 | C15: ='分层债务'!I13 | D15: =C15*'债务假设'!C3 | E15: =C15*'债务假设'!D3 | F15: =MIN(C15+E15,IF(AND('债务假设'!I3<>"",A15>='债务假设'!I3),C15+E15,C15*'债务假设'!E3)) | G15: =MIN(MAX(0,'现金与利息'!B8-SUMIFS($D$2:$D$500,$A$2:$A$500,A15)-SUMIFS($F$2:$F$500,$A$2:$A$500,A15)-SUM(G14:G14)),MAX(0,C15+E15-F15)) | H15: ='债务假设'!H3*0 | I15: =MAX(0,C15+E15+H15-F15-G15)

Sheet 现金与利息
A1: 年度 | B1: 利息前现金 | C1: 现金利息 | D1: PIK利息 | E1: 强制摊还 | F1: 现金扫款 | G1: 循环额度提款 | H1: 期末债务 | I1: 最低现金 | J1: 期末现金 | K1: 期末净债务 | L1: 流动性检查 | M1: 已实现财务投资人分红 | N1: 分红缺口
A2: ='经营预测'!A2 | B2: ='经营预测'!J2 | C2: =SUM('分层债务'!D2:D3) | D2: =SUM('分层债务'!E2:E3) | E2: =SUM('分层债务'!F2:F3) | F2: =SUM('分层债务'!G2:G3) | G2: =SUM('分层债务'!H2:H3) | H2: =SUM('分层债务'!I2:I3) | I2: ='交易与融资假设'!B7 | J2: =I2+MAX(0,B2-C2-E2-F2+G2)-M2/('Sources & Uses'!D5/('Sources & Uses'!D5+'交易与融资假设'!B8)) | K2: =H2-J2 | L2: =IF(B2-C2+G2>=E2,"PASS","FAIL") | M2: =MIN('经营预测'!I2,MAX(0,B2-C2-E2-F2+G2)*('Sources & Uses'!D5/('Sources & Uses'!D5+'交易与融资假设'!B8))) | N2: ='经营预测'!I2-M2
A3: ='经营预测'!A3 | B3: ='经营预测'!J3+MAX(0,J2-I2) | C3: =SUM('分层债务'!D4:D5) | D3: =SUM('分层债务'!E4:E5) | E3: =SUM('分层债务'!F4:F5) | F3: =SUM('分层债务'!G4:G5) | G3: =SUM('分层债务'!H4:H5) | H3: =SUM('分层债务'!I4:I5) | I3: ='交易与融资假设'!B7 | J3: =I3+MAX(0,B3-C3-E3-F3+G3)-M3/('Sources & Uses'!D5/('Sources & Uses'!D5+'交易与融资假设'!B8)) | K3: =H3-J3 | L3: =IF(B3-C3+G3>=E3,"PASS","FAIL") | M3: =MIN('经营预测'!I3,MAX(0,B3-C3-E3-F3+G3)*('Sources & Uses'!D5/('Sources & Uses'!D5+'交易与融资假设'!B8))) | N3: ='经营预测'!I3-M3
A4: ='经营预测'!A4 | B4: ='经营预测'!J4+MAX(0,J3-I3) | C4: =SUM('分层债务'!D6:D7) | D4: =SUM('分层债务'!E6:E7) | E4: =SUM('分层债务'!F6:F7) | F4: =SUM('分层债务'!G6:G7) | G4: =SUM('分层债务'!H6:H7) | H4: =SUM('分层债务'!I6:I7) | I4: ='交易与融资假设'!B7 | J4: =I4+MAX(0,B4-C4-E4-F4+G4)-M4/('Sources & Uses'!D5/('Sources & Uses'!D5+'交易与融资假设'!B8)) | K4: =H4-J4 | L4: =IF(B4-C4+G4>=E4,"PASS","FAIL") | M4: =MIN('经营预测'!I4,MAX(0,B4-C4-E4-F4+G4)*('Sources & Uses'!D5/('Sources & Uses'!D5+'交易与融资假设'!B8))) | N4: ='经营预测'!I4-M4
A5: ='经营预测'!A5 | B5: ='经营预测'!J5+MAX(0,J4-I4) | C5: =SUM('分层债务'!D8:D9) | D5: =SUM('分层债务'!E8:E9) | E5: =SUM('分层债务'!F8:F9) | F5: =SUM('分层债务'!G8:G9) | G5: =SUM('分层债务'!H8:H9) | H5: =SUM('分层债务'!I8:I9) | I5: ='交易与融资假设'!B7 | J5: =I5+MAX(0,B5-C5-E5-F5+G5)-M5/('Sources & Uses'!D5/('Sources & Uses'!D5+'交易与融资假设'!B8)) | K5: =H5-J5 | L5: =IF(B5-C5+G5>=E5,"PASS","FAIL") | M5: =MIN('经营预测'!I5,MAX(0,B5-C5-E5-F5+G5)*('Sources & Uses'!D5/('Sources & Uses'!D5+'交易与融资假设'!B8))) | N5: ='经营预测'!I5-M5
A6: ='经营预测'!A6 | B6: ='经营预测'!J6+MAX(0,J5-I5) | C6: =SUM('分层债务'!D10:D11) | D6: =SUM('分层债务'!E10:E11) | E6: =SUM('分层债务'!F10:F11) | F6: =SUM('分层债务'!G10:G11) | G6: =SUM('分层债务'!H10:H11) | H6: =SUM('分层债务'!I10:I11) | I6: ='交易与融资假设'!B7 | J6: =I6+MAX(0,B6-C6-E6-F6+G6)-M6/('Sources & Uses'!D5/('Sources & Uses'!D5+'交易与融资假设'!B8)) | K6: =H6-J6 | L6: =IF(B6-C6+G6>=E6,"PASS","FAIL") | M6: =MIN('经营预测'!I6,MAX(0,B6-C6-E6-F6+G6)*('Sources & Uses'!D5/('Sources & Uses'!D5+'交易与融资假设'!B8))) | N6: ='经营预测'!I6-M6
A7: ='经营预测'!A7 | B7: ='经营预测'!J7+MAX(0,J6-I6) | C7: =SUM('分层债务'!D12:D13) | D7: =SUM('分层债务'!E12:E13) | E7: =SUM('分层债务'!F12:F13) | F7: =SUM('分层债务'!G12:G13) | G7: =SUM('分层债务'!H12:H13) | H7: =SUM('分层债务'!I12:I13) | I7: ='交易与融资假设'!B7 | J7: =I7+MAX(0,B7-C7-E7-F7+G7)-M7/('Sources & Uses'!D5/('Sources & Uses'!D5+'交易与融资假设'!B8)) | K7: =H7-J7 | L7: =IF(B7-C7+G7>=E7,"PASS","FAIL") | M7: =MIN('经营预测'!I7,MAX(0,B7-C7-E7-F7+G7)*('Sources & Uses'!D5/('Sources & Uses'!D5+'交易与融资假设'!B8))) | N7: ='经营预测'!I7-M7
A8: ='经营预测'!A8 | B8: ='经营预测'!J8+MAX(0,J7-I7) | C8: =SUM('分层债务'!D14:D15) | D8: =SUM('分层债务'!E14:E15) | E8: =SUM('分层债务'!F14:F15) | F8: =SUM('分层债务'!G14:G15) | G8: =SUM('分层债务'!H14:H15) | H8: =SUM('分层债务'!I14:I15) | I8: ='交易与融资假设'!B7 | J8: =I8+MAX(0,B8-C8-E8-F8+G8)-M8/('Sources & Uses'!D5/('Sources & Uses'!D5+'交易与融资假设'!B8)) | K8: =H8-J8 | L8: =IF(B8-C8+G8>=E8,"PASS","FAIL") | M8: =MIN('经营预测'!I8,MAX(0,B8-C8-E8-F8+G8)*('Sources & Uses'!D5/('Sources & Uses'!D5+'交易与融资假设'!B8))) | N8: ='经营预测'!I8-M8

Sheet 退出回报
A1: 退出年 | B1: 退出倍数 | C1: 退出EBITDA | D1: 企业价值 | E1: 期末债务 | F1: 期末现金 | G1: 退出债务类调整 | H1: 退出费用 | I1: 股权价值 | J1: 财务投资人持股 | K1: 财务投资人退出所得 | L1: 累计投入 | M1: 利润 | N1: MOIC | O1: 简化IRR | P1: XIRR
A2: 3 | B2: 7 | C2: ='经营预测'!B4 | D2: =B2*C2 | E2: ='现金与利息'!H4 | F2: ='现金与利息'!J4 | G2: ='交易与融资假设'!B11 | H2: =D2*'交易与融资假设'!B10 | I2: =MAX(0,D2-E2+F2-G2-H2) | J2: ='Sources & Uses'!D5/('Sources & Uses'!D5+'交易与融资假设'!B8) | K2: =I2*J2 | L2: ='Sources & Uses'!D5+SUM('经营预测'!H$2:INDEX('经营预测'!H:H,A2+1)) | M2: =K2-L2+SUM('现金与利息'!M$2:INDEX('现金与利息'!M:M,A2+1)) | N2: =IFERROR((K2+SUM('现金与利息'!M$2:INDEX('现金与利息'!M:M,A2+1)))/L2,"") | O2: =IFERROR(N2^(1/A2)-1,"") | P2: =IFERROR(XIRR('投资人现金流'!C3:J3,'投资人现金流'!C2:J2),"")
A3: 3 | B3: 7.625 | C3: ='经营预测'!B4 | D3: =B3*C3 | E3: ='现金与利息'!H4 | F3: ='现金与利息'!J4 | G3: ='交易与融资假设'!B11 | H3: =D3*'交易与融资假设'!B10 | I3: =MAX(0,D3-E3+F3-G3-H3) | J3: ='Sources & Uses'!D5/('Sources & Uses'!D5+'交易与融资假设'!B8) | K3: =I3*J3 | L3: ='Sources & Uses'!D5+SUM('经营预测'!H$2:INDEX('经营预测'!H:H,A3+1)) | M3: =K3-L3+SUM('现金与利息'!M$2:INDEX('现金与利息'!M:M,A3+1)) | N3: =IFERROR((K3+SUM('现金与利息'!M$2:INDEX('现金与利息'!M:M,A3+1)))/L3,"") | O3: =IFERROR(N3^(1/A3)-1,"") | P3: =IFERROR(XIRR('投资人现金流'!C5:J5,'投资人现金流'!C4:J4),"")
A4: 3 | B4: 8.5 | C4: ='经营预测'!B4 | D4: =B4*C4 | E4: ='现金与利息'!H4 | F4: ='现金与利息'!J4 | G4: ='交易与融资假设'!B11 | H4: =D4*'交易与融资假设'!B10 | I4: =MAX(0,D4-E4+F4-G4-H4) | J4: ='Sources & Uses'!D5/('Sources & Uses'!D5+'交易与融资假设'!B8) | K4: =I4*J4 | L4: ='Sources & Uses'!D5+SUM('经营预测'!H$2:INDEX('经营预测'!H:H,A4+1)) | M4: =K4-L4+SUM('现金与利息'!M$2:INDEX('现金与利息'!M:M,A4+1)) | N4: =IFERROR((K4+SUM('现金与利息'!M$2:INDEX('现金与利息'!M:M,A4+1)))/L4,"") | O4: =IFERROR(N4^(1/A4)-1,"") | P4: =IFERROR(XIRR('投资人现金流'!C7:J7,'投资人现金流'!C6:J6),"")
A5: 4 | B5: 7 | C5: ='经营预测'!B5 | D5: =B5*C5 | E5: ='现金与利息'!H5 | F5: ='现金与利息'!J5 | G5: ='交易与融资假设'!B11 | H5: =D5*'交易与融资假设'!B10 | I5: =MAX(0,D5-E5+F5-G5-H5) | J5: ='Sources & Uses'!D5/('Sources & Uses'!D5+'交易与融资假设'!B8) | K5: =I5*J5 | L5: ='Sources & Uses'!D5+SUM('经营预测'!H$2:INDEX('经营预测'!H:H,A5+1)) | M5: =K5-L5+SUM('现金与利息'!M$2:INDEX('现金与利息'!M:M,A5+1)) | N5: =IFERROR((K5+SUM('现金与利息'!M$2:INDEX('现金与利息'!M:M,A5+1)))/L5,"") | O5: =IFERROR(N5^(1/A5)-1,"") | P5: =IFERROR(XIRR('投资人现金流'!C9:J9,'投资人现金流'!C8:J8),"")
A6: 4 | B6: 7.625 | C6: ='经营预测'!B5 | D6: =B6*C6 | E6: ='现金与利息'!H5 | F6: ='现金与利息'!J5 | G6: ='交易与融资假设'!B11 | H6: =D6*'交易与融资假设'!B10 | I6: =MAX(0,D6-E6+F6-G6-H6) | J6: ='Sources & Uses'!D5/('Sources & Uses'!D5+'交易与融资假设'!B8) | K6: =I6*J6 | L6: ='Sources & Uses'!D5+SUM('经营预测'!H$2:INDEX('经营预测'!H:H,A6+1)) | M6: =K6-L6+SUM('现金与利息'!M$2:INDEX('现金与利息'!M:M,A6+1)) | N6: =IFERROR((K6+SUM('现金与利息'!M$2:INDEX('现金与利息'!M:M,A6+1)))/L6,"") | O6: =IFERROR(N6^(1/A6)-1,"") | P6: =IFERROR(XIRR('投资人现金流'!C11:J11,'投资人现金流'!C10:J10),"")
A7: 4 | B7: 8.5 | C7: ='经营预测'!B5 | D7: =B7*C7 | E7: ='现金与利息'!H5 | F7: ='现金与利息'!J5 | G7: ='交易与融资假设'!B11 | H7: =D7*'交易与融资假设'!B10 | I7: =MAX(0,D7-E7+F7-G7-H7) | J7: ='Sources & Uses'!D5/('Sources & Uses'!D5+'交易与融资假设'!B8) | K7: =I7*J7 | L7: ='Sources & Uses'!D5+SUM('经营预测'!H$2:INDEX('经营预测'!H:H,A7+1)) | M7: =K7-L7+SUM('现金与利息'!M$2:INDEX('现金与利息'!M:M,A7+1)) | N7: =IFERROR((K7+SUM('现金与利息'!M$2:INDEX('现金与利息'!M:M,A7+1)))/L7,"") | O7: =IFERROR(N7^(1/A7)-1,"") | P7: =IFERROR(XIRR('投资人现金流'!C13:J13,'投资人现金流'!C12:J12),"")
A8: 5 | B8: 7 | C8: ='经营预测'!B6 | D8: =B8*C8 | E8: ='现金与利息'!H6 | F8: ='现金与利息'!J6 | G8: ='交易与融资假设'!B11 | H8: =D8*'交易与融资假设'!B10 | I8: =MAX(0,D8-E8+F8-G8-H8) | J8: ='Sources & Uses'!D5/('Sources & Uses'!D5+'交易与融资假设'!B8) | K8: =I8*J8 | L8: ='Sources & Uses'!D5+SUM('经营预测'!H$2:INDEX('经营预测'!H:H,A8+1)) | M8: =K8-L8+SUM('现金与利息'!M$2:INDEX('现金与利息'!M:M,A8+1)) | N8: =IFERROR((K8+SUM('现金与利息'!M$2:INDEX('现金与利息'!M:M,A8+1)))/L8,"") | O8: =IFERROR(N8^(1/A8)-1,"") | P8: =IFERROR(XIRR('投资人现金流'!C15:J15,'投资人现金流'!C14:J14),"")
A9: 5 | B9: 7.625 | C9: ='经营预测'!B6 | D9: =B9*C9 | E9: ='现金与利息'!H6 | F9: ='现金与利息'!J6 | G9: ='交易与融资假设'!B11 | H9: =D9*'交易与融资假设'!B10 | I9: =MAX(0,D9-E9+F9-G9-H9) | J9: ='Sources & Uses'!D5/('Sources & Uses'!D5+'交易与融资假设'!B8) | K9: =I9*J9 | L9: ='Sources & Uses'!D5+SUM('经营预测'!H$2:INDEX('经营预测'!H:H,A9+1)) | M9: =K9-L9+SUM('现金与利息'!M$2:INDEX('现金与利息'!M:M,A9+1)) | N9: =IFERROR((K9+SUM('现金与利息'!M$2:INDEX('现金与利息'!M:M,A9+1)))/L9,"") | O9: =IFERROR(N9^(1/A9)-1,"") | P9: =IFERROR(XIRR('投资人现金流'!C17:J17,'投资人现金流'!C16:J16),"")
A10: 5 | B10: 8.5 | C10: ='经营预测'!B6 | D10: =B10*C10 | E10: ='现金与利息'!H6 | F10: ='现金与利息'!J6 | G10: ='交易与融资假设'!B11 | H10: =D10*'交易与融资假设'!B10 | I10: =MAX(0,D10-E10+F10-G10-H10) | J10: ='Sources & Uses'!D5/('Sources & Uses'!D5+'交易与融资假设'!B8) | K10: =I10*J10 | L10: ='Sources & Uses'!D5+SUM('经营预测'!H$2:INDEX('经营预测'!H:H,A10+1)) | M10: =K10-L10+SUM('现金与利息'!M$2:INDEX('现金与利息'!M:M,A10+1)) | N10: =IFERROR((K10+SUM('现金与利息'!M$2:INDEX('现金与利息'!M:M,A10+1)))/L10,"") | O10: =IFERROR(N10^(1/A10)-1,"") | P10: =IFERROR(XIRR('投资人现金流'!C19:J19,'投资人现金流'!C18:J18),"")
A11: 6 | B11: 7 | C11: ='经营预测'!B7 | D11: =B11*C11 | E11: ='现金与利息'!H7 | F11: ='现金与利息'!J7 | G11: ='交易与融资假设'!B11 | H11: =D11*'交易与融资假设'!B10 | I11: =MAX(0,D11-E11+F11-G11-H11) | J11: ='Sources & Uses'!D5/('Sources & Uses'!D5+'交易与融资假设'!B8) | K11: =I11*J11 | L11: ='Sources & Uses'!D5+SUM('经营预测'!H$2:INDEX('经营预测'!H:H,A11+1)) | M11: =K11-L11+SUM('现金与利息'!M$2:INDEX('现金与利息'!M:M,A11+1)) | N11: =IFERROR((K11+SUM('现金与利息'!M$2:INDEX('现金与利息'!M:M,A11+1)))/L11,"") | O11: =IFERROR(N11^(1/A11)-1,"") | P11: =IFERROR(XIRR('投资人现金流'!C21:J21,'投资人现金流'!C20:J20),"")
A12: 6 | B12: 7.625 | C12: ='经营预测'!B7 | D12: =B12*C12 | E12: ='现金与利息'!H7 | F12: ='现金与利息'!J7 | G12: ='交易与融资假设'!B11 | H12: =D12*'交易与融资假设'!B10 | I12: =MAX(0,D12-E12+F12-G12-H12) | J12: ='Sources & Uses'!D5/('Sources & Uses'!D5+'交易与融资假设'!B8) | K12: =I12*J12 | L12: ='Sources & Uses'!D5+SUM('经营预测'!H$2:INDEX('经营预测'!H:H,A12+1)) | M12: =K12-L12+SUM('现金与利息'!M$2:INDEX('现金与利息'!M:M,A12+1)) | N12: =IFERROR((K12+SUM('现金与利息'!M$2:INDEX('现金与利息'!M:M,A12+1)))/L12,"") | O12: =IFERROR(N12^(1/A12)-1,"") | P12: =IFERROR(XIRR('投资人现金流'!C23:J23,'投资人现金流'!C22:J22),"")
A13: 6 | B13: 8.5 | C13: ='经营预测'!B7 | D13: =B13*C13 | E13: ='现金与利息'!H7 | F13: ='现金与利息'!J7 | G13: ='交易与融资假设'!B11 | H13: =D13*'交易与融资假设'!B10 | I13: =MAX(0,D13-E13+F13-G13-H13) | J13: ='Sources & Uses'!D5/('Sources & Uses'!D5+'交易与融资假设'!B8) | K13: =I13*J13 | L13: ='Sources & Uses'!D5+SUM('经营预测'!H$2:INDEX('经营预测'!H:H,A13+1)) | M13: =K13-L13+SUM('现金与利息'!M$2:INDEX('现金与利息'!M:M,A13+1)) | N13: =IFERROR((K13+SUM('现金与利息'!M$2:INDEX('现金与利息'!M:M,A13+1)))/L13,"") | O13: =IFERROR(N13^(1/A13)-1,"") | P13: =IFERROR(XIRR('投资人现金流'!C25:J25,'投资人现金流'!C24:J24),"")
A14: 7 | B14: 7 | C14: ='经营预测'!B8 | D14: =B14*C14 | E14: ='现金与利息'!H8 | F14: ='现金与利息'!J8 | G14: ='交易与融资假设'!B11 | H14: =D14*'交易与融资假设'!B10 | I14: =MAX(0,D14-E14+F14-G14-H14) | J14: ='Sources & Uses'!D5/('Sources & Uses'!D5+'交易与融资假设'!B8) | K14: =I14*J14 | L14: ='Sources & Uses'!D5+SUM('经营预测'!H$2:INDEX('经营预测'!H:H,A14+1)) | M14: =K14-L14+SUM('现金与利息'!M$2:INDEX('现金与利息'!M:M,A14+1)) | N14: =IFERROR((K14+SUM('现金与利息'!M$2:INDEX('现金与利息'!M:M,A14+1)))/L14,"") | O14: =IFERROR(N14^(1/A14)-1,"") | P14: =IFERROR(XIRR('投资人现金流'!C27:J27,'投资人现金流'!C26:J26),"")
A15: 7 | B15: 7.625 | C15: ='经营预测'!B8 | D15: =B15*C15 | E15: ='现金与利息'!H8 | F15: ='现金与利息'!J8 | G15: ='交易与融资假设'!B11 | H15: =D15*'交易与融资假设'!B10 | I15: =MAX(0,D15-E15+F15-G15-H15) | J15: ='Sources & Uses'!D5/('Sources & Uses'!D5+'交易与融资假设'!B8) | K15: =I15*J15 | L15: ='Sources & Uses'!D5+SUM('经营预测'!H$2:INDEX('经营预测'!H:H,A15+1)) | M15: =K15-L15+SUM('现金与利息'!M$2:INDEX('现金与利息'!M:M,A15+1)) | N15: =IFERROR((K15+SUM('现金与利息'!M$2:INDEX('现金与利息'!M:M,A15+1)))/L15,"") | O15: =IFERROR(N15^(1/A15)-1,"") | P15: =IFERROR(XIRR('投资人现金流'!C29:J29,'投资人现金流'!C28:J28),"")
A16: 7 | B16: 8.5 | C16: ='经营预测'!B8 | D16: =B16*C16 | E16: ='现金与利息'!H8 | F16: ='现金与利息'!J8 | G16: ='交易与融资假设'!B11 | H16: =D16*'交易与融资假设'!B10 | I16: =MAX(0,D16-E16+F16-G16-H16) | J16: ='Sources & Uses'!D5/('Sources & Uses'!D5+'交易与融资假设'!B8) | K16: =I16*J16 | L16: ='Sources & Uses'!D5+SUM('经营预测'!H$2:INDEX('经营预测'!H:H,A16+1)) | M16: =K16-L16+SUM('现金与利息'!M$2:INDEX('现金与利息'!M:M,A16+1)) | N16: =IFERROR((K16+SUM('现金与利息'!M$2:INDEX('现金与利息'!M:M,A16+1)))/L16,"") | O16: =IFERROR(N16^(1/A16)-1,"") | P16: =IFERROR(XIRR('投资人现金流'!C31:J31,'投资人现金流'!C30:J30),"")

Sheet 投资人现金流
A1: 退出情景 | B1: 行类型 | C1: 投入日 | D1: 第1年 | E1: 第2年 | F1: 第3年 | G1: 第4年 | H1: 第5年 | I1: 第6年 | J1: 第7年
A2: Y3-7.00x | B2: 日期 | C2: ='交易与融资假设'!B12 | D2: =DATE(YEAR('交易与融资假设'!B12)+1,MONTH('交易与融资假设'!B12),DAY('交易与融资假设'!B12)) | E2: =DATE(YEAR('交易与融资假设'!B12)+2,MONTH('交易与融资假设'!B12),DAY('交易与融资假设'!B12)) | F2: =DATE(YEAR('交易与融资假设'!B12)+3,MONTH('交易与融资假设'!B12),DAY('交易与融资假设'!B12)) | G2: =DATE(YEAR('交易与融资假设'!B12)+4,MONTH('交易与融资假设'!B12),DAY('交易与融资假设'!B12)) | H2: =DATE(YEAR('交易与融资假设'!B12)+5,MONTH('交易与融资假设'!B12),DAY('交易与融资假设'!B12)) | I2: =DATE(YEAR('交易与融资假设'!B12)+6,MONTH('交易与融资假设'!B12),DAY('交易与融资假设'!B12)) | J2: =DATE(YEAR('交易与融资假设'!B12)+7,MONTH('交易与融资假设'!B12),DAY('交易与融资假设'!B12))
A3: Y3-7.00x | B3: 现金流 | C3: =-'Sources & Uses'!D5 | D3: ='现金与利息'!M2-'经营预测'!H2 | E3: ='现金与利息'!M3-'经营预测'!H3 | F3: ='现金与利息'!M4-'经营预测'!H4+'退出回报'!K2 | G3: ='经营预测'!H5*0 | H3: ='经营预测'!H6*0 | I3: ='经营预测'!H7*0 | J3: ='经营预测'!H8*0
A4: Y3-7.62x | B4: 日期 | C4: ='交易与融资假设'!B12 | D4: =DATE(YEAR('交易与融资假设'!B12)+1,MONTH('交易与融资假设'!B12),DAY('交易与融资假设'!B12)) | E4: =DATE(YEAR('交易与融资假设'!B12)+2,MONTH('交易与融资假设'!B12),DAY('交易与融资假设'!B12)) | F4: =DATE(YEAR('交易与融资假设'!B12)+3,MONTH('交易与融资假设'!B12),DAY('交易与融资假设'!B12)) | G4: =DATE(YEAR('交易与融资假设'!B12)+4,MONTH('交易与融资假设'!B12),DAY('交易与融资假设'!B12)) | H4: =DATE(YEAR('交易与融资假设'!B12)+5,MONTH('交易与融资假设'!B12),DAY('交易与融资假设'!B12)) | I4: =DATE(YEAR('交易与融资假设'!B12)+6,MONTH('交易与融资假设'!B12),DAY('交易与融资假设'!B12)) | J4: =DATE(YEAR('交易与融资假设'!B12)+7,MONTH('交易与融资假设'!B12),DAY('交易与融资假设'!B12))
A5: Y3-7.62x | B5: 现金流 | C5: =-'Sources & Uses'!D5 | D5: ='现金与利息'!M2-'经营预测'!H2 | E5: ='现金与利息'!M3-'经营预测'!H3 | F5: ='现金与利息'!M4-'经营预测'!H4+'退出回报'!K3 | G5: ='经营预测'!H5*0 | H5: ='经营预测'!H6*0 | I5: ='经营预测'!H7*0 | J5: ='经营预测'!H8*0
A6: Y3-8.50x | B6: 日期 | C6: ='交易与融资假设'!B12 | D6: =DATE(YEAR('交易与融资假设'!B12)+1,MONTH('交易与融资假设'!B12),DAY('交易与融资假设'!B12)) | E6: =DATE(YEAR('交易与融资假设'!B12)+2,MONTH('交易与融资假设'!B12),DAY('交易与融资假设'!B12)) | F6: =DATE(YEAR('交易与融资假设'!B12)+3,MONTH('交易与融资假设'!B12),DAY('交易与融资假设'!B12)) | G6: =DATE(YEAR('交易与融资假设'!B12)+4,MONTH('交易与融资假设'!B12),DAY('交易与融资假设'!B12)) | H6: =DATE(YEAR('交易与融资假设'!B12)+5,MONTH('交易与融资假设'!B12),DAY('交易与融资假设'!B12)) | I6: =DATE(YEAR('交易与融资假设'!B12)+6,MONTH('交易与融资假设'!B12),DAY('交易与融资假设'!B12)) | J6: =DATE(YEAR('交易与融资假设'!B12)+7,MONTH('交易与融资假设'!B12),DAY('交易与融资假设'!B12))
A7: Y3-8.50x | B7: 现金流 | C7: =-'Sources & Uses'!D5 | D7: ='现金与利息'!M2-'经营预测'!H2 | E7: ='现金与利息'!M3-'经营预测'!H3 | F7: ='现金与利息'!M4-'经营预测'!H4+'退出回报'!K4 | G7: ='经营预测'!H5*0 | H7: ='经营预测'!H6*0 | I7: ='经营预测'!H7*0 | J7: ='经营预测'!H8*0
A8: Y4-7.00x | B8: 日期 | C8: ='交易与融资假设'!B12 | D8: =DATE(YEAR('交易与融资假设'!B12)+1,MONTH('交易与融资假设'!B12),DAY('交易与融资假设'!B12)) | E8: =DATE(YEAR('交易与融资假设'!B12)+2,MONTH('交易与融资假设'!B12),DAY('交易与融资假设'!B12)) | F8: =DATE(YEAR('交易与融资假设'!B12)+3,MONTH('交易与融资假设'!B12),DAY('交易与融资假设'!B12)) | G8: =DATE(YEAR('交易与融资假设'!B12)+4,MONTH('交易与融资假设'!B12),DAY('交易与融资假设'!B12)) | H8: =DATE(YEAR('交易与融资假设'!B12)+5,MONTH('交易与融资假设'!B12),DAY('交易与融资假设'!B12)) | I8: =DATE(YEAR('交易与融资假设'!B12)+6,MONTH('交易与融资假设'!B12),DAY('交易与融资假设'!B12)) | J8: =DATE(YEAR('交易与融资假设'!B12)+7,MONTH('交易与融资假设'!B12),DAY('交易与融资假设'!B12))
A9: Y4-7.00x | B9: 现金流 | C9: =-'Sources & Uses'!D5 | D9: ='现金与利息'!M2-'经营预测'!H2 | E9: ='现金与利息'!M3-'经营预测'!H3 | F9: ='现金与利息'!M4-'经营预测'!H4 | G9: ='现金与利息'!M5-'经营预测'!H5+'退出回报'!K5 | H9: ='经营预测'!H6*0 | I9: ='经营预测'!H7*0 | J9: ='经营预测'!H8*0
A10: Y4-7.62x | B10: 日期 | C10: ='交易与融资假设'!B12 | D10: =DATE(YEAR('交易与融资假设'!B12)+1,MONTH('交易与融资假设'!B12),DAY('交易与融资假设'!B12)) | E10: =DATE(YEAR('交易与融资假设'!B12)+2,MONTH('交易与融资假设'!B12),DAY('交易与融资假设'!B12)) | F10: =DATE(YEAR('交易与融资假设'!B12)+3,MONTH('交易与融资假设'!B12),DAY('交易与融资假设'!B12)) | G10: =DATE(YEAR('交易与融资假设'!B12)+4,MONTH('交易与融资假设'!B12),DAY('交易与融资假设'!B12)) | H10: =DATE(YEAR('交易与融资假设'!B12)+5,MONTH('交易与融资假设'!B12),DAY('交易与融资假设'!B12)) | I10: =DATE(YEAR('交易与融资假设'!B12)+6,MONTH('交易与融资假设'!B12),DAY('交易与融资假设'!B12)) | J10: =DATE(YEAR('交易与融资假设'!B12)+7,MONTH('交易与融资假设'!B12),DAY('交易与融资假设'!B12))
A11: Y4-7.62x | B11: 现金流 | C11: =-'Sources & Uses'!D5 | D11: ='现金与利息'!M2-'经营预测'!H2 | E11: ='现金与利息'!M3-'经营预测'!H3 | F11: ='现金与利息'!M4-'经营预测'!H4 | G11: ='现金与利息'!M5-'经营预测'!H5+'退出回报'!K6 | H11: ='经营预测'!H6*0 | I11: ='经营预测'!H7*0 | J11: ='经营预测'!H8*0
A12: Y4-8.50x | B12: 日期 | C12: ='交易与融资假设'!B12 | D12: =DATE(YEAR('交易与融资假设'!B12)+1,MONTH('交易与融资假设'!B12),DAY('交易与融资假设'!B12)) | E12: =DATE(YEAR('交易与融资假设'!B12)+2,MONTH('交易与融资假设'!B12),DAY('交易与融资假设'!B12)) | F12: =DATE(YEAR('交易与融资假设'!B12)+3,MONTH('交易与融资假设'!B12),DAY('交易与融资假设'!B12)) | G12: =DATE(YEAR('交易与融资假设'!B12)+4,MONTH('交易与融资假设'!B12),DAY('交易与融资假设'!B12)) | H12: =DATE(YEAR('交易与融资假设'!B12)+5,MONTH('交易与融资假设'!B12),DAY('交易与融资假设'!B12)) | I12: =DATE(YEAR('交易与融资假设'!B12)+6,MONTH('交易与融资假设'!B12),DAY('交易与融资假设'!B12)) | J12: =DATE(YEAR('交易与融资假设'!B12)+7,MONTH('交易与融资假设'!B12),DAY('交易与融资假设'!B12))
A13: Y4-8.50x | B13: 现金流 | C13: =-'Sources & Uses'!D5 | D13: ='现金与利息'!M2-'经营预测'!H2 | E13: ='现金与利息'!M3-'经营预测'!H3 | F13: ='现金与利息'!M4-'经营预测'!H4 | G13: ='现金与利息'!M5-'经营预测'!H5+'退出回报'!K7 | H13: ='经营预测'!H6*0 | I13: ='经营预测'!H7*0 | J13: ='经营预测'!H8*0
A14: Y5-7.00x | B14: 日期 | C14: ='交易与融资假设'!B12 | D14: =DATE(YEAR('交易与融资假设'!B12)+1,MONTH('交易与融资假设'!B12),DAY('交易与融资假设'!B12)) | E14: =DATE(YEAR('交易与融资假设'!B12)+2,MONTH('交易与融资假设'!B12),DAY('交易与融资假设'!B12)) | F14: =DATE(YEAR('交易与融资假设'!B12)+3,MONTH('交易与融资假设'!B12),DAY('交易与融资假设'!B12)) | G14: =DATE(YEAR('交易与融资假设'!B12)+4,MONTH('交易与融资假设'!B12),DAY('交易与融资假设'!B12)) | H14: =DATE(YEAR('交易与融资假设'!B12)+5,MONTH('交易与融资假设'!B12),DAY('交易与融资假设'!B12)) | I14: =DATE(YEAR('交易与融资假设'!B12)+6,MONTH('交易与融资假设'!B12),DAY('交易与融资假设'!B12)) | J14: =DATE(YEAR('交易与融资假设'!B12)+7,MONTH('交易与融资假设'!B12),DAY('交易与融资假设'!B12))
A15: Y5-7.00x | B15: 现金流 | C15: =-'Sources & Uses'!D5 | D15: ='现金与利息'!M2-'经营预测'!H2 | E15: ='现金与利息'!M3-'经营预测'!H3 | F15: ='现金与利息'!M4-'经营预测'!H4 | G15: ='现金与利息'!M5-'经营预测'!H5 | H15: ='现金与利息'!M6-'经营预测'!H6+'退出回报'!K8 | I15: ='经营预测'!H7*0 | J15: ='经营预测'!H8*0
A16: Y5-7.62x | B16: 日期 | C16: ='交易与融资假设'!B12 | D16: =DATE(YEAR('交易与融资假设'!B12)+1,MONTH('交易与融资假设'!B12),DAY('交易与融资假设'!B12)) | E16: =DATE(YEAR('交易与融资假设'!B12)+2,MONTH('交易与融资假设'!B12),DAY('交易与融资假设'!B12)) | F16: =DATE(YEAR('交易与融资假设'!B12)+3,MONTH('交易与融资假设'!B12),DAY('交易与融资假设'!B12)) | G16: =DATE(YEAR('交易与融资假设'!B12)+4,MONTH('交易与融资假设'!B12),DAY('交易与融资假设'!B12)) | H16: =DATE(YEAR('交易与融资假设'!B12)+5,MONTH('交易与融资假设'!B12),DAY('交易与融资假设'!B12)) | I16: =DATE(YEAR('交易与融资假设'!B12)+6,MONTH('交易与融资假设'!B12),DAY('交易与融资假设'!B12)) | J16: =DATE(YEAR('交易与融资假设'!B12)+7,MONTH('交易与融资假设'!B12),DAY('交易与融资假设'!B12))
A17: Y5-7.62x | B17: 现金流 | C17: =-'Sources & Uses'!D5 | D17: ='现金与利息'!M2-'经营预测'!H2 | E17: ='现金与利息'!M3-'经营预测'!H3 | F17: ='现金与利息'!M4-'经营预测'!H4 | G17: ='现金与利息'!M5-'经营预测'!H5 | H17: ='现金与利息'!M6-'经营预测'!H6+'退出回报'!K9 | I17: ='经营预测'!H7*0 | J17: ='经营预测'!H8*0
A18: Y5-8.50x | B18: 日期 | C18: ='交易与融资假设'!B12 | D18: =DATE(YEAR('交易与融资假设'!B12)+1,MONTH('交易与融资假设'!B12),DAY('交易与融资假设'!B12)) | E18: =DATE(YEAR('交易与融资假设'!B12)+2,MONTH('交易与融资假设'!B12),DAY('交易与融资假设'!B12)) | F18: =DATE(YEAR('交易与融资假设'!B12)+3,MONTH('交易与融资假设'!B12),DAY('交易与融资假设'!B12)) | G18: =DATE(YEAR('交易与融资假设'!B12)+4,MONTH('交易与融资假设'!B12),DAY('交易与融资假设'!B12)) | H18: =DATE(YEAR('交易与融资假设'!B12)+5,MONTH('交易与融资假设'!B12),DAY('交易与融资假设'!B12)) | I18: =DATE(YEAR('交易与融资假设'!B12)+6,MONTH('交易与融资假设'!B12),DAY('交易与融资假设'!B12)) | J18: =DATE(YEAR('交易与融资假设'!B12)+7,MONTH('交易与融资假设'!B12),DAY('交易与融资假设'!B12))
A19: Y5-8.50x | B19: 现金流 | C19: =-'Sources & Uses'!D5 | D19: ='现金与利息'!M2-'经营预测'!H2 | E19: ='现金与利息'!M3-'经营预测'!H3 | F19: ='现金与利息'!M4-'经营预测'!H4 | G19: ='现金与利息'!M5-'经营预测'!H5 | H19: ='现金与利息'!M6-'经营预测'!H6+'退出回报'!K10 | I19: ='经营预测'!H7*0 | J19: ='经营预测'!H8*0
A20: Y6-7.00x | B20: 日期 | C20: ='交易与融资假设'!B12 | D20: =DATE(YEAR('交易与融资假设'!B12)+1,MONTH('交易与融资假设'!B12),DAY('交易与融资假设'!B12)) | E20: =DATE(YEAR('交易与融资假设'!B12)+2,MONTH('交易与融资假设'!B12),DAY('交易与融资假设'!B12)) | F20: =DATE(YEAR('交易与融资假设'!B12)+3,MONTH('交易与融资假设'!B12),DAY('交易与融资假设'!B12)) | G20: =DATE(YEAR('交易与融资假设'!B12)+4,MONTH('交易与融资假设'!B12),DAY('交易与融资假设'!B12)) | H20: =DATE(YEAR('交易与融资假设'!B12)+5,MONTH('交易与融资假设'!B12),DAY('交易与融资假设'!B12)) | I20: =DATE(YEAR('交易与融资假设'!B12)+6,MONTH('交易与融资假设'!B12),DAY('交易与融资假设'!B12)) | J20: =DATE(YEAR('交易与融资假设'!B12)+7,MONTH('交易与融资假设'!B12),DAY('交易与融资假设'!B12))
A21: Y6-7.00x | B21: 现金流 | C21: =-'Sources & Uses'!D5 | D21: ='现金与利息'!M2-'经营预测'!H2 | E21: ='现金与利息'!M3-'经营预测'!H3 | F21: ='现金与利息'!M4-'经营预测'!H4 | G21: ='现金与利息'!M5-'经营预测'!H5 | H21: ='现金与利息'!M6-'经营预测'!H6 | I21: ='现金与利息'!M7-'经营预测'!H7+'退出回报'!K11 | J21: ='经营预测'!H8*0
A22: Y6-7.62x | B22: 日期 | C22: ='交易与融资假设'!B12 | D22: =DATE(YEAR('交易与融资假设'!B12)+1,MONTH('交易与融资假设'!B12),DAY('交易与融资假设'!B12)) | E22: =DATE(YEAR('交易与融资假设'!B12)+2,MONTH('交易与融资假设'!B12),DAY('交易与融资假设'!B12)) | F22: =DATE(YEAR('交易与融资假设'!B12)+3,MONTH('交易与融资假设'!B12),DAY('交易与融资假设'!B12)) | G22: =DATE(YEAR('交易与融资假设'!B12)+4,MONTH('交易与融资假设'!B12),DAY('交易与融资假设'!B12)) | H22: =DATE(YEAR('交易与融资假设'!B12)+5,MONTH('交易与融资假设'!B12),DAY('交易与融资假设'!B12)) | I22: =DATE(YEAR('交易与融资假设'!B12)+6,MONTH('交易与融资假设'!B12),DAY('交易与融资假设'!B12)) | J22: =DATE(YEAR('交易与融资假设'!B12)+7,MONTH('交易与融资假设'!B12),DAY('交易与融资假设'!B12))
A23: Y6-7.62x | B23: 现金流 | C23: =-'Sources & Uses'!D5 | D23: ='现金与利息'!M2-'经营预测'!H2 | E23: ='现金与利息'!M3-'经营预测'!H3 | F23: ='现金与利息'!M4-'经营预测'!H4 | G23: ='现金与利息'!M5-'经营预测'!H5 | H23: ='现金与利息'!M6-'经营预测'!H6 | I23: ='现金与利息'!M7-'经营预测'!H7+'退出回报'!K12 | J23: ='经营预测'!H8*0
A24: Y6-8.50x | B24: 日期 | C24: ='交易与融资假设'!B12 | D24: =DATE(YEAR('交易与融资假设'!B12)+1,MONTH('交易与融资假设'!B12),DAY('交易与融资假设'!B12)) | E24: =DATE(YEAR('交易与融资假设'!B12)+2,MONTH('交易与融资假设'!B12),DAY('交易与融资假设'!B12)) | F24: =DATE(YEAR('交易与融资假设'!B12)+3,MONTH('交易与融资假设'!B12),DAY('交易与融资假设'!B12)) | G24: =DATE(YEAR('交易与融资假设'!B12)+4,MONTH('交易与融资假设'!B12),DAY('交易与融资假设'!B12)) | H24: =DATE(YEAR('交易与融资假设'!B12)+5,MONTH('交易与融资假设'!B12),DAY('交易与融资假设'!B12)) | I24: =DATE(YEAR('交易与融资假设'!B12)+6,MONTH('交易与融资假设'!B12),DAY('交易与融资假设'!B12)) | J24: =DATE(YEAR('交易与融资假设'!B12)+7,MONTH('交易与融资假设'!B12),DAY('交易与融资假设'!B12))
A25: Y6-8.50x | B25: 现金流 | C25: =-'Sources & Uses'!D5 | D25: ='现金与利息'!M2-'经营预测'!H2 | E25: ='现金与利息'!M3-'经营预测'!H3 | F25: ='现金与利息'!M4-'经营预测'!H4 | G25: ='现金与利息'!M5-'经营预测'!H5 | H25: ='现金与利息'!M6-'经营预测'!H6 | I25: ='现金与利息'!M7-'经营预测'!H7+'退出回报'!K13 | J25: ='经营预测'!H8*0
A26: Y7-7.00x | B26: 日期 | C26: ='交易与融资假设'!B12 | D26: =DATE(YEAR('交易与融资假设'!B12)+1,MONTH('交易与融资假设'!B12),DAY('交易与融资假设'!B12)) | E26: =DATE(YEAR('交易与融资假设'!B12)+2,MONTH('交易与融资假设'!B12),DAY('交易与融资假设'!B12)) | F26: =DATE(YEAR('交易与融资假设'!B12)+3,MONTH('交易与融资假设'!B12),DAY('交易与融资假设'!B12)) | G26: =DATE(YEAR('交易与融资假设'!B12)+4,MONTH('交易与融资假设'!B12),DAY('交易与融资假设'!B12)) | H26: =DATE(YEAR('交易与融资假设'!B12)+5,MONTH('交易与融资假设'!B12),DAY('交易与融资假设'!B12)) | I26: =DATE(YEAR('交易与融资假设'!B12)+6,MONTH('交易与融资假设'!B12),DAY('交易与融资假设'!B12)) | J26: =DATE(YEAR('交易与融资假设'!B12)+7,MONTH('交易与融资假设'!B12),DAY('交易与融资假设'!B12))
A27: Y7-7.00x | B27: 现金流 | C27: =-'Sources & Uses'!D5 | D27: ='现金与利息'!M2-'经营预测'!H2 | E27: ='现金与利息'!M3-'经营预测'!H3 | F27: ='现金与利息'!M4-'经营预测'!H4 | G27: ='现金与利息'!M5-'经营预测'!H5 | H27: ='现金与利息'!M6-'经营预测'!H6 | I27: ='现金与利息'!M7-'经营预测'!H7 | J27: ='现金与利息'!M8-'经营预测'!H8+'退出回报'!K14
A28: Y7-7.62x | B28: 日期 | C28: ='交易与融资假设'!B12 | D28: =DATE(YEAR('交易与融资假设'!B12)+1,MONTH('交易与融资假设'!B12),DAY('交易与融资假设'!B12)) | E28: =DATE(YEAR('交易与融资假设'!B12)+2,MONTH('交易与融资假设'!B12),DAY('交易与融资假设'!B12)) | F28: =DATE(YEAR('交易与融资假设'!B12)+3,MONTH('交易与融资假设'!B12),DAY('交易与融资假设'!B12)) | G28: =DATE(YEAR('交易与融资假设'!B12)+4,MONTH('交易与融资假设'!B12),DAY('交易与融资假设'!B12)) | H28: =DATE(YEAR('交易与融资假设'!B12)+5,MONTH('交易与融资假设'!B12),DAY('交易与融资假设'!B12)) | I28: =DATE(YEAR('交易与融资假设'!B12)+6,MONTH('交易与融资假设'!B12),DAY('交易与融资假设'!B12)) | J28: =DATE(YEAR('交易与融资假设'!B12)+7,MONTH('交易与融资假设'!B12),DAY('交易与融资假设'!B12))
A29: Y7-7.62x | B29: 现金流 | C29: =-'Sources & Uses'!D5 | D29: ='现金与利息'!M2-'经营预测'!H2 | E29: ='现金与利息'!M3-'经营预测'!H3 | F29: ='现金与利息'!M4-'经营预测'!H4 | G29: ='现金与利息'!M5-'经营预测'!H5 | H29: ='现金与利息'!M6-'经营预测'!H6 | I29: ='现金与利息'!M7-'经营预测'!H7 | J29: ='现金与利息'!M8-'经营预测'!H8+'退出回报'!K15
A30: Y7-8.50x | B30: 日期 | C30: ='交易与融资假设'!B12 | D30: =DATE(YEAR('交易与融资假设'!B12)+1,MONTH('交易与融资假设'!B12),DAY('交易与融资假设'!B12)) | E30: =DATE(YEAR('交易与融资假设'!B12)+2,MONTH('交易与融资假设'!B12),DAY('交易与融资假设'!B12)) | F30: =DATE(YEAR('交易与融资假设'!B12)+3,MONTH('交易与融资假设'!B12),DAY('交易与融资假设'!B12)) | G30: =DATE(YEAR('交易与融资假设'!B12)+4,MONTH('交易与融资假设'!B12),DAY('交易与融资假设'!B12)) | H30: =DATE(YEAR('交易与融资假设'!B12)+5,MONTH('交易与融资假设'!B12),DAY('交易与融资假设'!B12)) | I30: =DATE(YEAR('交易与融资假设'!B12)+6,MONTH('交易与融资假设'!B12),DAY('交易与融资假设'!B12)) | J30: =DATE(YEAR('交易与融资假设'!B12)+7,MONTH('交易与融资假设'!B12),DAY('交易与融资假设'!B12))
A31: Y7-8.50x | B31: 现金流 | C31: =-'Sources & Uses'!D5 | D31: ='现金与利息'!M2-'经营预测'!H2 | E31: ='现金与利息'!M3-'经营预测'!H3 | F31: ='现金与利息'!M4-'经营预测'!H4 | G31: ='现金与利息'!M5-'经营预测'!H5 | H31: ='现金与利息'!M6-'经营预测'!H6 | I31: ='现金与利息'!M7-'经营预测'!H7 | J31: ='现金与利息'!M8-'经营预测'!H8+'退出回报'!K16

Sheet 回报归因
A1: 退出年 | B1: 退出倍数 | C1: 起始股权购买价 | D1: EBITDA增长贡献 | E1: 倍数变化贡献 | F1: 净债务偿还贡献 | G1: 债务类调整变化 | H1: 退出费用影响 | I1: 预期退出股权价值 | J1: 实际退出股权价值 | K1: 勾稽差异
A2: ='退出回报'!A2 | B2: ='退出回报'!B2 | C2: ='交易与融资假设'!B2 | D2: =('退出回报'!C2-'交易与融资假设'!B9)*'交易与融资假设'!B18 | E2: ='退出回报'!C2*('退出回报'!B2-'交易与融资假设'!B18) | F2: =('交易与融资假设'!B3-'交易与融资假设'!B13)-'现金与利息'!K4 | G2: =('交易与融资假设'!B14+'交易与融资假设'!B15+'交易与融资假设'!B16)-'退出回报'!G2 | H2: =-'退出回报'!H2 | I2: =SUM(C2:H2) | J2: ='退出回报'!I2 | K2: =J2-I2
A3: ='退出回报'!A3 | B3: ='退出回报'!B3 | C3: ='交易与融资假设'!B2 | D3: =('退出回报'!C3-'交易与融资假设'!B9)*'交易与融资假设'!B18 | E3: ='退出回报'!C3*('退出回报'!B3-'交易与融资假设'!B18) | F3: =('交易与融资假设'!B3-'交易与融资假设'!B13)-'现金与利息'!K4 | G3: =('交易与融资假设'!B14+'交易与融资假设'!B15+'交易与融资假设'!B16)-'退出回报'!G3 | H3: =-'退出回报'!H3 | I3: =SUM(C3:H3) | J3: ='退出回报'!I3 | K3: =J3-I3
A4: ='退出回报'!A4 | B4: ='退出回报'!B4 | C4: ='交易与融资假设'!B2 | D4: =('退出回报'!C4-'交易与融资假设'!B9)*'交易与融资假设'!B18 | E4: ='退出回报'!C4*('退出回报'!B4-'交易与融资假设'!B18) | F4: =('交易与融资假设'!B3-'交易与融资假设'!B13)-'现金与利息'!K4 | G4: =('交易与融资假设'!B14+'交易与融资假设'!B15+'交易与融资假设'!B16)-'退出回报'!G4 | H4: =-'退出回报'!H4 | I4: =SUM(C4:H4) | J4: ='退出回报'!I4 | K4: =J4-I4
A5: ='退出回报'!A5 | B5: ='退出回报'!B5 | C5: ='交易与融资假设'!B2 | D5: =('退出回报'!C5-'交易与融资假设'!B9)*'交易与融资假设'!B18 | E5: ='退出回报'!C5*('退出回报'!B5-'交易与融资假设'!B18) | F5: =('交易与融资假设'!B3-'交易与融资假设'!B13)-'现金与利息'!K5 | G5: =('交易与融资假设'!B14+'交易与融资假设'!B15+'交易与融资假设'!B16)-'退出回报'!G5 | H5: =-'退出回报'!H5 | I5: =SUM(C5:H5) | J5: ='退出回报'!I5 | K5: =J5-I5
A6: ='退出回报'!A6 | B6: ='退出回报'!B6 | C6: ='交易与融资假设'!B2 | D6: =('退出回报'!C6-'交易与融资假设'!B9)*'交易与融资假设'!B18 | E6: ='退出回报'!C6*('退出回报'!B6-'交易与融资假设'!B18) | F6: =('交易与融资假设'!B3-'交易与融资假设'!B13)-'现金与利息'!K5 | G6: =('交易与融资假设'!B14+'交易与融资假设'!B15+'交易与融资假设'!B16)-'退出回报'!G6 | H6: =-'退出回报'!H6 | I6: =SUM(C6:H6) | J6: ='退出回报'!I6 | K6: =J6-I6
A7: ='退出回报'!A7 | B7: ='退出回报'!B7 | C7: ='交易与融资假设'!B2 | D7: =('退出回报'!C7-'交易与融资假设'!B9)*'交易与融资假设'!B18 | E7: ='退出回报'!C7*('退出回报'!B7-'交易与融资假设'!B18) | F7: =('交易与融资假设'!B3-'交易与融资假设'!B13)-'现金与利息'!K5 | G7: =('交易与融资假设'!B14+'交易与融资假设'!B15+'交易与融资假设'!B16)-'退出回报'!G7 | H7: =-'退出回报'!H7 | I7: =SUM(C7:H7) | J7: ='退出回报'!I7 | K7: =J7-I7
A8: ='退出回报'!A8 | B8: ='退出回报'!B8 | C8: ='交易与融资假设'!B2 | D8: =('退出回报'!C8-'交易与融资假设'!B9)*'交易与融资假设'!B18 | E8: ='退出回报'!C8*('退出回报'!B8-'交易与融资假设'!B18) | F8: =('交易与融资假设'!B3-'交易与融资假设'!B13)-'现金与利息'!K6 | G8: =('交易与融资假设'!B14+'交易与融资假设'!B15+'交易与融资假设'!B16)-'退出回报'!G8 | H8: =-'退出回报'!H8 | I8: =SUM(C8:H8) | J8: ='退出回报'!I8 | K8: =J8-I8
A9: ='退出回报'!A9 | B9: ='退出回报'!B9 | C9: ='交易与融资假设'!B2 | D9: =('退出回报'!C9-'交易与融资假设'!B9)*'交易与融资假设'!B18 | E9: ='退出回报'!C9*('退出回报'!B9-'交易与融资假设'!B18) | F9: =('交易与融资假设'!B3-'交易与融资假设'!B13)-'现金与利息'!K6 | G9: =('交易与融资假设'!B14+'交易与融资假设'!B15+'交易与融资假设'!B16)-'退出回报'!G9 | H9: =-'退出回报'!H9 | I9: =SUM(C9:H9) | J9: ='退出回报'!I9 | K9: =J9-I9
A10: ='退出回报'!A10 | B10: ='退出回报'!B10 | C10: ='交易与融资假设'!B2 | D10: =('退出回报'!C10-'交易与融资假设'!B9)*'交易与融资假设'!B18 | E10: ='退出回报'!C10*('退出回报'!B10-'交易与融资假设'!B18) | F10: =('交易与融资假设'!B3-'交易与融资假设'!B13)-'现金与利息'!K6 | G10: =('交易与融资假设'!B14+'交易与融资假设'!B15+'交易与融资假设'!B16)-'退出回报'!G10 | H10: =-'退出回报'!H10 | I10: =SUM(C10:H10) | J10: ='退出回报'!I10 | K10: =J10-I10
A11: ='退出回报'!A11 | B11: ='退出回报'!B11 | C11: ='交易与融资假设'!B2 | D11: =('退出回报'!C11-'交易与融资假设'!B9)*'交易与融资假设'!B18 | E11: ='退出回报'!C11*('退出回报'!B11-'交易与融资假设'!B18) | F11: =('交易与融资假设'!B3-'交易与融资假设'!B13)-'现金与利息'!K7 | G11: =('交易与融资假设'!B14+'交易与融资假设'!B15+'交易与融资假设'!B16)-'退出回报'!G11 | H11: =-'退出回报'!H11 | I11: =SUM(C11:H11) | J11: ='退出回报'!I11 | K11: =J11-I11
A12: ='退出回报'!A12 | B12: ='退出回报'!B12 | C12: ='交易与融资假设'!B2 | D12: =('退出回报'!C12-'交易与融资假设'!B9)*'交易与融资假设'!B18 | E12: ='退出回报'!C12*('退出回报'!B12-'交易与融资假设'!B18) | F12: =('交易与融资假设'!B3-'交易与融资假设'!B13)-'现金与利息'!K7 | G12: =('交易与融资假设'!B14+'交易与融资假设'!B15+'交易与融资假设'!B16)-'退出回报'!G12 | H12: =-'退出回报'!H12 | I12: =SUM(C12:H12) | J12: ='退出回报'!I12 | K12: =J12-I12
A13: ='退出回报'!A13 | B13: ='退出回报'!B13 | C13: ='交易与融资假设'!B2 | D13: =('退出回报'!C13-'交易与融资假设'!B9)*'交易与融资假设'!B18 | E13: ='退出回报'!C13*('退出回报'!B13-'交易与融资假设'!B18) | F13: =('交易与融资假设'!B3-'交易与融资假设'!B13)-'现金与利息'!K7 | G13: =('交易与融资假设'!B14+'交易与融资假设'!B15+'交易与融资假设'!B16)-'退出回报'!G13 | H13: =-'退出回报'!H13 | I13: =SUM(C13:H13) | J13: ='退出回报'!I13 | K13: =J13-I13
A14: ='退出回报'!A14 | B14: ='退出回报'!B14 | C14: ='交易与融资假设'!B2 | D14: =('退出回报'!C14-'交易与融资假设'!B9)*'交易与融资假设'!B18 | E14: ='退出回报'!C14*('退出回报'!B14-'交易与融资假设'!B18) | F14: =('交易与融资假设'!B3-'交易与融资假设'!B13)-'现金与利息'!K8 | G14: =('交易与融资假设'!B14+'交易与融资假设'!B15+'交易与融资假设'!B16)-'退出回报'!G14 | H14: =-'退出回报'!H14 | I14: =SUM(C14:H14) | J14: ='退出回报'!I14 | K14: =J14-I14
A15: ='退出回报'!A15 | B15: ='退出回报'!B15 | C15: ='交易与融资假设'!B2 | D15: =('退出回报'!C15-'交易与融资假设'!B9)*'交易与融资假设'!B18 | E15: ='退出回报'!C15*('退出回报'!B15-'交易与融资假设'!B18) | F15: =('交易与融资假设'!B3-'交易与融资假设'!B13)-'现金与利息'!K8 | G15: =('交易与融资假设'!B14+'交易与融资假设'!B15+'交易与融资假设'!B16)-'退出回报'!G15 | H15: =-'退出回报'!H15 | I15: =SUM(C15:H15) | J15: ='退出回报'!I15 | K15: =J15-I15
A16: ='退出回报'!A16 | B16: ='退出回报'!B16 | C16: ='交易与融资假设'!B2 | D16: =('退出回报'!C16-'交易与融资假设'!B9)*'交易与融资假设'!B18 | E16: ='退出回报'!C16*('退出回报'!B16-'交易与融资假设'!B18) | F16: =('交易与融资假设'!B3-'交易与融资假设'!B13)-'现金与利息'!K8 | G16: =('交易与融资假设'!B14+'交易与融资假设'!B15+'交易与融资假设'!B16)-'退出回报'!G16 | H16: =-'退出回报'!H16 | I16: =SUM(C16:H16) | J16: ='退出回报'!I16 | K16: =J16-I16

Sheet 情景与敏感性
A1: 收购价因子/退出倍数 | B1: 6.1 | C1: 6.8625 | D1: 7.625 | E1: 8.3875 | F1: 9.15
A2: 0.8 | B2: =IFERROR((MAX(0,'退出回报'!C9*B1-'退出回报'!E9+'退出回报'!F9-'退出回报'!G9-'退出回报'!C9*B1*'交易与融资假设'!B10)*(('Sources & Uses'!D5+'交易与融资假设'!B2*($A2-1))/(('Sources & Uses'!D5+'交易与融资假设'!B2*($A2-1))+'交易与融资假设'!B8)))/(('Sources & Uses'!D5+'交易与融资假设'!B2*($A2-1))),"") | C2: =IFERROR((MAX(0,'退出回报'!C9*C1-'退出回报'!E9+'退出回报'!F9-'退出回报'!G9-'退出回报'!C9*C1*'交易与融资假设'!B10)*(('Sources & Uses'!D5+'交易与融资假设'!B2*($A2-1))/(('Sources & Uses'!D5+'交易与融资假设'!B2*($A2-1))+'交易与融资假设'!B8)))/(('Sources & Uses'!D5+'交易与融资假设'!B2*($A2-1))),"") | D2: =IFERROR((MAX(0,'退出回报'!C9*D1-'退出回报'!E9+'退出回报'!F9-'退出回报'!G9-'退出回报'!C9*D1*'交易与融资假设'!B10)*(('Sources & Uses'!D5+'交易与融资假设'!B2*($A2-1))/(('Sources & Uses'!D5+'交易与融资假设'!B2*($A2-1))+'交易与融资假设'!B8)))/(('Sources & Uses'!D5+'交易与融资假设'!B2*($A2-1))),"") | E2: =IFERROR((MAX(0,'退出回报'!C9*E1-'退出回报'!E9+'退出回报'!F9-'退出回报'!G9-'退出回报'!C9*E1*'交易与融资假设'!B10)*(('Sources & Uses'!D5+'交易与融资假设'!B2*($A2-1))/(('Sources & Uses'!D5+'交易与融资假设'!B2*($A2-1))+'交易与融资假设'!B8)))/(('Sources & Uses'!D5+'交易与融资假设'!B2*($A2-1))),"") | F2: =IFERROR((MAX(0,'退出回报'!C9*F1-'退出回报'!E9+'退出回报'!F9-'退出回报'!G9-'退出回报'!C9*F1*'交易与融资假设'!B10)*(('Sources & Uses'!D5+'交易与融资假设'!B2*($A2-1))/(('Sources & Uses'!D5+'交易与融资假设'!B2*($A2-1))+'交易与融资假设'!B8)))/(('Sources & Uses'!D5+'交易与融资假设'!B2*($A2-1))),"")
A3: 0.9 | B3: =IFERROR((MAX(0,'退出回报'!C9*B1-'退出回报'!E9+'退出回报'!F9-'退出回报'!G9-'退出回报'!C9*B1*'交易与融资假设'!B10)*(('Sources & Uses'!D5+'交易与融资假设'!B2*($A3-1))/(('Sources & Uses'!D5+'交易与融资假设'!B2*($A3-1))+'交易与融资假设'!B8)))/(('Sources & Uses'!D5+'交易与融资假设'!B2*($A3-1))),"") | C3: =IFERROR((MAX(0,'退出回报'!C9*C1-'退出回报'!E9+'退出回报'!F9-'退出回报'!G9-'退出回报'!C9*C1*'交易与融资假设'!B10)*(('Sources & Uses'!D5+'交易与融资假设'!B2*($A3-1))/(('Sources & Uses'!D5+'交易与融资假设'!B2*($A3-1))+'交易与融资假设'!B8)))/(('Sources & Uses'!D5+'交易与融资假设'!B2*($A3-1))),"") | D3: =IFERROR((MAX(0,'退出回报'!C9*D1-'退出回报'!E9+'退出回报'!F9-'退出回报'!G9-'退出回报'!C9*D1*'交易与融资假设'!B10)*(('Sources & Uses'!D5+'交易与融资假设'!B2*($A3-1))/(('Sources & Uses'!D5+'交易与融资假设'!B2*($A3-1))+'交易与融资假设'!B8)))/(('Sources & Uses'!D5+'交易与融资假设'!B2*($A3-1))),"") | E3: =IFERROR((MAX(0,'退出回报'!C9*E1-'退出回报'!E9+'退出回报'!F9-'退出回报'!G9-'退出回报'!C9*E1*'交易与融资假设'!B10)*(('Sources & Uses'!D5+'交易与融资假设'!B2*($A3-1))/(('Sources & Uses'!D5+'交易与融资假设'!B2*($A3-1))+'交易与融资假设'!B8)))/(('Sources & Uses'!D5+'交易与融资假设'!B2*($A3-1))),"") | F3: =IFERROR((MAX(0,'退出回报'!C9*F1-'退出回报'!E9+'退出回报'!F9-'退出回报'!G9-'退出回报'!C9*F1*'交易与融资假设'!B10)*(('Sources & Uses'!D5+'交易与融资假设'!B2*($A3-1))/(('Sources & Uses'!D5+'交易与融资假设'!B2*($A3-1))+'交易与融资假设'!B8)))/(('Sources & Uses'!D5+'交易与融资假设'!B2*($A3-1))),"")
A4: 1 | B4: =IFERROR((MAX(0,'退出回报'!C9*B1-'退出回报'!E9+'退出回报'!F9-'退出回报'!G9-'退出回报'!C9*B1*'交易与融资假设'!B10)*(('Sources & Uses'!D5+'交易与融资假设'!B2*($A4-1))/(('Sources & Uses'!D5+'交易与融资假设'!B2*($A4-1))+'交易与融资假设'!B8)))/(('Sources & Uses'!D5+'交易与融资假设'!B2*($A4-1))),"") | C4: =IFERROR((MAX(0,'退出回报'!C9*C1-'退出回报'!E9+'退出回报'!F9-'退出回报'!G9-'退出回报'!C9*C1*'交易与融资假设'!B10)*(('Sources & Uses'!D5+'交易与融资假设'!B2*($A4-1))/(('Sources & Uses'!D5+'交易与融资假设'!B2*($A4-1))+'交易与融资假设'!B8)))/(('Sources & Uses'!D5+'交易与融资假设'!B2*($A4-1))),"") | D4: =IFERROR((MAX(0,'退出回报'!C9*D1-'退出回报'!E9+'退出回报'!F9-'退出回报'!G9-'退出回报'!C9*D1*'交易与融资假设'!B10)*(('Sources & Uses'!D5+'交易与融资假设'!B2*($A4-1))/(('Sources & Uses'!D5+'交易与融资假设'!B2*($A4-1))+'交易与融资假设'!B8)))/(('Sources & Uses'!D5+'交易与融资假设'!B2*($A4-1))),"") | E4: =IFERROR((MAX(0,'退出回报'!C9*E1-'退出回报'!E9+'退出回报'!F9-'退出回报'!G9-'退出回报'!C9*E1*'交易与融资假设'!B10)*(('Sources & Uses'!D5+'交易与融资假设'!B2*($A4-1))/(('Sources & Uses'!D5+'交易与融资假设'!B2*($A4-1))+'交易与融资假设'!B8)))/(('Sources & Uses'!D5+'交易与融资假设'!B2*($A4-1))),"") | F4: =IFERROR((MAX(0,'退出回报'!C9*F1-'退出回报'!E9+'退出回报'!F9-'退出回报'!G9-'退出回报'!C9*F1*'交易与融资假设'!B10)*(('Sources & Uses'!D5+'交易与融资假设'!B2*($A4-1))/(('Sources & Uses'!D5+'交易与融资假设'!B2*($A4-1))+'交易与融资假设'!B8)))/(('Sources & Uses'!D5+'交易与融资假设'!B2*($A4-1))),"")
A5: 1.1 | B5: =IFERROR((MAX(0,'退出回报'!C9*B1-'退出回报'!E9+'退出回报'!F9-'退出回报'!G9-'退出回报'!C9*B1*'交易与融资假设'!B10)*(('Sources & Uses'!D5+'交易与融资假设'!B2*($A5-1))/(('Sources & Uses'!D5+'交易与融资假设'!B2*($A5-1))+'交易与融资假设'!B8)))/(('Sources & Uses'!D5+'交易与融资假设'!B2*($A5-1))),"") | C5: =IFERROR((MAX(0,'退出回报'!C9*C1-'退出回报'!E9+'退出回报'!F9-'退出回报'!G9-'退出回报'!C9*C1*'交易与融资假设'!B10)*(('Sources & Uses'!D5+'交易与融资假设'!B2*($A5-1))/(('Sources & Uses'!D5+'交易与融资假设'!B2*($A5-1))+'交易与融资假设'!B8)))/(('Sources & Uses'!D5+'交易与融资假设'!B2*($A5-1))),"") | D5: =IFERROR((MAX(0,'退出回报'!C9*D1-'退出回报'!E9+'退出回报'!F9-'退出回报'!G9-'退出回报'!C9*D1*'交易与融资假设'!B10)*(('Sources & Uses'!D5+'交易与融资假设'!B2*($A5-1))/(('Sources & Uses'!D5+'交易与融资假设'!B2*($A5-1))+'交易与融资假设'!B8)))/(('Sources & Uses'!D5+'交易与融资假设'!B2*($A5-1))),"") | E5: =IFERROR((MAX(0,'退出回报'!C9*E1-'退出回报'!E9+'退出回报'!F9-'退出回报'!G9-'退出回报'!C9*E1*'交易与融资假设'!B10)*(('Sources & Uses'!D5+'交易与融资假设'!B2*($A5-1))/(('Sources & Uses'!D5+'交易与融资假设'!B2*($A5-1))+'交易与融资假设'!B8)))/(('Sources & Uses'!D5+'交易与融资假设'!B2*($A5-1))),"") | F5: =IFERROR((MAX(0,'退出回报'!C9*F1-'退出回报'!E9+'退出回报'!F9-'退出回报'!G9-'退出回报'!C9*F1*'交易与融资假设'!B10)*(('Sources & Uses'!D5+'交易与融资假设'!B2*($A5-1))/(('Sources & Uses'!D5+'交易与融资假设'!B2*($A5-1))+'交易与融资假设'!B8)))/(('Sources & Uses'!D5+'交易与融资假设'!B2*($A5-1))),"")
A6: 1.2 | B6: =IFERROR((MAX(0,'退出回报'!C9*B1-'退出回报'!E9+'退出回报'!F9-'退出回报'!G9-'退出回报'!C9*B1*'交易与融资假设'!B10)*(('Sources & Uses'!D5+'交易与融资假设'!B2*($A6-1))/(('Sources & Uses'!D5+'交易与融资假设'!B2*($A6-1))+'交易与融资假设'!B8)))/(('Sources & Uses'!D5+'交易与融资假设'!B2*($A6-1))),"") | C6: =IFERROR((MAX(0,'退出回报'!C9*C1-'退出回报'!E9+'退出回报'!F9-'退出回报'!G9-'退出回报'!C9*C1*'交易与融资假设'!B10)*(('Sources & Uses'!D5+'交易与融资假设'!B2*($A6-1))/(('Sources & Uses'!D5+'交易与融资假设'!B2*($A6-1))+'交易与融资假设'!B8)))/(('Sources & Uses'!D5+'交易与融资假设'!B2*($A6-1))),"") | D6: =IFERROR((MAX(0,'退出回报'!C9*D1-'退出回报'!E9+'退出回报'!F9-'退出回报'!G9-'退出回报'!C9*D1*'交易与融资假设'!B10)*(('Sources & Uses'!D5+'交易与融资假设'!B2*($A6-1))/(('Sources & Uses'!D5+'交易与融资假设'!B2*($A6-1))+'交易与融资假设'!B8)))/(('Sources & Uses'!D5+'交易与融资假设'!B2*($A6-1))),"") | E6: =IFERROR((MAX(0,'退出回报'!C9*E1-'退出回报'!E9+'退出回报'!F9-'退出回报'!G9-'退出回报'!C9*E1*'交易与融资假设'!B10)*(('Sources & Uses'!D5+'交易与融资假设'!B2*($A6-1))/(('Sources & Uses'!D5+'交易与融资假设'!B2*($A6-1))+'交易与融资假设'!B8)))/(('Sources & Uses'!D5+'交易与融资假设'!B2*($A6-1))),"") | F6: =IFERROR((MAX(0,'退出回报'!C9*F1-'退出回报'!E9+'退出回报'!F9-'退出回报'!G9-'退出回报'!C9*F1*'交易与融资假设'!B10)*(('Sources & Uses'!D5+'交易与融资假设'!B2*($A6-1))/(('Sources & Uses'!D5+'交易与融资假设'!B2*($A6-1))+'交易与融资假设'!B8)))/(('Sources & Uses'!D5+'交易与融资假设'!B2*($A6-1))),"")
A8: 输出 | B8: 第5年MOIC；每个格子重新计算收购价、财务投资人股权和持股比例。

Sheet 目标回报反推
A1: 目标IRR | B1: 退出年 | C1: 退出倍数 | D1: 退出所得 | E1: 允许财务投资人股权 | F1: 最高股权购买价
A2: 0.2 | B2: 5 | C2: 7.625 | D2: ='退出回报'!K9 | E2: =D2/(1+A2)^B2 | F2: =E2+SUM('Sources & Uses'!D2:D4)-SUM('Sources & Uses'!B3:B8)
A3: 0.25 | B3: 5 | C3: 7.625 | D3: ='退出回报'!K9 | E3: =D3/(1+A3)^B3 | F3: =E3+SUM('Sources & Uses'!D2:D4)-SUM('Sources & Uses'!B3:B8)
A4: 0.3 | B4: 5 | C4: 7.625 | D4: ='退出回报'!K9 | E4: =D4/(1+A4)^B4 | F4: =E4+SUM('Sources & Uses'!D2:D4)-SUM('Sources & Uses'!B3:B8)

Sheet 假设依据
A1: 假设编号 | B1: 主题 | C1: 内容 | D1: 模型使用位置
A2: ASM-LBO-001 | B2: ebitda_growth | C2: 基准情景按5%年增长，仅用于结构测试 | D2: 交易、经营、债务或退出模型
A3: ASM-LBO-002 | B3: depreciation_amortization | C3: 未单独建模，现金税作为显式输入 | D3: 交易、经营、债务或退出模型
A4: ASM-LBO-003 | B4: depreciation_tax_shield | C4: 不另行计算，避免与现金税重复 | D4: 交易、经营、债务或退出模型
A5: ASM-LBO-004 | B5: capex | C5: 逐年显式输入 | D5: 交易、经营、债务或退出模型
A6: ASM-LBO-005 | B6: working_capital | C6: 逐年显式输入 | D6: 交易、经营、债务或退出模型
A7: ASM-LBO-006 | B7: cash_taxes | C7: 逐年显式输入 | D7: 交易、经营、债务或退出模型
A8: ASM-LBO-007 | B8: refinancing | C8: 到期债务不自动再融资，流动性缺口保留 | D8: 交易、经营、债务或退出模型

Sheet 历史数据与口径
A1: 项目 | B1: 数值 | C1: 期间/口径 | D1: 来源组
A2: 进入EBITDA | B2: ='交易与融资假设'!B9 | C2: 进入估值口径 | D2: SRC-DEMO
A3: 进入债务 | B3: ='交易与融资假设'!B3 | C3: 交易基准日需偿还债务 | D3: SRC-DEMO
A4: 收购现金 | B4: ='交易与融资假设'!B13 | C4: 交易可使用现金 | D4: SRC-DEMO
A5: 进入企业价值 | B5: ='交易与融资假设'!B17 | C5: 股权价值到企业价值桥 | D5: SRC-DEMO

Sheet 风险与失效条件
A1: 类型 | B1: 编号 | C1: 内容 | D1: 处理要求
A2: 失效条件 | B2: INV-001 | C2: EBITDA低于基准经营路径 | D2: 更新对应输入并完整重跑模型
A3: 失效条件 | B3: INV-002 | C3: 现金利率或再融资成本显著高于债务假设 | D3: 更新对应输入并完整重跑模型
A4: 失效条件 | B4: INV-003 | C4: 退出倍数低于敏感性下沿 | D4: 更新对应输入并完整重跑模型
A5: 警告 | B5: WRN-001 | C5: At least one exit multiple exceeds the entry multiple; do not use it as Base without evidence. | D5: 评估影响并在结论页披露
A6: 警告 | B6: WRN-002 | C6: No management_case supplied; add an operating improvement comparison when Base returns are impaired or near the equity cliff. | D6: 评估影响并在结论页披露

Sheet 数据来源
A1: 来源ID | B1: 标题 | C1: 日期 | D1: URL/定位 | E1: 备注
A2: SRC-DEMO | B2: 结构测试数据，不代表真实公司 | C2: 2026-07-16

Sheet 模型检查
A1: 检查项 | B1: 实际值 | C1: 期望值 | D1: 差异 | E1: 容差 | F1: 状态 | G1: 修复提示
A2: Sources & Uses平衡 | B2: ='Sources & Uses'!B10 | C2: 0 | D2: =B2-C2 | E2: 1e-06 | F2: =IF(ABS(D2)<=E2,"PASS","FAIL") | G2: 检查交易用途及资金来源
A3: 期末债务非负 | B3: =MIN('分层债务'!I2:I500) | C3: 0 | D3: =MIN(0,B3-C3) | E3: 0 | F3: =IF(B3>=C3,"PASS","FAIL") | G3: 检查摊还、现金扫款及循环额度提款
A4: 流动性检查 | B4: =COUNTIF('现金与利息'!L2:L100,"FAIL") | C4: 0 | D4: =B4-C4 | E4: 0 | F4: =IF(B4=0,"PASS","FAIL") | G4: 现金不足时需补充循环额度或股权
A5: 退出回报公式 | B5: =COUNT('退出回报'!N2:P16) | C5: 45 | D5: =B5-C5 | E5: 0 | F5: =IF(B5=C5,"PASS","FAIL") | G5: MOIC、IRR、XIRR均须由公式生成
A6: 回报归因勾稽 | B6: =MAX(ABS('回报归因'!K2:K16)) | C6: 0 | D6: =B6-C6 | E6: 1e-06 | F6: =IF(ABS(D6)<=E6,"PASS","FAIL") | G6: 检查EBITDA、倍数、净债务和费用贡献
A7: 敏感性公式数量 | B7: =COUNT('情景与敏感性'!B2:F6) | C7: 25 | D7: =B7-C7 | E7: 0 | F7: =IF(B7=C7,"PASS","FAIL") | G7: 25个敏感性格均须为公式
A8: 模型总体状态 | B8: =COUNTIF(F2:F7,"FAIL") | C8: 0 | D8: =B8-C8 | E8: 0 | F8: =IF(B8=0,"PASS","FAIL") | G8: 任一检查失败即阻断回报结论
